Workbook
Name Selected_County: 'County Profile, 2020-2024'!$B$78

Sheet data
B1: B01001 | C1: B01001 | D1: B01001 | E1: B01001 | F1: B01001 | G1: B01001 | H1: B01001 | I1: B01001 | J1: B01001 | K1: B01001 | L1: B01001 | M1: B01001 | N1: B01001 | O1: B01002 | P1: B11006 | Q1: B11006 | R1: B11006 | S1: B11007 | T1: B11007 | U1: B12002 | V1: B12002 | W1: B12002 | X1: B12002 | Y1: B12002 | Z1: B12002 | AA1: B12002 | AB1: B12002 | AC1: B12002 | AD1: B12002 | AE1: B12002 | AF1: B12002 | AG1: B12002 | AH1: B12002 | AI1: B12002 | AJ1: B12002 | AK1: B12002 | AL1: B12002 | AM1: B12002 | AN1: B12002 | AO1: B12002 | AP1: B12002 | AQ1: B12002 | AR1: B12002 | AS1: B12002 | AT1: B12002 | AU1: B12002 | AV1: B12002 | AW1: B12002 | AX1: B12002 | AY1: B12002 | AZ1: B12002 | BA1: B12002 | BB1: B18101 | BC1: B18101 | BD1: B18101 | BE1: B18101 | BF1: B18101 | BG1: B18101 | BH1: B18101 | BI1: B18101 | BJ1: B18101 | BK1: B09020 | BL1: B09020 | BM1: B09020 | BN1: B09020 | BO1: B09020 | BP1: B09020 | BQ1: B09020 | BR1: B09020 | BS1: B09020 | BT1: AEP | BU1: AEP | BV1: AEP | BW1: AEP | BX1: AEP | BY1: AEP | BZ1: AEP | CA1: AEP | CB1: AEP | CC1: AEP | CD1: AEP | CE1: AEP | CF1: AEP | CG1: AEP | CH1: AEP | CI1: AEP | CJ1: AEP | CK1: AEP | CL1: AEP | CM1: AEP | CN1: AEP | CO1: AEP | CP1: AEP | CQ1: AEP | CR1: B01001 | CS1: B01001 | CT1: B01001 | CU1: B01001 | CV1: AEP | CW1: AEP | CX1: AEP | CY1: AEP | CZ1: AEP | DA1: AEP | DB1: AEP | DC1: AEP | DD1: B15001 | DE1: B15001 | DF1: B15001 | DG1: B15001 | DH1: B15001 | DI1: B15001 | DJ1: B15001 | DK1: B15001 | DL1: B15001 | DM1: B15001 | DN1: B15001 | DO1: B15001 | DP1: B15001 | DQ1: B15001 | DR1: B15001 | DS1: B15001 | DT1: B15001 | DU1: B15001 | DV1: B15001 | DW1: B15001 | DX1: B15001 | DY1: B15001 | DZ1: B15001 | EA1: B15001 | EB1: B19037 | EC1: B19037 | ED1: B19037 | EE1: B19037 | EF1: B19037 | EG1: B19037 | EH1: B19037 | EI1: B19037 | EJ1: B19037 | EK1: B19037 | EL1: B19037 | EM1: B19037 | EN1: B19037 | EO1: B19049 | EP1: B19049 | EQ1: B19049 | ER1: B19049 | ES1: B19049 | ET1: B17001 | EU1: B17001 | EV1: B17001 | EW1: B17001 | EX1: B17001 | EY1: B17001 | EZ1: B17001 | FA1: B17001 | FB1: B17001 | FC1: B17024 | FD1: B17024 | FE1: B17024 | FF1: B17024 | FG1: B17024 | FH1: B17024 | FI1: B17024 | FJ1: B17024 | FK1: B17024 | FL1: B17024 | FM1: B17024 | FN1: B23001 | FO1: B23001 | FP1: B23001 | FQ1: B23001 | FR1: B23001 | FS1: B23001 | FT1: B23001 | FU1: B23001 | FV1: B23001 | FW1: B23001 | FX1: B23001 | FY1: B23001 | FZ1: B23001 | GA1: B23001 | GB1: B23001 | GC1: B23001 | GD1: B23001 | GE1: B23001 | GF1: B23001 | GG1: B23001 | GH1: B25072 | GI1: B25072 | GJ1: B25072 | GK1: B25072 | GL1: B25072 | GM1: B25072 | GN1: B25072 | GO1: B25093 | GP1: B25093 | GQ1: B25093 | GR1: B25093 | GS1: B25093 | GT1: B25093
B2: Age Group Estimates | C2: Age Group Estimates | D2: Age Group Estimates | E2: Age Group Estimates | F2: Age Group Estimates | G2: Age Group Estimates | H2: Age Group Estimates | I2: Age Group Estimates | J2: Age Group Estimates | K2: Age Group Estimates | L2: Age Group Estimates | M2: Age Group Estimates | N2: Age Group Estimates | O2: Median Age | P2: Households with Older Members | Q2: Households with Older Members | R2: Households with Older Members | S2: Households with Older Members | T2: Households with Older Members | U2: Marital Status, by Sex | V2: Marital Status, by Sex | W2: Marital Status, by Sex | X2: Marital Status, by Sex | Y2: Marital Status, by Sex | Z2: Marital Status, by Sex | AA2: Marital Status, by Sex | AB2: Marital Status, by Sex | AC2: Marital Status, by Sex | AD2: Marital Status, by Sex | AE2: Marital Status, by Sex | AF2: Marital Status, by Sex | AG2: Marital Status, by Sex | AH2: Marital Status, by Sex | AI2: Marital Status, by Sex | AJ2: Marital Status, by Sex | AK2: Marital Status, by Sex | AL2: Marital Status, by Sex | AM2: Marital Status, by Sex | AN2: Marital Status, by Sex | AO2: Marital Status, by Sex | AP2: Marital Status, by Sex | AQ2: Marital Status, by Sex | AR2: Marital Status, by Sex | AS2: Marital Status, by Sex | AT2: Marital Status, by Sex | AU2: Marital Status, by Sex | AV2: Marital Status, by Sex | AW2: Marital Status, by Sex | AX2: Marital Status, by Sex | AY2: Marital Status, by Sex | AZ2: Marital Status, by Sex | BA2: Marital Status, by Sex | BB2: Disability Status, by Sex | BC2: Disability Status, by Sex | BD2: Disability Status, by Sex | BE2: Disability Status, by Sex | BF2: Disability Status, by Sex | BG2: Disability Status, by Sex | BH2: Disability Status, by Sex | BI2: Disability Status, by Sex | BJ2: Disability Status, by Sex | BK2: Living Alone | BL2: Living Alone | BM2: Living Alone | BN2: Living Alone | BO2: Living Alone | BP2: Living Alone | BQ2: Living Alone | BR2: Living Alone | BS2: Living Alone | BT2: Race & Ethnicity | BU2: Race & Ethnicity | BV2: Race & Ethnicity | BW2: Race & Ethnicity | BX2: Race & Ethnicity | BY2: Race & Ethnicity | BZ2: Race & Ethnicity | CA2: Race & Ethnicity | CB2: Race & Ethnicity | CC2: Race & Ethnicity | CD2: Race & Ethnicity | CE2: Race & Ethnicity | CF2: Race & Ethnicity | CG2: Race & Ethnicity | CH2: Race & Ethnicity | CI2: Race & Ethnicity | CJ2: Race & Ethnicity | CK2: Race & Ethnicity | CL2: Race & Ethnicity | CM2: Race & Ethnicity | CN2: Race & Ethnicity | CO2: Race & Ethnicity | CP2: Race & Ethnicity | CQ2: Race & Ethnicity | CR2: Race & Ethnicity | CS2: Race & Ethnicity | CT2: Race & Ethnicity | CU2: Race & Ethnicity | CV2: Race & Ethnicity | CW2: Race & Ethnicity | CX2: Race & Ethnicity | CY2: Race & Ethnicity | CZ2: Race & Ethnicity | DA2: Race & Ethnicity | DB2: Race & Ethnicity | DC2: Race & Ethnicity | DD2: Educational Attainment | DE2: Educational Attainment | DF2: Educational Attainment | DG2: Educational Attainment | DH2: Educational Attainment | DI2: Educational Attainment | DJ2: Educational Attainment | DK2: Educational Attainment | DL2: Educational Attainment | DM2: Educational Attainment | DN2: Educational Attainment | DO2: Educational Attainment | DP2: Educational Attainment | DQ2: Educational Attainment | DR2: Educational Attainment | DS2: Educational Attainment | DT2: Educational Attainment | DU2: Educational Attainment | DV2: Educational Attainment | DW2: Educational Attainment | DX2: Educational Attainment | DY2: Educational Attainment | DZ2: Educational Attainment | EA2: Educational Attainment | EB2: Household Income | EC2: Household Income | ED2: Household Income | EE2: Household Income | EF2: Household Income | EG2: Household Income | EH2: Household Income | EI2: Household Income | EJ2: Household Income | EK2: Household Income | EL2: Household Income | EM2: Household Income | EN2: Household Income | EO2: Median Household Income | EP2: Median Household Income | EQ2: Median Household Income | ER2: Median Household Income | ES2: Median Household Income | ET2: Poverty by Sex | EU2: Poverty by Sex | EV2: Poverty by Sex | EW2: Poverty by Sex | EX2: Poverty by Sex | EY2: Poverty by Sex | EZ2: Poverty by Sex | FA2: Poverty by Sex | FB2: Poverty by Sex | FC2: Ratio of Income to Poverty | FD2: Ratio of Income to Poverty | FE2: Ratio of Income to Poverty | FF2: Ratio of Income to Poverty | FG2: Ratio of Income to Poverty | FH2: Ratio of Income to Poverty | FI2: Ratio of Income to Poverty | FJ2: Ratio of Income to Poverty | FK2: Ratio of Income to Poverty | FL2: Ratio of Income to Poverty | FM2: Ratio of Income to Poverty | FN2: Employment Status | FO2: Employment Status | FP2: Employment Status | FQ2: Employment Status | FR2: Employment Status | FS2: Employment Status | FT2: Employment Status | FU2: Employment Status | FV2: Employment Status | FW2: Employment Status | FX2: Employment Status | FY2: Employment Status | FZ2: Employment Status | GA2: Employment Status | GB2: Employment Status | GC2: Employment Status | GD2: Employment Status | GE2: Employment Status | GF2: Employment Status | GG2: Employment Status | GH2: Housing Tenure and Costs | GI2: Housing Tenure and Costs | GJ2: Housing Tenure and Costs | GK2: Housing Tenure and Costs | GL2: Housing Tenure and Costs | GM2: Housing Tenure and Costs | GN2: Housing Tenure and Costs | GO2: Housing Tenure and Costs | GP2: Housing Tenure and Costs | GQ2: Housing Tenure and Costs | GR2: Housing Tenure and Costs | GS2: Housing Tenure and Costs | GT2: Housing Tenure and Costs
B3: Total Population - All Ages, All Races | C3: 60+ | D3: 65+ | E3: 75+ | F3: 85+ | G3: % 60+ | H3: % 65+ | I3: % 75+ | J3: % 85+ | K3: Males age 65+ | L3: Males as percent of 65+ population | M3: Females age 65+ | N3: Females as percent of 65+ population | O3: Total (Males and Females, All Races) | P3: Total number of households | Q3: Households with one or more people 60 years and over: | R3: Percent with a member age 60+ | S3: Households with one or more people 65 years and over: | T3: Percent with a member age 65+ | U3: Total Males, 65+ | V3: Males, 65+: Never Married | W3: % Males Never Married | X3: Males, 65+: Married, Spouse Present | Y3: % Males Married, Spouse Present | Z3: Males, 65+: Married, Spouse Absent (e.g., Separated) | AA3: % Males Married, Spouse Absent | AB3: Males, 65+: Widowed | AC3: % Males Widowed | AD3: Males, 65+: Divorced | AE3: % Males Divorced | AF3: Total Females, 65+ | AG3: Females, 65+: Never Married | AH3: % Females Never Married | AI3: Females, 65+: Married, Spouse Present | AJ3: % Females Married, Spouse Present | AK3: Females, 65+: Married, Spouse Absent (e.g., Separated) | AL3: % Females Married, Spouse Absent | AM3: Females, 65+: Widowed | AN3: % Females Widowed | AO3: Females, 65+: Divorced | AP3: % Females Divorced | AQ3: Total Persons, 65+ | AR3: Persons, 65+: Never Married | AS3: % Total Never Married | AT3: Persons, 65+: Married, Spouse Present | AU3: % Total Married, Spouse Present | AV3: Persons, 65+: Married, Spouse Absent (e.g., Separated) | AW3: % Total Married, Spouse Absent | AX3: Persons, 65+: Widowed | AY3: % Total Widowed | AZ3: Persons, 65+: Divorced | BA3: % Total Divorced | BB3: Males, 65+, Total* | BC3: Males, 65+, With a Disability | BD3: Males, 65+, % with a Disability | BE3: Females, 65+, Total* | BF3: Females, 65+, With a Disability | BG3: Females, 65+, % with a Disability | BH3: All Persons, 65+* | BI3: Total Persons, 65+, With a Disability | BJ3: Total Persons, 65+, % with a Disability | BK3: Persons 65+ | BL3: Persons 65+ living alone | BM3: Persons, % living alone | BN3: Males age 65+ | BO3: Males age 65+ living alone | BP3: Males, % living alone | BQ3: Females age 65+ | BR3: Females age 65+ living alone | BS3: Females, % living alone | BT3: Total - All Ages: Total Population | BU3: 65+ All Races and Hispanic Ethnicity | BV3: % of Total Population that is 65+ | BW3: % of 65+ that is All Races and Hispanic Ethnicity | BX3: Total - All Ages: White/Caucasian Alone | BY3: 65+ White/Caucasian | BZ3: % of White/Caucasian pop that is 65+ | CA3: % of 65+ that is White/Caucasian | CB3: Total - All Ages: Black/African American Alone | CC3: 65+ Black/African American | CD3: % of Black/African American pop that is 65+ | CE3: % of 65+ that is Black/African American | CF3: Total - All Ages: Native American/Alaska Native Alone | CG3: 65+ Native American/Alaska Native | CH3: % of Native American/Alaska Native pop that is 65+ | CI3: % of 65+ that is Native American/Alaska Native | CJ3: Total - All Ages: Asian Alone | CK3: 65+ Asian | CL3: % of Asian pop that is 65+ | CM3: % of 65+ that is Asian | CN3: Total - All Ages: Hawaiian/Pacific Islander Alone | CO3: 65+ Hawaiian/Pacific Islander | CP3: % of Hawaiian/Pacific Islander pop that is 65+ | CQ3: % of 65+ that is Hawaiian/Pacific Islander | CR3: Total - All Ages: Some Other Race | CS3: 65+ Some Other Race | CT3: % of Some Other Race pop that is 65+ | CU3: % of 65+ that is Some Other Race | CV3: Total - All Ages: Two or More Races | CW3: 65+ Two or More Races | CX3: % of Two or More Races pop that is 65+ | CY3: % of 65+ that is Two or More Races | CZ3: Total - All Ages: Ethnicity Hispanic/Latino (May be any Race) | DA3: 65+ with Ethnicity Hispanic/Latino | DB3: % of Ethnicity Hispanic/Latino pop that is 65+ | DC3: % of 65+ with Ethnicity Hispanic/Latino | DD3: Males: 65 years and over: | DE3: 65+ Males: Less than high school graduate | DF3: 65+ Males: High school graduate (includes equiv.) | DG3: 65+ Males: Some college or associate's degree | DH3: 65+ Males: Bachelor's degree or higher | DI3: % 65+ Males: Less than high school | DJ3: % 65+ Males: High school only | DK3: % 65+ Males: More than high school | DL3: Females: 65 years and over: | DM3: 65+ Females: Less than high school graduate | DN3: 65+ Females: High school graduate (includes equiv) | DO3: 65+ Females: Some college or associate's degree | DP3: 65+ Females: Bachelor's degree or higher | DQ3: % 65+ Females: Less than high school | DR3: % 65+ Females: High school only | DS3: % 65+ Females: More than high school | DT3: Persons: 65 years and over: | DU3: 65+ Persons: Less than high school graduate | DV3: 65+ Persons: High school graduate (includes equiv) | DW3: 65+ Persons: Some college or associate's degree | DX3: 65+ Persons: Bachelor's degree or higher | DY3: % 65+ Persons: Less than high school | DZ3: % 65+ Persons: High school only | EA3: % 65+ Persons: More than high school | EB3: Households with head age 65+ | EC3: Household income below $15,000 | ED3: % with HH income below $15,000 | EE3: Household income below $25,000 | EF3: % with HH income below $25,000 | EG3: Household income below $35,000 | EH3: % with HH income below $35,000 | EI3: Household income below $50,000 | EJ3: % with HH income below $50,000 | EK3: Household income below $75,000 | EL3: % with HH income below $75,000 | EM3: Household income below $100,000 | EN3: % with HH income below $100,000 | EO3: Total, householders of all ages: | EP3: Householder under 25 years | EQ3: Householder 25 to 44 years | ER3: Householder 45 to 64 years | ES3: Householder 65 years and over | ET3: Males age 65+ (for poverty) | EU3: 65+ Males in Poverty | EV3: % of 65+ males in poverty | EW3: Females age 65+ (for poverty) | EX3: 65+ Females in Poverty | EY3: % of 65+ females in poverty | EZ3: Persons age 65+ (for poverty) | FA3: Persons 65+ in poverty | FB3: % of persons 65+ in poverty | FC3: Total, Age 65+* | FD3: Age 65+ below poverty | FE3: % of 65+ Pop below poverty | FF3: Age 65+: 150% of poverty or less | FG3: % of 65+ Pop: 150% of poverty or less | FH3: Age 65+: 185% of poverty or less | FI3: % of 65+ Pop: 185% of poverty or less | FJ3: Age 65+: 200% of poverty or less | FK3: % of 65+ Pop: 200% of poverty or less | FL3: Age 65+: 300% of poverty or less | FM3: % of 65+ Pop: 300% of poverty or less | FN3: Males age 65-74: Employed | FO3: Males 65-74; % Employed | FP3: Males age 65-74: Unemployed | FQ3: Males 65-74; % Unemployed | FR3: Males age 75+: Employed | FS3: Males 75+; % Employed | FT3: Males age 75+: Unemployed | FU3: Males 75+; % Unemployed | FV3: Females age 65-74: Employed | FW3: Females 65-74; % Employed | FX3: Females age 65-74: Unemployed | FY3: Females 65-74; % Unemployed | FZ3: Females age 75+: Employed | GA3: Females 75+; % Employed | GB3: Females age 75+: Unemployed | GC3: Females 75+; % Unemployed | GD3: Persons age 65+: Employed | GE3: Persons age 65+; % Employed | GF3: Persons age 65+: Unemployed | GG3: Persons age 65+; % Unemployed | GH3: Housing units occupied by householders age 65+ | GI3: Number of units that are rentals | GJ3: Percent of units that are rentals | GK3: Rental costs less than 30% of income | GL3: Percent with rental costs <30% of income | GM3: Rental costs 30% of income or more | GN3: Percent with rental costs >=30% of income or more | GO3: Number of units that are owner-occupied | GP3: Percent of units that are owner-occupied | GQ3: Monthly owner costs less than 30% of income | GR3: Percent with monthly owner costs <30% of income | GS3: Monthly owner costs 30% of income or more | GT3: Percent with owner costs >=30% of income
A4: Wisconsin | B4: 5914872 | C4: 1514099 | D4: 1096043 | E4: 434379 | F4: 124459 | G4: =C4/B4 -> 0.2559817 | H4: =D4/B4 -> 0.18530291 | I4: =E4/B4 -> 0.073438445 | J4: =F4/B4 -> 0.021041706 | K4: 510727 | L4: =K4/D4 -> 0.46597351 | M4: 585316 | N4: =M4/D4 -> 0.53402649 | O4: 40.2 | P4: 2479480 | Q4: 1033712 | R4: =Q4/P4 -> 0.41690677 | S4: 778619 | T4: =S4/P4 -> 0.31402512 | U4: 510727 | V4: 35830 | W4: =V4/U4 -> 0.070154897 | X4: 343234 | Y4: =X4/U4 -> 0.67204984 | Z4: 14953 | AA4: =Z4/U4 -> 0.029277873 | AB4: 50209 | AC4: =AB4/U4 -> 0.098308881 | AD4: 66501 | AE4: =AD4/U4 -> 0.13020851 | AF4: 585316 | AG4: 37140 | AH4: =AG4/AF4 -> 0.063452904 | AI4: 275664 | AJ4: =AI4/AF4 -> 0.47096611 | AK4: 14366 | AL4: =AK4/AF4 -> 0.024544007 | AM4: 165331 | AN4: =AM4/AF4 -> 0.28246451 | AO4: 92815 | AP4: =AO4/AF4 -> 0.15857246 | AQ4: =SUM(U4,AF4) -> 1096043 | AR4: =SUM(V4,AG4) -> 72970 | AS4: =AR4/AQ4 -> 0.066575855 | AT4: =SUM(X4,AI4) -> 618898 | AU4: =AT4/AQ4 -> 0.5646658 | AV4: =SUM(Z4,AK4) -> 29319 | AW4: =AV4/AQ4 -> 0.026749863 | AX4: =SUM(AB4,AM4) -> 215540 | AY4: =AX4/AQ4 -> 0.19665287 | AZ4: =SUM(AD4,AO4) -> 159316 | BA4: =AZ4/AQ4 -> 0.14535561 | BB4: 501270 | BC4: 144564 | BD4: =BC4/BB4 -> 0.28839548 | BE4: 568121 | BF4: 159656 | BG4: =BF4/BE4 -> 0.28102464 | BH4: =SUM(BB4,BE4) -> 1069391 | BI4: =SUM(BC4,BF4) -> 304220 | BJ4: =BI4/BH4 -> 0.28447967 | BK4: 1096043 | BL4: 320658 | BM4: =BL4/BK4 -> 0.29255969 | BN4: 510727 | BO4: 109743 | BP4: =BO4/BN4 -> 0.21487605 | BQ4: 585316 | BR4: 210915 | BS4: =BR4/BQ4 -> 0.36034381 | BT4: 5960975 | BU4: 1168733 | BV4: =BU4/BT4 -> 0.19606407 | BW4: =BU4/$BU4 -> 1 | BX4: 4704156 | BY4: 1076580 | BZ4: =BY4/BX4 -> 0.22885721 | CA4: =BY4/$BU4 -> 0.92115137 | CB4: 376518 | CC4: 36846 | CD4: =CC4/CB4 -> 0.097859863 | CE4: =CC4/$BU4 -> 0.031526448 | CF4: 52129 | CG4: 7377 | CH4: =CG4/CF4 -> 0.14151432 | CI4: =CG4/$BU4 -> 0.0063119635 | CJ4: 206457 | CK4: 14292 | CL4: =CK4/CJ4 -> 0.069225069 | CM4: =CK4/$BU4 -> 0.012228627 | CN4: 2518 | CO4: 299 | CP4: =CO4/CN4 -> 0.11874504 | CQ4: =CO4/$BU4 -> 0.0002558326 | CR4: 92690 | CS4: 2381 | CT4: =CS4/CR4 -> 0.025687776 | CU4: =CS4/$BU4 -> 0.0020372489 | CV4: 118928 | CW4: 5630 | CX4: =CW4/CV4 -> 0.047339567 | CY4: =CW4/$BU4 -> 0.0048171824 | CZ4: 500269 | DA4: 27709 | DB4: =DA4/CZ4 -> 0.055388201 | DC4: =DA4/$BU4 -> 0.02370858 | DD4: 510727 | DE4: 37962 | DF4: 179581 | DG4: 142801 | DH4: 150383 | DI4: =DE4/DD4 -> 0.074329338 | DJ4: =DF4/DD4 -> 0.35161838 | DK4: =SUM(DG4:DH4)/DD4 -> 0.57405228 | DL4: 585316 | DM4: 39828 | DN4: 230513 | DO4: 164474 | DP4: 150501 | DQ4: =DM4/DL4 -> 0.068045295 | DR4: =DN4/DL4 -> 0.39382658 | DS4: =SUM(DO4:DP4)/DL4 -> 0.53812812 | DT4: =SUM(DL4,DD4) -> 1096043 | DU4: =SUM(DM4,DE4) -> 77790 | DV4: =SUM(DN4,DF4) -> 410094 | DW4: =SUM(DO4,DG4) -> 307275 | DX4: =SUM(DP4,DH4) -> 300884 | DY4: =DU4/DT4 -> 0.070973493 | DZ4: =DV4/DT4 -> 0.37415868 | EA4: =SUM(DW4:DX4)/DT4 -> 0.55486783 | EB4: 704634 | EC4: 62109 | ED4: =EC4/$EB4 -> 0.088143632 | EE4: 129765 | EF4: =EE4/$EB4 -> 0.18415944 | EG4: 215008 | EH4: =EG4/$EB4 -> 0.3051343 | EI4: 309613 | EJ4: =EI4/$EB4 -> 0.43939549 | EK4: 454481 | EL4: =EK4/$EB4 -> 0.64498875 | EM4: 546311 | EN4: =EM4/$EB4 -> 0.77531172 | EO4: 77485 | EP4: 45850 | EQ4: 90128 | ER4: 94903 | ES4: 56488 | ET4: 501270 | EU4: 37828 | EV4: =EU4/ET4 -> 0.075464321 | EW4: 568121 | EX4: 59402 | EY4: =EX4/EW4 -> 0.10455871 | EZ4: =SUM(ET4,EW4) -> 1069391 | FA4: =SUM(EU4,EX4) -> 97230 | FB4: =FA4/EZ4 -> 0.090920907 | FC4: 1069391 | FD4: 97230 | FE4: =FD4/$FC4 -> 0.090920907 | FF4: 170118 | FG4: =FF4/$FC4 -> 0.15907933 | FH4: 234788 | FI4: =FH4/$FC4 -> 0.219553 | FJ4: 271979 | FK4: =FJ4/$FC4 -> 0.25433074 | FL4: 461898 | FM4: =FL4/$FC4 -> 0.43192621 | FN4: 85607 | FO4: 0.26448199 | FP4: 1872 | FQ4: 0.0057835256 | FR4: 15521 | FS4: 0.082978257 | FT4: 187 | FU4: 0.00099973804 | FV4: 70927 | FW4: 0.20985189 | FX4: 1471 | FY4: 0.0043522513 | FZ4: 11118 | GA4: 0.044952088 | GB4: 313 | GC4: 0.0012655157 | GD4: 183173 | GE4: 0.16712209 | GF4: 3843 | GG4: 0.0035062493 | GH4: 704634 | GI4: 158043 | GJ4: =GI4/GH4 -> 0.22429091 | GK4: 56619 | GL4: =GK4/GI4 -> 0.3582506 | GM4: 87122 | GN4: =GM4/GI4 -> 0.55125504 | GO4: 546591 | GP4: =GO4/GH4 -> 0.77570909 | GQ4: 413533 | GR4: =GQ4/GO4 -> 0.75656752 | GS4: 128749 | GT4: =GS4/GO4 -> 0.23554907
A5: Adams | B5: 21123 | C5: 9045 | D5: 6803 | E5: 2595 | F5: 668 | G5: =C5/B5 -> 0.42820622 | H5: =D5/B5 -> 0.32206599 | I5: =E5/B5 -> 0.12285187 | J5: =F5/B5 -> 0.031624296 | K5: 3531 | L5: =K5/D5 -> 0.51903572 | M5: 3272 | N5: =M5/D5 -> 0.48096428 | O5: 55.7 | P5: 9517 | Q5: 5968 | R5: =Q5/P5 -> 0.62708837 | S5: 4721 | T5: =S5/P5 -> 0.49605968 | U5: 3531 | V5: 148 | W5: =V5/U5 -> 0.041914472 | X5: 2326 | Y5: =X5/U5 -> 0.6587369 | Z5: 91 | AA5: =Z5/U5 -> 0.025771736 | AB5: 325 | AC5: =AB5/U5 -> 0.092041914 | AD5: 641 | AE5: =AD5/U5 -> 0.18153498 | AF5: 3272 | AG5: 165 | AH5: =AG5/AF5 -> 0.050427873 | AI5: 1739 | AJ5: =AI5/AF5 -> 0.53147922 | AK5: 68 | AL5: =AK5/AF5 -> 0.020782396 | AM5: 836 | AN5: =AM5/AF5 -> 0.25550122 | AO5: 464 | AP5: =AO5/AF5 -> 0.14180929 | AQ5: =SUM(U5,AF5) -> 6803 | AR5: =SUM(V5,AG5) -> 313 | AS5: =AR5/AQ5 -> 0.046009114 | AT5: =SUM(X5,AI5) -> 4065 | AU5: =AT5/AQ5 -> 0.5975305 | AV5: =SUM(Z5,AK5) -> 159 | AW5: =AV5/AQ5 -> 0.023372042 | AX5: =SUM(AB5,AM5) -> 1161 | AY5: =AX5/AQ5 -> 0.17066 | AZ5: =SUM(AD5,AO5) -> 1105 | BA5: =AZ5/AQ5 -> 0.16242834 | BB5: 3519 | BC5: 1240 | BD5: =BC5/BB5 -> 0.35237283 | BE5: 3241 | BF5: 1130 | BG5: =BF5/BE5 -> 0.34865782 | BH5: =SUM(BB5,BE5) -> 6760 | BI5: =SUM(BC5,BF5) -> 2370 | BJ5: =BI5/BH5 -> 0.35059172 | BK5: 6803 | BL5: 1740 | BM5: =BL5/BK5 -> 0.25576951 | BN5: 3531 | BO5: 901 | BP5: =BO5/BN5 -> 0.25516851 | BQ5: 3272 | BR5: 839 | BS5: =BR5/BQ5 -> 0.25641809 | BT5: 21352 | BU5: 7276 | BV5: =BU5/BT5 -> 0.34076433 | BW5: =BU5/$BU5 -> 1 | BX5: 19105 | BY5: 7026 | BZ5: =BY5/BX5 -> 0.36775713 | CA5: =BY5/$BU5 -> 0.96564046 | CB5: 624 | CC5: 47 | CD5: =CC5/CB5 -> 0.075320513 | CE5: =CC5/$BU5 -> 0.0064595932 | CF5: 201 | CG5: 33 | CH5: =CG5/CF5 -> 0.1641791 | CI5: =CG5/$BU5 -> 0.004535459 | CJ5: 137 | CK5: 26 | CL5: =CK5/CJ5 -> 0.18978102 | CM5: =CK5/$BU5 -> 0.003573392 | CN5: 7 | CO5: 1 | CP5: =CO5/CN5 -> 0.14285714 | CQ5: =CO5/$BU5 -> 0.00013743815 | CR5: 126 | CS5: 11 | CT5: =CS5/CR5 -> 0.087301587 | CU5: =CS5/$BU5 -> 0.0015118197 | CV5: 291 | CW5: 47 | CX5: =CW5/CV5 -> 0.16151203 | CY5: =CW5/$BU5 -> 0.0064595932 | CZ5: 987 | DA5: 96 | DB5: =DA5/CZ5 -> 0.097264438 | DC5: =DA5/BU5 -> 0.013194063 | DD5: 3531 | DE5: 458 | DF5: 1466 | DG5: 923 | DH5: 684 | DI5: =DE5/DD5 -> 0.1297083 | DJ5: =DF5/DD5 -> 0.41517984 | DK5: =SUM(DG5:DH5)/DD5 -> 0.45511187 | DL5: 3272 | DM5: 319 | DN5: 1372 | DO5: 1095 | DP5: 486 | DQ5: =DM5/DL5 -> 0.097493888 | DR5: =DN5/DL5 -> 0.4193154 | DS5: =SUM(DO5:DP5)/DL5 -> 0.48319071 | DT5: =SUM(DL5,DD5) -> 6803 | DU5: =SUM(DM5,DE5) -> 777 | DV5: =SUM(DN5,DF5) -> 2838 | DW5: =SUM(DO5,DG5) -> 2018 | DX5: =SUM(DP5,DH5) -> 1170 | DY5: =DU5/DT5 -> 0.11421432 | DZ5: =DV5/DT5 -> 0.4171689 | EA5: =SUM(DW5:DX5)/DT5 -> 0.46861679 | EB5: 4285 | EC5: 392 | ED5: =EC5/$EB5 -> 0.091481914 | EE5: 835 | EF5: =EE5/$EB5 -> 0.19486581 | EG5: 1531 | EH5: =EG5/$EB5 -> 0.35729288 | EI5: 2315 | EJ5: =EI5/$EB5 -> 0.54025671 | EK5: 3163 | EL5: =EK5/$EB5 -> 0.73815636 | EM5: 3658 | EN5: =EM5/$EB5 -> 0.85367561 | EO5: 59442 | EP5: 67500 | EQ5: 69730 | ER5: 80799 | ES5: 47002 | ET5: 3519 | EU5: 311 | EV5: =EU5/ET5 -> 0.08837738 | EW5: 3241 | EX5: 534 | EY5: =EX5/EW5 -> 0.16476396 | EZ5: =SUM(ET5,EW5) -> 6760 | FA5: =SUM(EU5,EX5) -> 845 | FB5: =FA5/EZ5 -> 0.125 | FC5: 6760 | FD5: 845 | FE5: =FD5/$FC5 -> 0.125 | FF5: 1442 | FG5: =FF5/$FC5 -> 0.21331361 | FH5: 1873 | FI5: =FH5/$FC5 -> 0.27707101 | FJ5: 2380 | FK5: =FJ5/$FC5 -> 0.35207101 | FL5: 3744 | FM5: =FL5/$FC5 -> 0.55384615 | FN5: 362 | FO5: 0.16153503 | FP5: 2 | FQ5: 0.00089245872 | FR5: 72 | FS5: 0.055813953 | FT5: 1 | FU5: 0.0007751938 | FV5: 267 | FW5: 0.13573971 | FX5: 3 | FY5: 0.0015251652 | FZ5: 125 | GA5: 0.095785441 | GB5: 0 | GC5: 0 | GD5: 826 | GE5: 0.12141702 | GF5: 6 | GG5: 0.00088196384 | GH5: 4285 | GI5: 333 | GJ5: =GI5/GH5 -> 0.077712952 | GK5: 104 | GL5: =GK5/GI5 -> 0.31231231 | GM5: 126 | GN5: =GM5/GI5 -> 0.37837838 | GO5: 3952 | GP5: =GO5/GH5 -> 0.92228705 | GQ5: 2866 | GR5: =GQ5/GO5 -> 0.72520243 | GS5: 1052 | GT5: =GS5/GO5 -> 0.26619433
A6: Ashland | B6: 16080 | C6: 4731 | D6: 3452 | E6: 1316 | F6: 459 | G6: =C6/B6 -> 0.29421642 | H6: =D6/B6 -> 0.21467662 | I6: =E6/B6 -> 0.081840796 | J6: =F6/B6 -> 0.028544776 | K6: 1683 | L6: =K6/D6 -> 0.48754345 | M6: 1769 | N6: =M6/D6 -> 0.51245655 | O6: 43.1 | P6: 6832 | Q6: 3251 | R6: =Q6/P6 -> 0.47584895 | S6: 2483 | T6: =S6/P6 -> 0.36343677 | U6: 1683 | V6: 159 | W6: =V6/U6 -> 0.094474153 | X6: 973 | Y6: =X6/U6 -> 0.57813428 | Z6: 54 | AA6: =Z6/U6 -> 0.032085561 | AB6: 210 | AC6: =AB6/U6 -> 0.12477718 | AD6: 287 | AE6: =AD6/U6 -> 0.17052882 | AF6: 1769 | AG6: 153 | AH6: =AG6/AF6 -> 0.086489542 | AI6: 815 | AJ6: =AI6/AF6 -> 0.46071227 | AK6: 51 | AL6: =AK6/AF6 -> 0.028829847 | AM6: 434 | AN6: =AM6/AF6 -> 0.24533635 | AO6: 316 | AP6: =AO6/AF6 -> 0.178632 | AQ6: =SUM(U6,AF6) -> 3452 | AR6: =SUM(V6,AG6) -> 312 | AS6: =AR6/AQ6 -> 0.090382387 | AT6: =SUM(X6,AI6) -> 1788 | AU6: =AT6/AQ6 -> 0.5179606 | AV6: =SUM(Z6,AK6) -> 105 | AW6: =AV6/AQ6 -> 0.030417149 | AX6: =SUM(AB6,AM6) -> 644 | AY6: =AX6/AQ6 -> 0.18655852 | AZ6: =SUM(AD6,AO6) -> 603 | BA6: =AZ6/AQ6 -> 0.17468134 | BB6: 1600 | BC6: 534 | BD6: =BC6/BB6 -> 0.33375 | BE6: 1680 | BF6: 509 | BG6: =BF6/BE6 -> 0.30297619 | BH6: =SUM(BB6,BE6) -> 3280 | BI6: =SUM(BC6,BF6) -> 1043 | BJ6: =BI6/BH6 -> 0.3179878 | BK6: 3452 | BL6: 1154 | BM6: =BL6/BK6 -> 0.33429896 | BN6: 1683 | BO6: 494 | BP6: =BO6/BN6 -> 0.29352347 | BQ6: 1769 | BR6: 660 | BS6: =BR6/BQ6 -> 0.37309214 | BT6: 16196 | BU6: 3708 | BV6: =BU6/BT6 -> 0.22894542 | BW6: =BU6/$BU6 -> 1 | BX6: 13277 | BY6: 3295 | BZ6: =BY6/BX6 -> 0.24817353 | CA6: =BY6/$BU6 -> 0.8886192 | CB6: 112 | CC6: 8 | CD6: =CC6/CB6 -> 0.071428571 | CE6: =CC6/$BU6 -> 0.0021574973 | CF6: 1595 | CG6: 260 | CH6: =CG6/CF6 -> 0.1630094 | CI6: =CG6/$BU6 -> 0.070118662 | CJ6: 157 | CK6: 17 | CL6: =CK6/CJ6 -> 0.10828025 | CM6: =CK6/$BU6 -> 0.0045846818 | CN6: 6 | CO6: 0 | CP6: =CO6/CN6 -> 0 | CQ6: =CO6/$BU6 -> 0 | CR6: 44 | CS6: 0 | CT6: =CS6/CR6 -> 0 | CU6: =CS6/$BU6 -> 0 | CV6: 531 | CW6: 87 | CX6: =CW6/CV6 -> 0.16384181 | CY6: =CW6/$BU6 -> 0.023462783 | CZ6: 518 | DA6: 41 | DB6: =DA6/CZ6 -> 0.079150579 | DC6: =DA6/BU6 -> 0.011057174 | DD6: 1683 | DE6: 91 | DF6: 697 | DG6: 525 | DH6: 370 | DI6: =DE6/DD6 -> 0.054070113 | DJ6: =DF6/DD6 -> 0.41414141 | DK6: =SUM(DG6:DH6)/DD6 -> 0.53178847 | DL6: 1769 | DM6: 54 | DN6: 834 | DO6: 515 | DP6: 366 | DQ6: =DM6/DL6 -> 0.030525721 | DR6: =DN6/DL6 -> 0.4714528 | DS6: =SUM(DO6:DP6)/DL6 -> 0.49802148 | DT6: =SUM(DL6,DD6) -> 3452 | DU6: =SUM(DM6,DE6) -> 145 | DV6: =SUM(DN6,DF6) -> 1531 | DW6: =SUM(DO6,DG6) -> 1040 | DX6: =SUM(DP6,DH6) -> 736 | DY6: =DU6/DT6 -> 0.042004635 | DZ6: =DV6/DT6 -> 0.44351101 | EA6: =SUM(DW6:DX6)/DT6 -> 0.51448436 | EB6: 2292 | EC6: 410 | ED6: =EC6/$EB6 -> 0.17888307 | EE6: 665 | EF6: =EE6/$EB6 -> 0.29013962 | EG6: 940 | EH6: =EG6/$EB6 -> 0.41012216 | EI6: 1236 | EJ6: =EI6/$EB6 -> 0.53926702 | EK6: 1712 | EL6: =EK6/$EB6 -> 0.7469459 | EM6: 1918 | EN6: =EM6/$EB6 -> 0.83682373 | EO6: 62462 | EP6: 56667 | EQ6: 70406 | ER6: 75422 | ES6: 44602 | ET6: 1600 | EU6: 227 | EV6: =EU6/ET6 -> 0.141875 | EW6: 1680 | EX6: 345 | EY6: =EX6/EW6 -> 0.20535714 | EZ6: =SUM(ET6,EW6) -> 3280 | FA6: =SUM(EU6,EX6) -> 572 | FB6: =FA6/EZ6 -> 0.17439024 | FC6: 3280 | FD6: 572 | FE6: =FD6/$FC6 -> 0.17439024 | FF6: 869 | FG6: =FF6/$FC6 -> 0.26493902 | FH6: 1048 | FI6: =FH6/$FC6 -> 0.3195122 | FJ6: 1198 | FK6: =FJ6/$FC6 -> 0.3652439 | FL6: 1736 | FM6: =FL6/$FC6 -> 0.52926829 | FN6: 240 | FO6: 0.21937843 | FP6: 2 | FQ6: 0.0018281536 | FR6: 75 | FS6: 0.12733447 | FT6: 2 | FU6: 0.0033955857 | FV6: 240 | FW6: 0.2303263 | FX6: 3 | FY6: 0.0028790787 | FZ6: 67 | GA6: 0.09215956 | GB6: 1 | GC6: 0.0013755158 | GD6: 622 | GE6: 0.1801854 | GF6: 8 | GG6: 0.0023174971 | GH6: 2292 | GI6: 487 | GJ6: =GI6/GH6 -> 0.21247818 | GK6: 166 | GL6: =GK6/GI6 -> 0.34086242 | GM6: 243 | GN6: =GM6/GI6 -> 0.49897331 | GO6: 1805 | GP6: =GO6/GH6 -> 0.78752182 | GQ6: 1361 | GR6: =GQ6/GO6 -> 0.75401662 | GS6: 439 | GT6: =GS6/GO6 -> 0.2432133
A7: Barron | B7: 46797 | C7: 14886 | D7: 11028 | E7: 4690 | F7: 1241 | G7: =C7/B7 -> 0.31809731 | H7: =D7/B7 -> 0.23565613 | I7: =E7/B7 -> 0.1002201 | J7: =F7/B7 -> 0.026518794 | K7: 5326 | L7: =K7/D7 -> 0.48295248 | M7: 5702 | N7: =M7/D7 -> 0.51704752 | O7: 44.9 | P7: 19955 | Q7: 10027 | R7: =Q7/P7 -> 0.50248058 | S7: 7708 | T7: =S7/P7 -> 0.38626911 | U7: 5326 | V7: 322 | W7: =V7/U7 -> 0.06045813 | X7: 3609 | Y7: =X7/U7 -> 0.67761923 | Z7: 196 | AA7: =Z7/U7 -> 0.036800601 | AB7: 465 | AC7: =AB7/U7 -> 0.087307548 | AD7: 734 | AE7: =AD7/U7 -> 0.13781449 | AF7: 5702 | AG7: 280 | AH7: =AG7/AF7 -> 0.049105577 | AI7: 2823 | AJ7: =AI7/AF7 -> 0.49508944 | AK7: 150 | AL7: =AK7/AF7 -> 0.026306559 | AM7: 1519 | AN7: =AM7/AF7 -> 0.26639776 | AO7: 930 | AP7: =AO7/AF7 -> 0.16310067 | AQ7: =SUM(U7,AF7) -> 11028 | AR7: =SUM(V7,AG7) -> 602 | AS7: =AR7/AQ7 -> 0.054588321 | AT7: =SUM(X7,AI7) -> 6432 | AU7: =AT7/AQ7 -> 0.58324266 | AV7: =SUM(Z7,AK7) -> 346 | AW7: =AV7/AQ7 -> 0.031374683 | AX7: =SUM(AB7,AM7) -> 1984 | AY7: =AX7/AQ7 -> 0.17990569 | AZ7: =SUM(AD7,AO7) -> 1664 | BA7: =AZ7/AQ7 -> 0.15088865 | BB7: 5228 | BC7: 1569 | BD7: =BC7/BB7 -> 0.30011477 | BE7: 5495 | BF7: 1629 | BG7: =BF7/BE7 -> 0.29645132 | BH7: =SUM(BB7,BE7) -> 10723 | BI7: =SUM(BC7,BF7) -> 3198 | BJ7: =BI7/BH7 -> 0.29823743 | BK7: 11028 | BL7: 3134 | BM7: =BL7/BK7 -> 0.28418571 | BN7: 5326 | BO7: 1217 | BP7: =BO7/BN7 -> 0.22850169 | BQ7: 5702 | BR7: 1917 | BS7: =BR7/BQ7 -> 0.33619783 | BT7: 46810 | BU7: 11576 | BV7: =BU7/BT7 -> 0.24729759 | BW7: =BU7/$BU7 -> 1 | BX7: 42815 | BY7: 11263 | BZ7: =BY7/BX7 -> 0.26306201 | CA7: =BY7/$BU7 -> 0.9729613 | CB7: 759 | CC7: 51 | CD7: =CC7/CB7 -> 0.067193676 | CE7: =CC7/$BU7 -> 0.0044056669 | CF7: 478 | CG7: 65 | CH7: =CG7/CF7 -> 0.13598326 | CI7: =CG7/$BU7 -> 0.0056150657 | CJ7: 359 | CK7: 51 | CL7: =CK7/CJ7 -> 0.14206128 | CM7: =CK7/$BU7 -> 0.0044056669 | CN7: 6 | CO7: 2 | CP7: =CO7/CN7 -> 0.33333333 | CQ7: =CO7/$BU7 -> 0.00017277125 | CR7: 275 | CS7: 4 | CT7: =CS7/CR7 -> 0.014545455 | CU7: =CS7/$BU7 -> 0.0003455425 | CV7: 644 | CW7: 53 | CX7: =CW7/CV7 -> 0.082298137 | CY7: =CW7/$BU7 -> 0.0045784381 | CZ7: 1749 | DA7: 91 | DB7: =DA7/CZ7 -> 0.052029731 | DC7: =DA7/BU7 -> 0.0078610919 | DD7: 5326 | DE7: 657 | DF7: 2194 | DG7: 1285 | DH7: 1190 | DI7: =DE7/DD7 -> 0.12335712 | DJ7: =DF7/DD7 -> 0.41194142 | DK7: =SUM(DG7:DH7)/DD7 -> 0.46470146 | DL7: 5702 | DM7: 490 | DN7: 2435 | DO7: 1570 | DP7: 1207 | DQ7: =DM7/DL7 -> 0.08593476 | DR7: =DN7/DL7 -> 0.42704314 | DS7: =SUM(DO7:DP7)/DL7 -> 0.4870221 | DT7: =SUM(DL7,DD7) -> 11028 | DU7: =SUM(DM7,DE7) -> 1147 | DV7: =SUM(DN7,DF7) -> 4629 | DW7: =SUM(DO7,DG7) -> 2855 | DX7: =SUM(DP7,DH7) -> 2397 | DY7: =DU7/DT7 -> 0.10400798 | DZ7: =DV7/DT7 -> 0.41974973 | EA7: =SUM(DW7:DX7)/DT7 -> 0.47624229 | EB7: 7065 | EC7: 663 | ED7: =EC7/$EB7 -> 0.093842887 | EE7: 1425 | EF7: =EE7/$EB7 -> 0.20169851 | EG7: 2524 | EH7: =EG7/$EB7 -> 0.35725407 | EI7: 3654 | EJ7: =EI7/$EB7 -> 0.51719745 | EK7: 5119 | EL7: =EK7/$EB7 -> 0.72455768 | EM7: 6080 | EN7: =EM7/$EB7 -> 0.86058033 | EO7: 65933 | EP7: 46080 | EQ7: 79497 | ER7: 83273 | ES7: 48481 | ET7: 5228 | EU7: 435 | EV7: =EU7/ET7 -> 0.083205815 | EW7: 5495 | EX7: 528 | EY7: =EX7/EW7 -> 0.096087352 | EZ7: =SUM(ET7,EW7) -> 10723 | FA7: =SUM(EU7,EX7) -> 963 | FB7: =FA7/EZ7 -> 0.089806957 | FC7: 10723 | FD7: 963 | FE7: =FD7/$FC7 -> 0.089806957 | FF7: 2161 | FG7: =FF7/$FC7 -> 0.20152942 | FH7: 2786 | FI7: =FH7/$FC7 -> 0.25981535 | FJ7: 3269 | FK7: =FJ7/$FC7 -> 0.30485871 | FL7: 5684 | FM7: =FL7/$FC7 -> 0.53007554 | FN7: 673 | FO7: 0.20933126 | FP7: 7 | FQ7: 0.0021772939 | FR7: 135 | FS7: 0.063950734 | FT7: 0 | FU7: 0 | FV7: 701 | FW7: 0.22446366 | FX7: 22 | FY7: 0.0070445085 | FZ7: 140 | GA7: 0.054284606 | GB7: 0 | GC7: 0 | GD7: 1649 | GE7: 0.14952847 | GF7: 29 | GG7: 0.0026296699 | GH7: 7065 | GI7: 1457 | GJ7: =GI7/GH7 -> 0.20622788 | GK7: 558 | GL7: =GK7/GI7 -> 0.38297872 | GM7: 633 | GN7: =GM7/GI7 -> 0.43445436 | GO7: 5608 | GP7: =GO7/GH7 -> 0.79377212 | GQ7: 4281 | GR7: =GQ7/GO7 -> 0.76337375 | GS7: 1310 | GT7: =GS7/GO7 -> 0.23359486
A8: Bayfield | B8: 16575 | C8: 6838 | D8: 5185 | E8: 1901 | F8: 497 | G8: =C8/B8 -> 0.41254902 | H8: =D8/B8 -> 0.31282051 | I8: =E8/B8 -> 0.1146908 | J8: =F8/B8 -> 0.029984917 | K8: 2623 | L8: =K8/D8 -> 0.50588235 | M8: 2562 | N8: =M8/D8 -> 0.49411765 | O8: 54.6 | P8: 7437 | Q8: 4514 | R8: =Q8/P8 -> 0.60696517 | S8: 3600 | T8: =S8/P8 -> 0.48406616 | U8: 2623 | V8: 125 | W8: =V8/U8 -> 0.047655356 | X8: 1892 | Y8: =X8/U8 -> 0.72131148 | Z8: 87 | AA8: =Z8/U8 -> 0.033168128 | AB8: 211 | AC8: =AB8/U8 -> 0.080442242 | AD8: 308 | AE8: =AD8/U8 -> 0.1174228 | AF8: 2562 | AG8: 110 | AH8: =AG8/AF8 -> 0.042935207 | AI8: 1489 | AJ8: =AI8/AF8 -> 0.58118657 | AK8: 18 | AL8: =AK8/AF8 -> 0.0070257611 | AM8: 601 | AN8: =AM8/AF8 -> 0.23458236 | AO8: 344 | AP8: =AO8/AF8 -> 0.1342701 | AQ8: =SUM(U8,AF8) -> 5185 | AR8: =SUM(V8,AG8) -> 235 | AS8: =AR8/AQ8 -> 0.045323047 | AT8: =SUM(X8,AI8) -> 3381 | AU8: =AT8/AQ8 -> 0.65207329 | AV8: =SUM(Z8,AK8) -> 105 | AW8: =AV8/AQ8 -> 0.020250723 | AX8: =SUM(AB8,AM8) -> 812 | AY8: =AX8/AQ8 -> 0.15660559 | AZ8: =SUM(AD8,AO8) -> 652 | BA8: =AZ8/AQ8 -> 0.12574735 | BB8: 2599 | BC8: 811 | BD8: =BC8/BB8 -> 0.31204309 | BE8: 2524 | BF8: 661 | BG8: =BF8/BE8 -> 0.2618859 | BH8: =SUM(BB8,BE8) -> 5123 | BI8: =SUM(BC8,BF8) -> 1472 | BJ8: =BI8/BH8 -> 0.28733164 | BK8: 5185 | BL8: 1231 | BM8: =BL8/BK8 -> 0.23741562 | BN8: 2623 | BO8: 507 | BP8: =BO8/BN8 -> 0.19329013 | BQ8: 2562 | BR8: 724 | BS8: =BR8/BQ8 -> 0.28259173 | BT8: 16838 | BU8: 5636 | BV8: =BU8/BT8 -> 0.33471909 | BW8: =BU8/$BU8 -> 1 | BX8: 14304 | BY8: 5283 | BZ8: =BY8/BX8 -> 0.36933725 | CA8: =BY8/$BU8 -> 0.93736693 | CB8: 108 | CC8: 11 | CD8: =CC8/CB8 -> 0.10185185 | CE8: =CC8/$BU8 -> 0.0019517388 | CF8: 1475 | CG8: 226 | CH8: =CG8/CF8 -> 0.15322034 | CI8: =CG8/$BU8 -> 0.040099361 | CJ8: 88 | CK8: 9 | CL8: =CK8/CJ8 -> 0.10227273 | CM8: =CK8/$BU8 -> 0.0015968772 | CN8: 2 | CO8: 1 | CP8: =CO8/CN8 -> 0.5 | CQ8: =CO8/$BU8 -> 0.0001774308 | CR8: 42 | CS8: 0 | CT8: =CS8/CR8 -> 0 | CU8: =CS8/$BU8 -> 0 | CV8: 460 | CW8: 65 | CX8: =CW8/CV8 -> 0.14130435 | CY8: =CW8/$BU8 -> 0.011533002 | CZ8: 401 | DA8: 41 | DB8: =DA8/CZ8 -> 0.10224439 | DC8: =DA8/BU8 -> 0.0072746629 | DD8: 2623 | DE8: 68 | DF8: 764 | DG8: 765 | DH8: 1026 | DI8: =DE8/DD8 -> 0.025924514 | DJ8: =DF8/DD8 -> 0.29126954 | DK8: =SUM(DG8:DH8)/DD8 -> 0.68280595 | DL8: 2562 | DM8: 146 | DN8: 671 | DO8: 798 | DP8: 947 | DQ8: =DM8/DL8 -> 0.056986729 | DR8: =DN8/DL8 -> 0.26190476 | DS8: =SUM(DO8:DP8)/DL8 -> 0.68110851 | DT8: =SUM(DL8,DD8) -> 5185 | DU8: =SUM(DM8,DE8) -> 214 | DV8: =SUM(DN8,DF8) -> 1435 | DW8: =SUM(DO8,DG8) -> 1563 | DX8: =SUM(DP8,DH8) -> 1973 | DY8: =DU8/DT8 -> 0.041272903 | DZ8: =DV8/DT8 -> 0.27675988 | EA8: =SUM(DW8:DX8)/DT8 -> 0.68196721 | EB8: 3288 | EC8: 256 | ED8: =EC8/$EB8 -> 0.077858881 | EE8: 575 | EF8: =EE8/$EB8 -> 0.17487835 | EG8: 953 | EH8: =EG8/$EB8 -> 0.28984185 | EI8: 1341 | EJ8: =EI8/$EB8 -> 0.40784672 | EK8: 2133 | EL8: =EK8/$EB8 -> 0.64872263 | EM8: 2680 | EN8: =EM8/$EB8 -> 0.81508516 | EO8: 71151 | EP8: 49375 | EQ8: 82287 | ER8: 90231 | ES8: 59286 | ET8: 2599 | EU8: 159 | EV8: =EU8/ET8 -> 0.061177376 | EW8: 2524 | EX8: 199 | EY8: =EX8/EW8 -> 0.078843106 | EZ8: =SUM(ET8,EW8) -> 5123 | FA8: =SUM(EU8,EX8) -> 358 | FB8: =FA8/EZ8 -> 0.069880929 | FC8: 5123 | FD8: 358 | FE8: =FD8/$FC8 -> 0.069880929 | FF8: 772 | FG8: =FF8/$FC8 -> 0.15069295 | FH8: 1078 | FI8: =FH8/$FC8 -> 0.21042358 | FJ8: 1272 | FK8: =FJ8/$FC8 -> 0.24829202 | FL8: 2196 | FM8: =FL8/$FC8 -> 0.42865508 | FN8: 388 | FO8: 0.2305407 | FP8: 11 | FQ8: 0.0065359477 | FR8: 66 | FS8: 0.070212766 | FT8: 0 | FU8: 0 | FV8: 395 | FW8: 0.2467208 | FX8: 7 | FY8: 0.0043722673 | FZ8: 69 | GA8: 0.071800208 | GB8: 0 | GC8: 0 | GD8: 918 | GE8: 0.17704918 | GF8: 18 | GG8: 0.0034715526 | GH8: 3288 | GI8: 374 | GJ8: =GI8/GH8 -> 0.11374696 | GK8: 152 | GL8: =GK8/GI8 -> 0.40641711 | GM8: 164 | GN8: =GM8/GI8 -> 0.43850267 | GO8: 2914 | GP8: =GO8/GH8 -> 0.88625304 | GQ8: 2264 | GR8: =GQ8/GO8 -> 0.77693892 | GS8: 645 | GT8: =GS8/GO8 -> 0.22134523
A9: Brown | B9: 270892 | C9: 61112 | D9: 44324 | E9: 17095 | F9: 4364 | G9: =C9/B9 -> 0.22559544 | H9: =D9/B9 -> 0.1636224 | I9: =E9/B9 -> 0.06310633 | J9: =F9/B9 -> 0.016109741 | K9: 20365 | L9: =K9/D9 -> 0.45945763 | M9: 23959 | N9: =M9/D9 -> 0.54054237 | O9: 38.2 | P9: 110933 | Q9: 42474 | R9: =Q9/P9 -> 0.38287976 | S9: 31870 | T9: =S9/P9 -> 0.28729053 | U9: 20365 | V9: 1234 | W9: =V9/U9 -> 0.060594157 | X9: 13136 | Y9: =X9/U9 -> 0.64502823 | Z9: 588 | AA9: =Z9/U9 -> 0.028873067 | AB9: 2245 | AC9: =AB9/U9 -> 0.11023815 | AD9: 3162 | AE9: =AD9/U9 -> 0.15526639 | AF9: 23959 | AG9: 1529 | AH9: =AG9/AF9 -> 0.063817355 | AI9: 10809 | AJ9: =AI9/AF9 -> 0.45114571 | AK9: 442 | AL9: =AK9/AF9 -> 0.018448182 | AM9: 7025 | AN9: =AM9/AF9 -> 0.29320923 | AO9: 4154 | AP9: =AO9/AF9 -> 0.17337952 | AQ9: =SUM(U9,AF9) -> 44324 | AR9: =SUM(V9,AG9) -> 2763 | AS9: =AR9/AQ9 -> 0.062336432 | AT9: =SUM(X9,AI9) -> 23945 | AU9: =AT9/AQ9 -> 0.54022651 | AV9: =SUM(Z9,AK9) -> 1030 | AW9: =AV9/AQ9 -> 0.023237975 | AX9: =SUM(AB9,AM9) -> 9270 | AY9: =AX9/AQ9 -> 0.20914177 | AZ9: =SUM(AD9,AO9) -> 7316 | BA9: =AZ9/AQ9 -> 0.16505731 | BB9: 20041 | BC9: 5841 | BD9: =BC9/BB9 -> 0.29145252 | BE9: 23462 | BF9: 5973 | BG9: =BF9/BE9 -> 0.25458188 | BH9: =SUM(BB9,BE9) -> 43503 | BI9: =SUM(BC9,BF9) -> 11814 | BJ9: =BI9/BH9 -> 0.27156748 | BK9: 44324 | BL9: 13782 | BM9: =BL9/BK9 -> 0.31093764 | BN9: 20365 | BO9: 4796 | BP9: =BO9/BN9 -> 0.23550209 | BQ9: 23959 | BR9: 8986 | BS9: =BR9/BQ9 -> 0.37505739 | BT9: 273909 | BU9: 47490 | BV9: =BU9/BT9 -> 0.17337875 | BW9: =BU9/$BU9 -> 1 | BX9: 212413 | BY9: 44327 | BZ9: =BY9/BX9 -> 0.20868308 | CA9: =BY9/$BU9 -> 0.9333965 | CB9: 8315 | CC9: 309 | CD9: =CC9/CB9 -> 0.037161756 | CE9: =CC9/$BU9 -> 0.006506633 | CF9: 6565 | CG9: 762 | CH9: =CG9/CF9 -> 0.11607007 | CI9: =CG9/$BU9 -> 0.016045483 | CJ9: 10647 | CK9: 547 | CL9: =CK9/CJ9 -> 0.051375974 | CM9: =CK9/$BU9 -> 0.011518214 | CN9: 133 | CO9: 16 | CP9: =CO9/CN9 -> 0.12030075 | CQ9: =CO9/$BU9 -> 0.00033691303 | CR9: 5458 | CS9: 31 | CT9: =CS9/CR9 -> 0.0056797362 | CU9: =CS9/$BU9 -> 0.000652769 | CV9: 6301 | CW9: 222 | CX9: =CW9/CV9 -> 0.035232503 | CY9: =CW9/$BU9 -> 0.0046746684 | CZ9: 29535 | DA9: 1307 | DB9: =DA9/CZ9 -> 0.044252582 | DC9: =DA9/BU9 -> 0.027521583 | DD9: 20365 | DE9: 1302 | DF9: 6554 | DG9: 6209 | DH9: 6300 | DI9: =DE9/DD9 -> 0.063933219 | DJ9: =DF9/DD9 -> 0.32182666 | DK9: =SUM(DG9:DH9)/DD9 -> 0.61424012 | DL9: 23959 | DM9: 1399 | DN9: 10781 | DO9: 6635 | DP9: 5144 | DQ9: =DM9/DL9 -> 0.058391419 | DR9: =DN9/DL9 -> 0.44997704 | DS9: =SUM(DO9:DP9)/DL9 -> 0.49163154 | DT9: =SUM(DL9,DD9) -> 44324 | DU9: =SUM(DM9,DE9) -> 2701 | DV9: =SUM(DN9,DF9) -> 17335 | DW9: =SUM(DO9,DG9) -> 12844 | DX9: =SUM(DP9,DH9) -> 11444 | DY9: =DU9/DT9 -> 0.060937641 | DZ9: =DV9/DT9 -> 0.39109737 | EA9: =SUM(DW9:DX9)/DT9 -> 0.54796499 | EB9: 28946 | EC9: 2480 | ED9: =EC9/$EB9 -> 0.085676777 | EE9: 5310 | EF9: =EE9/$EB9 -> 0.18344504 | EG9: 9006 | EH9: =EG9/$EB9 -> 0.31113107 | EI9: 12896 | EJ9: =EI9/$EB9 -> 0.44551924 | EK9: 18340 | EL9: =EK9/$EB9 -> 0.63359359 | EM9: 22539 | EN9: =EM9/$EB9 -> 0.77865681 | EO9: 79649 | EP9: 49858 | EQ9: 90857 | ER9: 92652 | ES9: 57169 | ET9: 20041 | EU9: 1466 | EV9: =EU9/ET9 -> 0.073150042 | EW9: 23462 | EX9: 2044 | EY9: =EX9/EW9 -> 0.087119598 | EZ9: =SUM(ET9,EW9) -> 43503 | FA9: =SUM(EU9,EX9) -> 3510 | FB9: =FA9/EZ9 -> 0.080684091 | FC9: 43503 | FD9: 3510 | FE9: =FD9/$FC9 -> 0.080684091 | FF9: 6539 | FG9: =FF9/$FC9 -> 0.15031147 | FH9: 9383 | FI9: =FH9/$FC9 -> 0.21568627 | FJ9: 10954 | FK9: =FJ9/$FC9 -> 0.25179873 | FL9: 18332 | FM9: =FL9/$FC9 -> 0.42139623 | FN9: 3261 | FO9: 0.24933099 | FP9: 66 | FQ9: 0.0050462574 | FR9: 329 | FS9: 0.045155092 | FT9: 0 | FU9: 0 | FV9: 2379 | FW9: 0.16812721 | FX9: 37 | FY9: 0.002614841 | FZ9: 579 | GA9: 0.059027424 | GB9: 0 | GC9: 0 | GD9: 6548 | GE9: 0.14773035 | GF9: 103 | GG9: 0.0023237975 | GH9: 28946 | GI9: 7917 | GJ9: =GI9/GH9 -> 0.27350929 | GK9: 3071 | GL9: =GK9/GI9 -> 0.38789946 | GM9: 4345 | GN9: =GM9/GI9 -> 0.548819 | GO9: 21029 | GP9: =GO9/GH9 -> 0.72649071 | GQ9: 16581 | GR9: =GQ9/GO9 -> 0.78848257 | GS9: 4277 | GT9: =GS9/GO9 -> 0.2033858
A10: Buffalo | B10: 13393 | C10: 4353 | D10: 3218 | E10: 1328 | F10: 382 | G10: =C10/B10 -> 0.32502053 | H10: =D10/B10 -> 0.24027477 | I10: =E10/B10 -> 0.099156276 | J10: =F10/B10 -> 0.028522362 | K10: 1637 | L10: =K10/D10 -> 0.50870106 | M10: 1581 | N10: =M10/D10 -> 0.49129894 | O10: 46.5 | P10: 5720 | Q10: 2948 | R10: =Q10/P10 -> 0.51538462 | S10: 2293 | T10: =S10/P10 -> 0.40087413 | U10: 1637 | V10: 129 | W10: =V10/U10 -> 0.078802688 | X10: 1092 | Y10: =X10/U10 -> 0.66707392 | Z10: 50 | AA10: =Z10/U10 -> 0.030543677 | AB10: 150 | AC10: =AB10/U10 -> 0.091631032 | AD10: 216 | AE10: =AD10/U10 -> 0.13194869 | AF10: 1581 | AG10: 45 | AH10: =AG10/AF10 -> 0.028462998 | AI10: 751 | AJ10: =AI10/AF10 -> 0.47501581 | AK10: 43 | AL10: =AK10/AF10 -> 0.027197976 | AM10: 493 | AN10: =AM10/AF10 -> 0.31182796 | AO10: 249 | AP10: =AO10/AF10 -> 0.15749526 | AQ10: =SUM(U10,AF10) -> 3218 | AR10: =SUM(V10,AG10) -> 174 | AS10: =AR10/AQ10 -> 0.054070851 | AT10: =SUM(X10,AI10) -> 1843 | AU10: =AT10/AQ10 -> 0.57271597 | AV10: =SUM(Z10,AK10) -> 93 | AW10: =AV10/AQ10 -> 0.028899938 | AX10: =SUM(AB10,AM10) -> 643 | AY10: =AX10/AQ10 -> 0.19981355 | AZ10: =SUM(AD10,AO10) -> 465 | BA10: =AZ10/AQ10 -> 0.14449969 | BB10: 1628 | BC10: 594 | BD10: =BC10/BB10 -> 0.36486486 | BE10: 1567 | BF10: 442 | BG10: =BF10/BE10 -> 0.28206765 | BH10: =SUM(BB10,BE10) -> 3195 | BI10: =SUM(BC10,BF10) -> 1036 | BJ10: =BI10/BH10 -> 0.32425665 | BK10: 3218 | BL10: 979 | BM10: =BL10/BK10 -> 0.30422623 | BN10: 1637 | BO10: 381 | BP10: =BO10/BN10 -> 0.23274282 | BQ10: 1581 | BR10: 598 | BS10: =BR10/BQ10 -> 0.37824162 | BT10: 13464 | BU10: 3434 | BV10: =BU10/BT10 -> 0.25505051 | BW10: =BU10/$BU10 -> 1 | BX10: 12699 | BY10: 3369 | BZ10: =BY10/BX10 -> 0.26529648 | CA10: =BY10/$BU10 -> 0.98107164 | CB10: 77 | CC10: 5 | CD10: =CC10/CB10 -> 0.064935065 | CE10: =CC10/$BU10 -> 0.001456028 | CF10: 54 | CG10: 7 | CH10: =CG10/CF10 -> 0.12962963 | CI10: =CG10/$BU10 -> 0.0020384391 | CJ10: 58 | CK10: 5 | CL10: =CK10/CJ10 -> 0.086206897 | CM10: =CK10/$BU10 -> 0.001456028 | CN10: 0 | CO10: 0 | CP10: 0 | CQ10: =CO10/$BU10 -> 0 | CR10: 132 | CS10: 0 | CT10: =CS10/CR10 -> 0 | CU10: =CS10/$BU10 -> 0 | CV10: 149 | CW10: 25 | CX10: =CW10/CV10 -> 0.16778523 | CY10: =CW10/$BU10 -> 0.0072801398 | CZ10: 427 | DA10: 23 | DB10: =DA10/CZ10 -> 0.053864169 | DC10: =DA10/BU10 -> 0.0066977286 | DD10: 1637 | DE10: 202 | DF10: 721 | DG10: 383 | DH10: 331 | DI10: =DE10/DD10 -> 0.12339646 | DJ10: =DF10/DD10 -> 0.44043983 | DK10: =SUM(DG10:DH10)/DD10 -> 0.43616371 | DL10: 1581 | DM10: 175 | DN10: 664 | DO10: 365 | DP10: 377 | DQ10: =DM10/DL10 -> 0.11068944 | DR10: =DN10/DL10 -> 0.41998735 | DS10: =SUM(DO10:DP10)/DL10 -> 0.46932321 | DT10: =SUM(DL10,DD10) -> 3218 | DU10: =SUM(DM10,DE10) -> 377 | DV10: =SUM(DN10,DF10) -> 1385 | DW10: =SUM(DO10,DG10) -> 748 | DX10: =SUM(DP10,DH10) -> 708 | DY10: =DU10/DT10 -> 0.11715351 | DZ10: =DV10/DT10 -> 0.43039155 | EA10: =SUM(DW10:DX10)/DT10 -> 0.45245494 | EB10: 2080 | EC10: 230 | ED10: =EC10/$EB10 -> 0.11057692 | EE10: 523 | EF10: =EE10/$EB10 -> 0.25144231 | EG10: 779 | EH10: =EG10/$EB10 -> 0.37451923 | EI10: 1101 | EJ10: =EI10/$EB10 -> 0.52932692 | EK10: 1525 | EL10: =EK10/$EB10 -> 0.73317308 | EM10: 1771 | EN10: =EM10/$EB10 -> 0.85144231 | EO10: 70479 | EP10: 44821 | EQ10: 86216 | ER10: 96181 | ES10: 46625 | ET10: 1628 | EU10: 120 | EV10: =EU10/ET10 -> 0.073710074 | EW10: 1567 | EX10: 222 | EY10: =EX10/EW10 -> 0.14167198 | EZ10: =SUM(ET10,EW10) -> 3195 | FA10: =SUM(EU10,EX10) -> 342 | FB10: =FA10/EZ10 -> 0.10704225 | FC10: 3195 | FD10: 342 | FE10: =FD10/$FC10 -> 0.10704225 | FF10: 680 | FG10: =FF10/$FC10 -> 0.21283255 | FH10: 944 | FI10: =FH10/$FC10 -> 0.29546166 | FJ10: 1058 | FK10: =FJ10/$FC10 -> 0.33114241 | FL10: 1674 | FM10: =FL10/$FC10 -> 0.52394366 | FN10: 319 | FO10: 0.31490622 | FP10: 24 | FQ10: 0.023692004 | FR10: 75 | FS10: 0.12019231 | FT10: 0 | FU10: 0 | FV10: 162 | FW10: 0.18472064 | FX10: 12 | FY10: 0.01368301 | FZ10: 32 | GA10: 0.045454545 | GB10: 0 | GC10: 0 | GD10: 588 | GE10: 0.18272219 | GF10: 36 | GG10: 0.011187073 | GH10: 2080 | GI10: 422 | GJ10: =GI10/GH10 -> 0.20288462 | GK10: 191 | GL10: =GK10/GI10 -> 0.45260664 | GM10: 148 | GN10: =GM10/GI10 -> 0.3507109 | GO10: 1658 | GP10: =GO10/GH10 -> 0.79711538 | GQ10: 1147 | GR10: =GQ10/GO10 -> 0.69179735 | GS10: 496 | GT10: =GS10/GO10 -> 0.29915561
A11: Burnett | B11: 16916 | C11: 7320 | D11: 5460 | E11: 2033 | F11: 516 | G11: =C11/B11 -> 0.43272641 | H11: =D11/B11 -> 0.32277134 | I11: =E11/B11 -> 0.12018208 | J11: =F11/B11 -> 0.030503665 | K11: 2804 | L11: =K11/D11 -> 0.51355311 | M11: 2656 | N11: =M11/D11 -> 0.48644689 | O11: 56 | P11: 7188 | Q11: 4678 | R11: =Q11/P11 -> 0.6508069 | S11: 3674 | T11: =S11/P11 -> 0.51112966 | U11: 2804 | V11: 196 | W11: =V11/U11 -> 0.069900143 | X11: 1693 | Y11: =X11/U11 -> 0.60378031 | Z11: 117 | AA11: =Z11/U11 -> 0.041726106 | AB11: 295 | AC11: =AB11/U11 -> 0.10520685 | AD11: 503 | AE11: =AD11/U11 -> 0.17938659 | AF11: 2656 | AG11: 128 | AH11: =AG11/AF11 -> 0.048192771 | AI11: 1514 | AJ11: =AI11/AF11 -> 0.57003012 | AK11: 33 | AL11: =AK11/AF11 -> 0.012424699 | AM11: 631 | AN11: =AM11/AF11 -> 0.2375753 | AO11: 350 | AP11: =AO11/AF11 -> 0.13177711 | AQ11: =SUM(U11,AF11) -> 5460 | AR11: =SUM(V11,AG11) -> 324 | AS11: =AR11/AQ11 -> 0.059340659 | AT11: =SUM(X11,AI11) -> 3207 | AU11: =AT11/AQ11 -> 0.58736264 | AV11: =SUM(Z11,AK11) -> 150 | AW11: =AV11/AQ11 -> 0.027472527 | AX11: =SUM(AB11,AM11) -> 926 | AY11: =AX11/AQ11 -> 0.16959707 | AZ11: =SUM(AD11,AO11) -> 853 | BA11: =AZ11/AQ11 -> 0.15622711 | BB11: 2794 | BC11: 900 | BD11: =BC11/BB11 -> 0.32211883 | BE11: 2617 | BF11: 735 | BG11: =BF11/BE11 -> 0.28085594 | BH11: =SUM(BB11,BE11) -> 5411 | BI11: =SUM(BC11,BF11) -> 1635 | BJ11: =BI11/BH11 -> 0.30216226 | BK11: 5460 | BL11: 1436 | BM11: =BL11/BK11 -> 0.26300366 | BN11: 2804 | BO11: 724 | BP11: =BO11/BN11 -> 0.25820257 | BQ11: 2656 | BR11: 712 | BS11: =BR11/BQ11 -> 0.26807229 | BT11: 17187 | BU11: 5899 | BV11: =BU11/BT11 -> 0.34322453 | BW11: =BU11/$BU11 -> 1 | BX11: 15579 | BY11: 5617 | BZ11: =BY11/BX11 -> 0.36054946 | CA11: =BY11/$BU11 -> 0.95219529 | CB11: 138 | CC11: 22 | CD11: =CC11/CB11 -> 0.15942029 | CE11: =CC11/$BU11 -> 0.0037294457 | CF11: 644 | CG11: 141 | CH11: =CG11/CF11 -> 0.2189441 | CI11: =CG11/$BU11 -> 0.023902356 | CJ11: 86 | CK11: 17 | CL11: =CK11/CJ11 -> 0.19767442 | CM11: =CK11/$BU11 -> 0.0028818444 | CN11: 9 | CO11: 2 | CP11: =CO11/CN11 -> 0.22222222 | CQ11: =CO11/$BU11 -> 0.00033904052 | CR11: 43 | CS11: 1 | CT11: =CS11/CR11 -> 0.023255814 | CU11: =CS11/$BU11 -> 0.00016952026 | CV11: 377 | CW11: 66 | CX11: =CW11/CV11 -> 0.17506631 | CY11: =CW11/$BU11 -> 0.011188337 | CZ11: 354 | DA11: 34 | DB11: =DA11/CZ11 -> 0.096045198 | DC11: =DA11/BU11 -> 0.0057636888 | DD11: 2804 | DE11: 254 | DF11: 989 | DG11: 851 | DH11: 710 | DI11: =DE11/DD11 -> 0.090584879 | DJ11: =DF11/DD11 -> 0.35271041 | DK11: =SUM(DG11:DH11)/DD11 -> 0.55670471 | DL11: 2656 | DM11: 140 | DN11: 1196 | DO11: 812 | DP11: 508 | DQ11: =DM11/DL11 -> 0.052710843 | DR11: =DN11/DL11 -> 0.4503012 | DS11: =SUM(DO11:DP11)/DL11 -> 0.49698795 | DT11: =SUM(DL11,DD11) -> 5460 | DU11: =SUM(DM11,DE11) -> 394 | DV11: =SUM(DN11,DF11) -> 2185 | DW11: =SUM(DO11,DG11) -> 1663 | DX11: =SUM(DP11,DH11) -> 1218 | DY11: =DU11/DT11 -> 0.072161172 | DZ11: =DV11/DT11 -> 0.40018315 | EA11: =SUM(DW11:DX11)/DT11 -> 0.52765568 | EB11: 3371 | EC11: 363 | ED11: =EC11/$EB11 -> 0.10768318 | EE11: 698 | EF11: =EE11/$EB11 -> 0.20706022 | EG11: 1126 | EH11: =EG11/$EB11 -> 0.33402551 | EI11: 1544 | EJ11: =EI11/$EB11 -> 0.45802433 | EK11: 2341 | EL11: =EK11/$EB11 -> 0.69445268 | EM11: 2720 | EN11: =EM11/$EB11 -> 0.80688223 | EO11: 62819 | EP11: 51250 | EQ11: 87500 | ER11: 71550 | ES11: 53472 | ET11: 2794 | EU11: 292 | EV11: =EU11/ET11 -> 0.10450966 | EW11: 2617 | EX11: 305 | EY11: =EX11/EW11 -> 0.11654566 | EZ11: =SUM(ET11,EW11) -> 5411 | FA11: =SUM(EU11,EX11) -> 597 | FB11: =FA11/EZ11 -> 0.11033081 | FC11: 5411 | FD11: 597 | FE11: =FD11/$FC11 -> 0.11033081 | FF11: 946 | FG11: =FF11/$FC11 -> 0.17482905 | FH11: 1348 | FI11: =FH11/$FC11 -> 0.24912216 | FJ11: 1465 | FK11: =FJ11/$FC11 -> 0.27074478 | FL11: 2521 | FM11: =FL11/$FC11 -> 0.46590279 | FN11: 323 | FO11: 0.18074986 | FP11: 6 | FQ11: 0.0033575825 | FR11: 58 | FS11: 0.057030482 | FT11: 2 | FU11: 0.0019665683 | FV11: 303 | FW11: 0.1847561 | FX11: 0 | FY11: 0 | FZ11: 51 | GA11: 0.05019685 | GB11: 0 | GC11: 0 | GD11: 735 | GE11: 0.13461538 | GF11: 8 | GG11: 0.0014652015 | GH11: 3371 | GI11: 448 | GJ11: =GI11/GH11 -> 0.13289825 | GK11: 176 | GL11: =GK11/GI11 -> 0.39285714 | GM11: 147 | GN11: =GM11/GI11 -> 0.328125 | GO11: 2923 | GP11: =GO11/GH11 -> 0.86710175 | GQ11: 2300 | GR11: =GQ11/GO11 -> 0.78686281 | GS11: 590 | GT11: =GS11/GO11 -> 0.20184742
A12: Calumet | B12: 52942 | C12: 12889 | D12: 9104 | E12: 3407 | F12: 885 | G12: =C12/B12 -> 0.2434551 | H12: =D12/B12 -> 0.17196177 | I12: =E12/B12 -> 0.064353443 | J12: =F12/B12 -> 0.016716407 | K12: 4298 | L12: =K12/D12 -> 0.47210018 | M12: 4806 | N12: =M12/D12 -> 0.52789982 | O12: 41.7 | P12: 21372 | Q12: 8792 | R12: =Q12/P12 -> 0.41137937 | S12: 6540 | T12: =S12/P12 -> 0.30600786 | U12: 4298 | V12: 294 | W12: =V12/U12 -> 0.068403909 | X12: 2953 | Y12: =X12/U12 -> 0.68706375 | Z12: 163 | AA12: =Z12/U12 -> 0.037924616 | AB12: 490 | AC12: =AB12/U12 -> 0.11400651 | AD12: 398 | AE12: =AD12/U12 -> 0.09260121 | AF12: 4806 | AG12: 181 | AH12: =AG12/AF12 -> 0.037661257 | AI12: 2593 | AJ12: =AI12/AF12 -> 0.53953392 | AK12: 89 | AL12: =AK12/AF12 -> 0.018518519 | AM12: 1325 | AN12: =AM12/AF12 -> 0.27569705 | AO12: 618 | AP12: =AO12/AF12 -> 0.12858926 | AQ12: =SUM(U12,AF12) -> 9104 | AR12: =SUM(V12,AG12) -> 475 | AS12: =AR12/AQ12 -> 0.052174868 | AT12: =SUM(X12,AI12) -> 5546 | AU12: =AT12/AQ12 -> 0.60918278 | AV12: =SUM(Z12,AK12) -> 252 | AW12: =AV12/AQ12 -> 0.027680141 | AX12: =SUM(AB12,AM12) -> 1815 | AY12: =AX12/AQ12 -> 0.19936292 | AZ12: =SUM(AD12,AO12) -> 1016 | BA12: =AZ12/AQ12 -> 0.1115993 | BB12: 4270 | BC12: 1155 | BD12: =BC12/BB12 -> 0.2704918 | BE12: 4750 | BF12: 1211 | BG12: =BF12/BE12 -> 0.25494737 | BH12: =SUM(BB12,BE12) -> 9020 | BI12: =SUM(BC12,BF12) -> 2366 | BJ12: =BI12/BH12 -> 0.26230599 | BK12: 9104 | BL12: 2547 | BM12: =BL12/BK12 -> 0.27976714 | BN12: 4298 | BO12: 984 | BP12: =BO12/BN12 -> 0.22894369 | BQ12: 4806 | BR12: 1563 | BS12: =BR12/BQ12 -> 0.32521848 | BT12: 53602 | BU12: 10036 | BV12: =BU12/BT12 -> 0.18723182 | BW12: =BU12/$BU12 -> 1 | BX12: 47077 | BY12: 9664 | BZ12: =BY12/BX12 -> 0.20528071 | CA12: =BY12/$BU12 -> 0.96293344 | CB12: 602 | CC12: 26 | CD12: =CC12/CB12 -> 0.043189369 | CE12: =CC12/$BU12 -> 0.0025906736 | CF12: 264 | CG12: 37 | CH12: =CG12/CF12 -> 0.14015152 | CI12: =CG12/$BU12 -> 0.0036867278 | CJ12: 1635 | CK12: 120 | CL12: =CK12/CJ12 -> 0.073394495 | CM12: =CK12/$BU12 -> 0.011956955 | CN12: 30 | CO12: 2 | CP12: =CO12/CN12 -> 0.066666667 | CQ12: =CO12/$BU12 -> 0.00019928258 | CR12: 329 | CS12: 0 | CT12: =CS12/CR12 -> 0 | CU12: =CS12/$BU12 -> 0 | CV12: 809 | CW12: 48 | CX12: =CW12/CV12 -> 0.059332509 | CY12: =CW12/$BU12 -> 0.004782782 | CZ12: 3185 | DA12: 139 | DB12: =DA12/CZ12 -> 0.043642072 | DC12: =DA12/BU12 -> 0.013850139 | DD12: 4298 | DE12: 304 | DF12: 1898 | DG12: 1165 | DH12: 931 | DI12: =DE12/DD12 -> 0.070730572 | DJ12: =DF12/DD12 -> 0.44160074 | DK12: =SUM(DG12:DH12)/DD12 -> 0.48766868 | DL12: 4806 | DM12: 319 | DN12: 2187 | DO12: 1523 | DP12: 777 | DQ12: =DM12/DL12 -> 0.066375364 | DR12: =DN12/DL12 -> 0.45505618 | DS12: =SUM(DO12:DP12)/DL12 -> 0.47856846 | DT12: =SUM(DL12,DD12) -> 9104 | DU12: =SUM(DM12,DE12) -> 623 | DV12: =SUM(DN12,DF12) -> 4085 | DW12: =SUM(DO12,DG12) -> 2688 | DX12: =SUM(DP12,DH12) -> 1708 | DY12: =DU12/DT12 -> 0.068431459 | DZ12: =DV12/DT12 -> 0.44870387 | EA12: =SUM(DW12:DX12)/DT12 -> 0.48286467 | EB12: 6028 | EC12: 406 | ED12: =EC12/$EB12 -> 0.067352356 | EE12: 942 | EF12: =EE12/$EB12 -> 0.15627074 | EG12: 1961 | EH12: =EG12/$EB12 -> 0.3253152 | EI12: 2979 | EJ12: =EI12/$EB12 -> 0.49419376 | EK12: 4506 | EL12: =EK12/$EB12 -> 0.74751161 | EM12: 5120 | EN12: =EM12/$EB12 -> 0.84936961 | EO12: 88810 | EP12: 43631 | EQ12: 112699 | ER12: 112092 | ES12: 50433 | ET12: 4270 | EU12: 341 | EV12: =EU12/ET12 -> 0.079859485 | EW12: 4750 | EX12: 492 | EY12: =EX12/EW12 -> 0.10357895 | EZ12: =SUM(ET12,EW12) -> 9020 | FA12: =SUM(EU12,EX12) -> 833 | FB12: =FA12/EZ12 -> 0.092350333 | FC12: 9020 | FD12: 833 | FE12: =FD12/$FC12 -> 0.092350333 | FF12: 1301 | FG12: =FF12/$FC12 -> 0.14423503 | FH12: 2009 | FI12: =FH12/$FC12 -> 0.22272727 | FJ12: 2191 | FK12: =FJ12/$FC12 -> 0.24290466 | FL12: 4472 | FM12: =FL12/$FC12 -> 0.49578714 | FN12: 516 | FO12: 0.18527828 | FP12: 0 | FQ12: 0 | FR12: 97 | FS12: 0.064111038 | FT12: 0 | FU12: 0 | FV12: 581 | FW12: 0.19951923 | FX12: 25 | FY12: 0.0085851648 | FZ12: 38 | GA12: 0.020063358 | GB12: 0 | GC12: 0 | GD12: 1232 | GE12: 0.13532513 | GF12: 25 | GG12: 0.0027460457 | GH12: 6028 | GI12: 1074 | GJ12: =GI12/GH12 -> 0.17816855 | GK12: 311 | GL12: =GK12/GI12 -> 0.28957169 | GM12: 691 | GN12: =GM12/GI12 -> 0.6433892 | GO12: 4954 | GP12: =GO12/GH12 -> 0.82183145 | GQ12: 3691 | GR12: =GQ12/GO12 -> 0.7450545 | GS12: 1222 | GT12: =GS12/GO12 -> 0.24666936
A13: Chippewa | B13: 66799 | C13: 18379 | D13: 13188 | E13: 5270 | F13: 1582 | G13: =C13/B13 -> 0.27513885 | H13: =D13/B13 -> 0.19742811 | I13: =E13/B13 -> 0.078893397 | J13: =F13/B13 -> 0.023682989 | K13: 6307 | L13: =K13/D13 -> 0.47823779 | M13: 6881 | N13: =M13/D13 -> 0.52176221 | O13: 42.2 | P13: 27139 | Q13: 12125 | R13: =Q13/P13 -> 0.44677402 | S13: 9155 | T13: =S13/P13 -> 0.33733741 | U13: 6307 | V13: 353 | W13: =V13/U13 -> 0.055969558 | X13: 4148 | Y13: =X13/U13 -> 0.65768194 | Z13: 96 | AA13: =Z13/U13 -> 0.015221183 | AB13: 869 | AC13: =AB13/U13 -> 0.13778342 | AD13: 841 | AE13: =AD13/U13 -> 0.1333439 | AF13: 6881 | AG13: 429 | AH13: =AG13/AF13 -> 0.062345589 | AI13: 3303 | AJ13: =AI13/AF13 -> 0.48001744 | AK13: 107 | AL13: =AK13/AF13 -> 0.015550065 | AM13: 1986 | AN13: =AM13/AF13 -> 0.28862084 | AO13: 1056 | AP13: =AO13/AF13 -> 0.15346607 | AQ13: =SUM(U13,AF13) -> 13188 | AR13: =SUM(V13,AG13) -> 782 | AS13: =AR13/AQ13 -> 0.05929633 | AT13: =SUM(X13,AI13) -> 7451 | AU13: =AT13/AQ13 -> 0.56498332 | AV13: =SUM(Z13,AK13) -> 203 | AW13: =AV13/AQ13 -> 0.015392781 | AX13: =SUM(AB13,AM13) -> 2855 | AY13: =AX13/AQ13 -> 0.21648468 | AZ13: =SUM(AD13,AO13) -> 1897 | BA13: =AZ13/AQ13 -> 0.14384289 | BB13: 6139 | BC13: 1708 | BD13: =BC13/BB13 -> 0.27822121 | BE13: 6666 | BF13: 1724 | BG13: =BF13/BE13 -> 0.25862586 | BH13: =SUM(BB13,BE13) -> 12805 | BI13: =SUM(BC13,BF13) -> 3432 | BJ13: =BI13/BH13 -> 0.2680203 | BK13: 13188 | BL13: 3893 | BM13: =BL13/BK13 -> 0.2951926 | BN13: 6307 | BO13: 1516 | BP13: =BO13/BN13 -> 0.24036785 | BQ13: 6881 | BR13: 2377 | BS13: =BR13/BQ13 -> 0.34544398 | BT13: 67323 | BU13: 14023 | BV13: =BU13/BT13 -> 0.20829434 | BW13: =BU13/$BU13 -> 1 | BX13: 62476 | BY13: 13708 | BZ13: =BY13/BX13 -> 0.21941225 | CA13: =BY13/$BU13 -> 0.9775369 | CB13: 1102 | CC13: 27 | CD13: =CC13/CB13 -> 0.024500907 | CE13: =CC13/$BU13 -> 0.0019254083 | CF13: 349 | CG13: 52 | CH13: =CG13/CF13 -> 0.14899713 | CI13: =CG13/$BU13 -> 0.0037081937 | CJ13: 1005 | CK13: 85 | CL13: =CK13/CJ13 -> 0.084577114 | CM13: =CK13/$BU13 -> 0.0060614704 | CN13: 24 | CO13: 4 | CP13: =CO13/CN13 -> 0.16666667 | CQ13: =CO13/$BU13 -> 0.00028524567 | CR13: 153 | CS13: 0 | CT13: =CS13/CR13 -> 0 | CU13: =CS13/$BU13 -> 0 | CV13: 977 | CW13: 74 | CX13: =CW13/CV13 -> 0.075742068 | CY13: =CW13/$BU13 -> 0.0052770449 | CZ13: 1390 | DA13: 73 | DB13: =DA13/CZ13 -> 0.052517986 | DC13: =DA13/BU13 -> 0.0052057334 | DD13: 6307 | DE13: 491 | DF13: 2719 | DG13: 1769 | DH13: 1328 | DI13: =DE13/DD13 -> 0.077850008 | DJ13: =DF13/DD13 -> 0.43110829 | DK13: =SUM(DG13:DH13)/DD13 -> 0.4910417 | DL13: 6881 | DM13: 310 | DN13: 3108 | DO13: 2166 | DP13: 1297 | DQ13: =DM13/DL13 -> 0.045051591 | DR13: =DN13/DL13 -> 0.45167854 | DS13: =SUM(DO13:DP13)/DL13 -> 0.50326987 | DT13: =SUM(DL13,DD13) -> 13188 | DU13: =SUM(DM13,DE13) -> 801 | DV13: =SUM(DN13,DF13) -> 5827 | DW13: =SUM(DO13,DG13) -> 3935 | DX13: =SUM(DP13,DH13) -> 2625 | DY13: =DU13/DT13 -> 0.060737034 | DZ13: =DV13/DT13 -> 0.44184107 | EA13: =SUM(DW13:DX13)/DT13 -> 0.4974219 | EB13: 8369 | EC13: 797 | ED13: =EC13/$EB13 -> 0.095232405 | EE13: 1551 | EF13: =EE13/$EB13 -> 0.1853268 | EG13: 2847 | EH13: =EG13/$EB13 -> 0.34018401 | EI13: 4007 | EJ13: =EI13/$EB13 -> 0.47879078 | EK13: 5792 | EL13: =EK13/$EB13 -> 0.69207791 | EM13: 6832 | EN13: =EM13/$EB13 -> 0.81634604 | EO13: 74680 | EP13: 49836 | EQ13: 92635 | ER13: 94612 | ES13: 51546 | ET13: 6139 | EU13: 513 | EV13: =EU13/ET13 -> 0.083564098 | EW13: 6666 | EX13: 676 | EY13: =EX13/EW13 -> 0.10141014 | EZ13: =SUM(ET13,EW13) -> 12805 | FA13: =SUM(EU13,EX13) -> 1189 | FB13: =FA13/EZ13 -> 0.092854354 | FC13: 12805 | FD13: 1189 | FE13: =FD13/$FC13 -> 0.092854354 | FF13: 2008 | FG13: =FF13/$FC13 -> 0.15681374 | FH13: 2820 | FI13: =FH13/$FC13 -> 0.22022647 | FJ13: 3678 | FK13: =FJ13/$FC13 -> 0.28723155 | FL13: 6043 | FM13: =FL13/$FC13 -> 0.47192503 | FN13: 1035 | FO13: 0.26005025 | FP13: 28 | FQ13: 0.0070351759 | FR13: 150 | FS13: 0.064460679 | FT13: 0 | FU13: 0 | FV13: 904 | FW13: 0.22955815 | FX13: 3 | FY13: 0.00076180802 | FZ13: 81 | GA13: 0.027522936 | GB13: 6 | GC13: 0.002038736 | GD13: 2170 | GE13: 0.16454352 | GF13: 37 | GG13: 0.0028055808 | GH13: 8369 | GI13: 1617 | GJ13: =GI13/GH13 -> 0.19321305 | GK13: 606 | GL13: =GK13/GI13 -> 0.37476809 | GM13: 896 | GN13: =GM13/GI13 -> 0.55411255 | GO13: 6752 | GP13: =GO13/GH13 -> 0.80678695 | GQ13: 5347 | GR13: =GQ13/GO13 -> 0.79191351 | GS13: 1343 | GT13: =GS13/GO13 -> 0.19890403
A14: Clark | B14: 34739 | C14: 8406 | D14: 5984 | E14: 2371 | F14: 770 | G14: =C14/B14 -> 0.24197588 | H14: =D14/B14 -> 0.17225597 | I14: =E14/B14 -> 0.068251821 | J14: =F14/B14 -> 0.02216529 | K14: 2935 | L14: =K14/D14 -> 0.4904746 | M14: 3049 | N14: =M14/D14 -> 0.5095254 | O14: 36.7 | P14: 12839 | Q14: 5540 | R14: =Q14/P14 -> 0.43149778 | S14: 4132 | T14: =S14/P14 -> 0.32183192 | U14: 2935 | V14: 164 | W14: =V14/U14 -> 0.055877342 | X14: 2055 | Y14: =X14/U14 -> 0.70017036 | Z14: 119 | AA14: =Z14/U14 -> 0.040545145 | AB14: 325 | AC14: =AB14/U14 -> 0.11073254 | AD14: 272 | AE14: =AD14/U14 -> 0.092674617 | AF14: 3049 | AG14: 160 | AH14: =AG14/AF14 -> 0.052476222 | AI14: 1555 | AJ14: =AI14/AF14 -> 0.51000328 | AK14: 103 | AL14: =AK14/AF14 -> 0.033781568 | AM14: 791 | AN14: =AM14/AF14 -> 0.25942932 | AO14: 440 | AP14: =AO14/AF14 -> 0.14430961 | AQ14: =SUM(U14,AF14) -> 5984 | AR14: =SUM(V14,AG14) -> 324 | AS14: =AR14/AQ14 -> 0.054144385 | AT14: =SUM(X14,AI14) -> 3610 | AU14: =AT14/AQ14 -> 0.6032754 | AV14: =SUM(Z14,AK14) -> 222 | AW14: =AV14/AQ14 -> 0.03709893 | AX14: =SUM(AB14,AM14) -> 1116 | AY14: =AX14/AQ14 -> 0.18649733 | AZ14: =SUM(AD14,AO14) -> 712 | BA14: =AZ14/AQ14 -> 0.11898396 | BB14: 2841 | BC14: 851 | BD14: =BC14/BB14 -> 0.29954241 | BE14: 2858 | BF14: 866 | BG14: =BF14/BE14 -> 0.3030091 | BH14: =SUM(BB14,BE14) -> 5699 | BI14: =SUM(BC14,BF14) -> 1717 | BJ14: =BI14/BH14 -> 0.30128093 | BK14: 5984 | BL14: 1494 | BM14: =BL14/BK14 -> 0.24966578 | BN14: 2935 | BO14: 553 | BP14: =BO14/BN14 -> 0.18841567 | BQ14: 3049 | BR14: 941 | BS14: =BR14/BQ14 -> 0.30862578 | BT14: 34801 | BU14: 6363 | BV14: =BU14/BT14 -> 0.18283957 | BW14: =BU14/$BU14 -> 1 | BX14: 31505 | BY14: 6205 | BZ14: =BY14/BX14 -> 0.19695286 | CA14: =BY14/$BU14 -> 0.97516895 | CB14: 175 | CC14: 10 | CD14: =CC14/CB14 -> 0.057142857 | CE14: =CC14/$BU14 -> 0.0015715857 | CF14: 187 | CG14: 28 | CH14: =CG14/CF14 -> 0.14973262 | CI14: =CG14/$BU14 -> 0.00440044 | CJ14: 184 | CK14: 18 | CL14: =CK14/CJ14 -> 0.097826087 | CM14: =CK14/$BU14 -> 0.0028288543 | CN14: 9 | CO14: 2 | CP14: =CO14/CN14 -> 0.22222222 | CQ14: =CO14/$BU14 -> 0.00031431715 | CR14: 166 | CS14: 3 | CT14: =CS14/CR14 -> 0.018072289 | CU14: =CS14/$BU14 -> 0.00047147572 | CV14: 306 | CW14: 28 | CX14: =CW14/CV14 -> 0.091503268 | CY14: =CW14/$BU14 -> 0.00440044 | CZ14: 2435 | DA14: 72 | DB14: =DA14/CZ14 -> 0.029568789 | DC14: =DA14/BU14 -> 0.011315417 | DD14: 2935 | DE14: 377 | DF14: 1544 | DG14: 701 | DH14: 313 | DI14: =DE14/DD14 -> 0.12844974 | DJ14: =DF14/DD14 -> 0.52606474 | DK14: =SUM(DG14:DH14)/DD14 -> 0.34548552 | DL14: 3049 | DM14: 271 | DN14: 1550 | DO14: 804 | DP14: 424 | DQ14: =DM14/DL14 -> 0.088881601 | DR14: =DN14/DL14 -> 0.5083634 | DS14: =SUM(DO14:DP14)/DL14 -> 0.402755 | DT14: =SUM(DL14,DD14) -> 5984 | DU14: =SUM(DM14,DE14) -> 648 | DV14: =SUM(DN14,DF14) -> 3094 | DW14: =SUM(DO14,DG14) -> 1505 | DX14: =SUM(DP14,DH14) -> 737 | DY14: =DU14/DT14 -> 0.10828877 | DZ14: =DV14/DT14 -> 0.51704545 | EA14: =SUM(DW14:DX14)/DT14 -> 0.37466578 | EB14: 3716 | EC14: 326 | ED14: =EC14/$EB14 -> 0.087728741 | EE14: 768 | EF14: =EE14/$EB14 -> 0.20667384 | EG14: 1337 | EH14: =EG14/$EB14 -> 0.35979548 | EI14: 1848 | EJ14: =EI14/$EB14 -> 0.49730893 | EK14: 2636 | EL14: =EK14/$EB14 -> 0.70936491 | EM14: 3104 | EN14: =EM14/$EB14 -> 0.83530678 | EO14: 67400 | EP14: 54432 | EQ14: 80688 | ER14: 79298 | ES14: 50368 | ET14: 2841 | EU14: 199 | EV14: =EU14/ET14 -> 0.070045759 | EW14: 2858 | EX14: 279 | EY14: =EX14/EW14 -> 0.097620714 | EZ14: =SUM(ET14,EW14) -> 5699 | FA14: =SUM(EU14,EX14) -> 478 | FB14: =FA14/EZ14 -> 0.083874364 | FC14: 5699 | FD14: 478 | FE14: =FD14/$FC14 -> 0.083874364 | FF14: 1080 | FG14: =FF14/$FC14 -> 0.18950693 | FH14: 1536 | FI14: =FH14/$FC14 -> 0.26952097 | FJ14: 1817 | FK14: =FJ14/$FC14 -> 0.31882786 | FL14: 2992 | FM14: =FL14/$FC14 -> 0.52500439 | FN14: 586 | FO14: 0.30761155 | FP14: 13 | FQ14: 0.006824147 | FR14: 122 | FS14: 0.1184466 | FT14: 2 | FU14: 0.0019417476 | FV14: 462 | FW14: 0.2704918 | FX14: 3 | FY14: 0.0017564403 | FZ14: 110 | GA14: 0.082028337 | GB14: 0 | GC14: 0 | GD14: 1280 | GE14: 0.21390374 | GF14: 18 | GG14: 0.0030080214 | GH14: 3716 | GI14: 533 | GJ14: =GI14/GH14 -> 0.1434338 | GK14: 223 | GL14: =GK14/GI14 -> 0.41838649 | GM14: 170 | GN14: =GM14/GI14 -> 0.31894934 | GO14: 3183 | GP14: =GO14/GH14 -> 0.8565662 | GQ14: 2527 | GR14: =GQ14/GO14 -> 0.79390512 | GS14: 635 | GT14: =GS14/GO14 -> 0.19949733
A15: Columbia | B15: 58272 | C15: 15939 | D15: 11422 | E15: 4452 | F15: 1133 | G15: =C15/B15 -> 0.27352759 | H15: =D15/B15 -> 0.19601181 | I15: =E15/B15 -> 0.076400329 | J15: =F15/B15 -> 0.0194433 | K15: 5495 | L15: =K15/D15 -> 0.48108913 | M15: 5927 | N15: =M15/D15 -> 0.51891087 | O15: 43.7 | P15: 24158 | Q15: 10968 | R15: =Q15/P15 -> 0.45401109 | S15: 8063 | T15: =S15/P15 -> 0.33376107 | U15: 5495 | V15: 261 | W15: =V15/U15 -> 0.047497725 | X15: 4011 | Y15: =X15/U15 -> 0.72993631 | Z15: 171 | AA15: =Z15/U15 -> 0.031119199 | AB15: 499 | AC15: =AB15/U15 -> 0.090809827 | AD15: 553 | AE15: =AD15/U15 -> 0.10063694 | AF15: 5927 | AG15: 247 | AH15: =AG15/AF15 -> 0.041673697 | AI15: 2900 | AJ15: =AI15/AF15 -> 0.48928632 | AK15: 139 | AL15: =AK15/AF15 -> 0.023451999 | AM15: 1844 | AN15: =AM15/AF15 -> 0.31111861 | AO15: 797 | AP15: =AO15/AF15 -> 0.13446938 | AQ15: =SUM(U15,AF15) -> 11422 | AR15: =SUM(V15,AG15) -> 508 | AS15: =AR15/AQ15 -> 0.044475573 | AT15: =SUM(X15,AI15) -> 6911 | AU15: =AT15/AQ15 -> 0.60506041 | AV15: =SUM(Z15,AK15) -> 310 | AW15: =AV15/AQ15 -> 0.027140606 | AX15: =SUM(AB15,AM15) -> 2343 | AY15: =AX15/AQ15 -> 0.20513045 | AZ15: =SUM(AD15,AO15) -> 1350 | BA15: =AZ15/AQ15 -> 0.11819296 | BB15: 5353 | BC15: 1415 | BD15: =BC15/BB15 -> 0.26433775 | BE15: 5686 | BF15: 1338 | BG15: =BF15/BE15 -> 0.23531481 | BH15: =SUM(BB15,BE15) -> 11039 | BI15: =SUM(BC15,BF15) -> 2753 | BJ15: =BI15/BH15 -> 0.24938853 | BK15: 11422 | BL15: 2930 | BM15: =BL15/BK15 -> 0.2565225 | BN15: 5495 | BO15: 904 | BP15: =BO15/BN15 -> 0.16451319 | BQ15: 5927 | BR15: 2026 | BS15: =BR15/BQ15 -> 0.34182554 | BT15: 58113 | BU15: 12150 | BV15: =BU15/BT15 -> 0.20907542 | BW15: =BU15/$BU15 -> 1 | BX15: 52730 | BY15: 11734 | BZ15: =BY15/BX15 -> 0.22252987 | CA15: =BY15/$BU15 -> 0.96576132 | CB15: 879 | CC15: 69 | CD15: =CC15/CB15 -> 0.078498294 | CE15: =CC15/$BU15 -> 0.0056790123 | CF15: 330 | CG15: 50 | CH15: =CG15/CF15 -> 0.15151515 | CI15: =CG15/$BU15 -> 0.0041152263 | CJ15: 547 | CK15: 87 | CL15: =CK15/CJ15 -> 0.15904936 | CM15: =CK15/$BU15 -> 0.0071604938 | CN15: 43 | CO15: 6 | CP15: =CO15/CN15 -> 0.13953488 | CQ15: =CO15/$BU15 -> 0.00049382716 | CR15: 229 | CS15: 0 | CT15: =CS15/CR15 -> 0 | CU15: =CS15/$BU15 -> 0 | CV15: 901 | CW15: 59 | CX15: =CW15/CV15 -> 0.065482797 | CY15: =CW15/$BU15 -> 0.0048559671 | CZ15: 2683 | DA15: 145 | DB15: =DA15/CZ15 -> 0.054043981 | DC15: =DA15/BU15 -> 0.011934156 | DD15: 5495 | DE15: 358 | DF15: 2062 | DG15: 1858 | DH15: 1217 | DI15: =DE15/DD15 -> 0.065150136 | DJ15: =DF15/DD15 -> 0.37525023 | DK15: =SUM(DG15:DH15)/DD15 -> 0.55959964 | DL15: 5927 | DM15: 201 | DN15: 2138 | DO15: 2145 | DP15: 1443 | DQ15: =DM15/DL15 -> 0.033912603 | DR15: =DN15/DL15 -> 0.36072212 | DS15: =SUM(DO15:DP15)/DL15 -> 0.60536528 | DT15: =SUM(DL15,DD15) -> 11422 | DU15: =SUM(DM15,DE15) -> 559 | DV15: =SUM(DN15,DF15) -> 4200 | DW15: =SUM(DO15,DG15) -> 4003 | DX15: =SUM(DP15,DH15) -> 2660 | DY15: =DU15/DT15 -> 0.048940641 | DZ15: =DV15/DT15 -> 0.36771143 | EA15: =SUM(DW15:DX15)/DT15 -> 0.58334793 | EB15: 7203 | EC15: 592 | ED15: =EC15/$EB15 -> 0.082187977 | EE15: 1241 | EF15: =EE15/$EB15 -> 0.17228932 | EG15: 2077 | EH15: =EG15/$EB15 -> 0.28835208 | EI15: 3111 | EJ15: =EI15/$EB15 -> 0.43190337 | EK15: 4514 | EL15: =EK15/$EB15 -> 0.62668333 | EM15: 5501 | EN15: =EM15/$EB15 -> 0.76370957 | EO15: 85351 | EP15: 46528 | EQ15: 95611 | ER15: 103373 | ES15: 57885 | ET15: 5353 | EU15: 285 | EV15: =EU15/ET15 -> 0.053241173 | EW15: 5686 | EX15: 563 | EY15: =EX15/EW15 -> 0.099015125 | EZ15: =SUM(ET15,EW15) -> 11039 | FA15: =SUM(EU15,EX15) -> 848 | FB15: =FA15/EZ15 -> 0.076818552 | FC15: 11039 | FD15: 848 | FE15: =FD15/$FC15 -> 0.076818552 | FF15: 1551 | FG15: =FF15/$FC15 -> 0.14050186 | FH15: 2290 | FI15: =FH15/$FC15 -> 0.20744633 | FJ15: 2735 | FK15: =FJ15/$FC15 -> 0.24775795 | FL15: 4500 | FM15: =FL15/$FC15 -> 0.40764562 | FN15: 966 | FO15: 0.27043673 | FP15: 13 | FQ15: 0.0036394177 | FR15: 217 | FS15: 0.11284451 | FT15: 4 | FU15: 0.0020800832 | FV15: 685 | FW15: 0.20158917 | FX15: 1 | FY15: 0.00029429076 | FZ15: 136 | GA15: 0.053776196 | GB15: 0 | GC15: 0 | GD15: 2004 | GE15: 0.17545088 | GF15: 18 | GG15: 0.0015759061 | GH15: 7203 | GI15: 1361 | GJ15: =GI15/GH15 -> 0.18894905 | GK15: 668 | GL15: =GK15/GI15 -> 0.49081558 | GM15: 554 | GN15: =GM15/GI15 -> 0.40705364 | GO15: 5842 | GP15: =GO15/GH15 -> 0.81105095 | GQ15: 4498 | GR15: =GQ15/GO15 -> 0.7699418 | GS15: 1296 | GT15: =GS15/GO15 -> 0.22184183
A16: Crawford | B16: 16042 | C16: 5294 | D16: 4032 | E16: 1658 | F16: 405 | G16: =C16/B16 -> 0.33000873 | H16: =D16/B16 -> 0.25134023 | I16: =E16/B16 -> 0.1033537 | J16: =F16/B16 -> 0.025246229 | K16: 1981 | L16: =K16/D16 -> 0.49131944 | M16: 2051 | N16: =M16/D16 -> 0.50868056 | O16: 47.4 | P16: 6706 | Q16: 3531 | R16: =Q16/P16 -> 0.52654339 | S16: 2788 | T16: =S16/P16 -> 0.41574709 | U16: 1981 | V16: 154 | W16: =V16/U16 -> 0.077738516 | X16: 1248 | Y16: =X16/U16 -> 0.62998486 | Z16: 87 | AA16: =Z16/U16 -> 0.043917214 | AB16: 201 | AC16: =AB16/U16 -> 0.10146391 | AD16: 291 | AE16: =AD16/U16 -> 0.14689551 | AF16: 2051 | AG16: 88 | AH16: =AG16/AF16 -> 0.0429059 | AI16: 1114 | AJ16: =AI16/AF16 -> 0.54314968 | AK16: 39 | AL16: =AK16/AF16 -> 0.019015115 | AM16: 475 | AN16: =AM16/AF16 -> 0.23159434 | AO16: 335 | AP16: =AO16/AF16 -> 0.16333496 | AQ16: =SUM(U16,AF16) -> 4032 | AR16: =SUM(V16,AG16) -> 242 | AS16: =AR16/AQ16 -> 0.060019841 | AT16: =SUM(X16,AI16) -> 2362 | AU16: =AT16/AQ16 -> 0.58581349 | AV16: =SUM(Z16,AK16) -> 126 | AW16: =AV16/AQ16 -> 0.03125 | AX16: =SUM(AB16,AM16) -> 676 | AY16: =AX16/AQ16 -> 0.16765873 | AZ16: =SUM(AD16,AO16) -> 626 | BA16: =AZ16/AQ16 -> 0.15525794 | BB16: 1894 | BC16: 590 | BD16: =BC16/BB16 -> 0.31151003 | BE16: 1983 | BF16: 462 | BG16: =BF16/BE16 -> 0.23298033 | BH16: =SUM(BB16,BE16) -> 3877 | BI16: =SUM(BC16,BF16) -> 1052 | BJ16: =BI16/BH16 -> 0.27134382 | BK16: 4032 | BL16: 1088 | BM16: =BL16/BK16 -> 0.26984127 | BN16: 1981 | BO16: 507 | BP16: =BO16/BN16 -> 0.25593135 | BQ16: 2051 | BR16: 581 | BS16: =BR16/BQ16 -> 0.28327645 | BT16: 16008 | BU16: 4216 | BV16: =BU16/BT16 -> 0.26336832 | BW16: =BU16/$BU16 -> 1 | BX16: 14959 | BY16: 4123 | BZ16: =BY16/BX16 -> 0.27562003 | CA16: =BY16/$BU16 -> 0.97794118 | CB16: 350 | CC16: 17 | CD16: =CC16/CB16 -> 0.048571429 | CE16: =CC16/$BU16 -> 0.0040322581 | CF16: 58 | CG16: 11 | CH16: =CG16/CF16 -> 0.18965517 | CI16: =CG16/$BU16 -> 0.0026091082 | CJ16: 124 | CK16: 15 | CL16: =CK16/CJ16 -> 0.12096774 | CM16: =CK16/$BU16 -> 0.0035578748 | CN16: 7 | CO16: 2 | CP16: =CO16/CN16 -> 0.28571429 | CQ16: =CO16/$BU16 -> 0.0004743833 | CR16: 23 | CS16: 3 | CT16: =CS16/CR16 -> 0.13043478 | CU16: =CS16/$BU16 -> 0.00071157495 | CV16: 176 | CW16: 24 | CX16: =CW16/CV16 -> 0.13636364 | CY16: =CW16/$BU16 -> 0.0056925996 | CZ16: 334 | DA16: 24 | DB16: =DA16/CZ16 -> 0.071856287 | DC16: =DA16/BU16 -> 0.0056925996 | DD16: 1981 | DE16: 145 | DF16: 945 | DG16: 501 | DH16: 390 | DI16: =DE16/DD16 -> 0.073195356 | DJ16: =DF16/DD16 -> 0.4770318 | DK16: =SUM(DG16:DH16)/DD16 -> 0.44977284 | DL16: 2051 | DM16: 146 | DN16: 946 | DO16: 632 | DP16: 327 | DQ16: =DM16/DL16 -> 0.071184788 | DR16: =DN16/DL16 -> 0.46123842 | DS16: =SUM(DO16:DP16)/DL16 -> 0.46757679 | DT16: =SUM(DL16,DD16) -> 4032 | DU16: =SUM(DM16,DE16) -> 291 | DV16: =SUM(DN16,DF16) -> 1891 | DW16: =SUM(DO16,DG16) -> 1133 | DX16: =SUM(DP16,DH16) -> 717 | DY16: =DU16/DT16 -> 0.072172619 | DZ16: =DV16/DT16 -> 0.46899802 | EA16: =SUM(DW16:DX16)/DT16 -> 0.45882937 | EB16: 2580 | EC16: 257 | ED16: =EC16/$EB16 -> 0.099612403 | EE16: 561 | EF16: =EE16/$EB16 -> 0.21744186 | EG16: 973 | EH16: =EG16/$EB16 -> 0.37713178 | EI16: 1333 | EJ16: =EI16/$EB16 -> 0.51666667 | EK16: 1803 | EL16: =EK16/$EB16 -> 0.69883721 | EM16: 2178 | EN16: =EM16/$EB16 -> 0.84418605 | EO16: 64094 | EP16: 62692 | EQ16: 81971 | ER16: 76094 | ES16: 48045 | ET16: 1894 | EU16: 148 | EV16: =EU16/ET16 -> 0.078141499 | EW16: 1983 | EX16: 235 | EY16: =EX16/EW16 -> 0.11850731 | EZ16: =SUM(ET16,EW16) -> 3877 | FA16: =SUM(EU16,EX16) -> 383 | FB16: =FA16/EZ16 -> 0.098787722 | FC16: 3877 | FD16: 383 | FE16: =FD16/$FC16 -> 0.098787722 | FF16: 743 | FG16: =FF16/$FC16 -> 0.19164302 | FH16: 1055 | FI16: =FH16/$FC16 -> 0.27211762 | FJ16: 1210 | FK16: =FJ16/$FC16 -> 0.31209698 | FL16: 1903 | FM16: =FL16/$FC16 -> 0.49084344 | FN16: 212 | FO16: 0.17535153 | FP16: 0 | FQ16: 0 | FR16: 83 | FS16: 0.10751295 | FT16: 1 | FU16: 0.0012953368 | FV16: 280 | FW16: 0.24034335 | FX16: 4 | FY16: 0.0034334764 | FZ16: 30 | GA16: 0.033860045 | GB16: 33 | GC16: 0.03724605 | GD16: 605 | GE16: 0.1500496 | GF16: 38 | GG16: 0.0094246032 | GH16: 2580 | GI16: 447 | GJ16: =GI16/GH16 -> 0.17325581 | GK16: 197 | GL16: =GK16/GI16 -> 0.44071588 | GM16: 152 | GN16: =GM16/GI16 -> 0.34004474 | GO16: 2133 | GP16: =GO16/GH16 -> 0.82674419 | GQ16: 1609 | GR16: =GQ16/GO16 -> 0.75433662 | GS16: 512 | GT16: =GS16/GO16 -> 0.24003751
A17: Dane | B17: 572674 | C17: 116841 | D17: 86269 | E17: 33690 | F17: 9551 | G17: =C17/B17 -> 0.20402707 | H17: =D17/B17 -> 0.15064242 | I17: =E17/B17 -> 0.058829282 | J17: =F17/B17 -> 0.016677901 | K17: 39271 | L17: =K17/D17 -> 0.45521566 | M17: 46998 | N17: =M17/D17 -> 0.54478434 | O17: 35.7 | P17: 251529 | Q17: 80141 | R17: =Q17/P17 -> 0.31861535 | S17: 61406 | T17: =S17/P17 -> 0.2441309 | U17: 39271 | V17: 2946 | W17: =V17/U17 -> 0.075017188 | X17: 27462 | Y17: =X17/U17 -> 0.69929464 | Z17: 1071 | AA17: =Z17/U17 -> 0.027272033 | AB17: 3380 | AC17: =AB17/U17 -> 0.0860686 | AD17: 4412 | AE17: =AD17/U17 -> 0.11234753 | AF17: 46998 | AG17: 3832 | AH17: =AG17/AF17 -> 0.081535384 | AI17: 22639 | AJ17: =AI17/AF17 -> 0.48170135 | AK17: 1065 | AL17: =AK17/AF17 -> 0.022660539 | AM17: 11107 | AN17: =AM17/AF17 -> 0.23632921 | AO17: 8355 | AP17: =AO17/AF17 -> 0.17777352 | AQ17: =SUM(U17,AF17) -> 86269 | AR17: =SUM(V17,AG17) -> 6778 | AS17: =AR17/AQ17 -> 0.078568199 | AT17: =SUM(X17,AI17) -> 50101 | AU17: =AT17/AQ17 -> 0.58075323 | AV17: =SUM(Z17,AK17) -> 2136 | AW17: =AV17/AQ17 -> 0.024759763 | AX17: =SUM(AB17,AM17) -> 14487 | AY17: =AX17/AQ17 -> 0.16792822 | AZ17: =SUM(AD17,AO17) -> 12767 | BA17: =AZ17/AQ17 -> 0.14799059 | BB17: 38702 | BC17: 8747 | BD17: =BC17/BB17 -> 0.22600899 | BE17: 46005 | BF17: 11511 | BG17: =BF17/BE17 -> 0.25021193 | BH17: =SUM(BB17,BE17) -> 84707 | BI17: =SUM(BC17,BF17) -> 20258 | BJ17: =BI17/BH17 -> 0.23915379 | BK17: 86269 | BL17: 24873 | BM17: =BL17/BK17 -> 0.28831909 | BN17: 39271 | BO17: 7810 | BP17: =BO17/BN17 -> 0.19887449 | BQ17: 46998 | BR17: 17063 | BS17: =BR17/BQ17 -> 0.363058 | BT17: 588347 | BU17: 92821 | BV17: =BU17/BT17 -> 0.15776574 | BW17: =BU17/$BU17 -> 1 | BX17: 445504 | BY17: 85681 | BZ17: =BY17/BX17 -> 0.19232375 | CA17: =BY17/$BU17 -> 0.92307775 | CB17: 33968 | CC17: 2066 | CD17: =CC17/CB17 -> 0.06082195 | CE17: =CC17/$BU17 -> 0.022257894 | CF17: 1612 | CG17: 133 | CH17: =CG17/CF17 -> 0.082506203 | CI17: =CG17/$BU17 -> 0.0014328654 | CJ17: 42989 | CK17: 2469 | CL17: =CK17/CJ17 -> 0.057433297 | CM17: =CK17/$BU17 -> 0.026599584 | CN17: 174 | CO17: 22 | CP17: =CO17/CN17 -> 0.12643678 | CQ17: =CO17/$BU17 -> 0.00023701533 | CR17: 8812 | CS17: 186 | CT17: =CS17/CR17 -> 0.021107581 | CU17: =CS17/$BU17 -> 0.0020038569 | CV17: 15717 | CW17: 388 | CX17: =CW17/CV17 -> 0.024686645 | CY17: =CW17/$BU17 -> 0.0041800886 | CZ17: 48383 | DA17: 2062 | DB17: =DA17/CZ17 -> 0.042618275 | DC17: =DA17/BU17 -> 0.022214801 | DD17: 39271 | DE17: 1657 | DF17: 9414 | DG17: 9048 | DH17: 19152 | DI17: =DE17/DD17 -> 0.042193985 | DJ17: =DF17/DD17 -> 0.23971888 | DK17: =SUM(DG17:DH17)/DD17 -> 0.71808714 | DL17: 46998 | DM17: 1736 | DN17: 13024 | DO17: 12882 | DP17: 19356 | DQ17: =DM17/DL17 -> 0.036937742 | DR17: =DN17/DL17 -> 0.27711818 | DS17: =SUM(DO17:DP17)/DL17 -> 0.68594408 | DT17: =SUM(DL17,DD17) -> 86269 | DU17: =SUM(DM17,DE17) -> 3393 | DV17: =SUM(DN17,DF17) -> 22438 | DW17: =SUM(DO17,DG17) -> 21930 | DX17: =SUM(DP17,DH17) -> 38508 | DY17: =DU17/DT17 -> 0.039330466 | DZ17: =DV17/DT17 -> 0.26009343 | EA17: =SUM(DW17:DX17)/DT17 -> 0.7005761 | EB17: 55214 | EC17: 3075 | ED17: =EC17/$EB17 -> 0.055692397 | EE17: 6401 | EF17: =EE17/$EB17 -> 0.11593074 | EG17: 10985 | EH17: =EG17/$EB17 -> 0.19895316 | EI17: 17033 | EJ17: =EI17/$EB17 -> 0.3084906 | EK17: 28459 | EL17: =EK17/$EB17 -> 0.51543087 | EM17: 36015 | EN17: =EM17/$EB17 -> 0.65228022 | EO17: 89975 | EP17: 40002 | EQ17: 101525 | ER17: 115057 | ES17: 72639 | ET17: 38702 | EU17: 2246 | EV17: =EU17/ET17 -> 0.058033177 | EW17: 46005 | EX17: 2837 | EY17: =EX17/EW17 -> 0.06166721 | EZ17: =SUM(ET17,EW17) -> 84707 | FA17: =SUM(EU17,EX17) -> 5083 | FB17: =FA17/EZ17 -> 0.060006847 | FC17: 84707 | FD17: 5083 | FE17: =FD17/$FC17 -> 0.060006847 | FF17: 8593 | FG17: =FF17/$FC17 -> 0.1014438 | FH17: 11896 | FI17: =FH17/$FC17 -> 0.14043704 | FJ17: 13924 | FK17: =FJ17/$FC17 -> 0.16437839 | FL17: 25885 | FM17: =FL17/$FC17 -> 0.30558277 | FN17: 8133 | FO17: 0.32645607 | FP17: 139 | FQ17: 0.0055794164 | FR17: 1357 | FS17: 0.09451177 | FT17: 10 | FU17: 0.00069647583 | FV17: 6397 | FW17: 0.23122244 | FX17: 75 | FY17: 0.0027109087 | FZ17: 1167 | GA17: 0.060366232 | GB17: 40 | GC17: 0.0020691082 | GD17: 17054 | GE17: 0.19768399 | GF17: 264 | GG17: 0.0030601954 | GH17: 55214 | GI17: 12775 | GJ17: =GI17/GH17 -> 0.23137248 | GK17: 4611 | GL17: =GK17/GI17 -> 0.36093933 | GM17: 7328 | GN17: =GM17/GI17 -> 0.57362035 | GO17: 42439 | GP17: =GO17/GH17 -> 0.76862752 | GQ17: 31785 | GR17: =GQ17/GO17 -> 0.74895733 | GS17: 10443 | GT17: =GS17/GO17 -> 0.24607083
A18: Dodge | B18: 88742 | C18: 23654 | D18: 16859 | E18: 6706 | F18: 2128 | G18: =C18/B18 -> 0.26654797 | H18: =D18/B18 -> 0.18997769 | I18: =E18/B18 -> 0.075567375 | J18: =F18/B18 -> 0.023979626 | K18: 7922 | L18: =K18/D18 -> 0.46989738 | M18: 8937 | N18: =M18/D18 -> 0.53010262 | O18: 43 | P18: 35910 | Q18: 16051 | R18: =Q18/P18 -> 0.44697856 | S18: 11819 | T18: =S18/P18 -> 0.32912838 | U18: 7922 | V18: 658 | W18: =V18/U18 -> 0.083059833 | X18: 5301 | Y18: =X18/U18 -> 0.6691492 | Z18: 166 | AA18: =Z18/U18 -> 0.020954304 | AB18: 1005 | AC18: =AB18/U18 -> 0.1268619 | AD18: 792 | AE18: =AD18/U18 -> 0.099974754 | AF18: 8937 | AG18: 622 | AH18: =AG18/AF18 -> 0.069598299 | AI18: 4073 | AJ18: =AI18/AF18 -> 0.45574578 | AK18: 216 | AL18: =AK18/AF18 -> 0.024169184 | AM18: 2462 | AN18: =AM18/AF18 -> 0.27548394 | AO18: 1564 | AP18: =AO18/AF18 -> 0.1750028 | AQ18: =SUM(U18,AF18) -> 16859 | AR18: =SUM(V18,AG18) -> 1280 | AS18: =AR18/AQ18 -> 0.075923839 | AT18: =SUM(X18,AI18) -> 9374 | AU18: =AT18/AQ18 -> 0.55602349 | AV18: =SUM(Z18,AK18) -> 382 | AW18: =AV18/AQ18 -> 0.022658521 | AX18: =SUM(AB18,AM18) -> 3467 | AY18: =AX18/AQ18 -> 0.20564684 | AZ18: =SUM(AD18,AO18) -> 2356 | BA18: =AZ18/AQ18 -> 0.13974732 | BB18: 7667 | BC18: 2273 | BD18: =BC18/BB18 -> 0.29646537 | BE18: 8464 | BF18: 2498 | BG18: =BF18/BE18 -> 0.29513233 | BH18: =SUM(BB18,BE18) -> 16131 | BI18: =SUM(BC18,BF18) -> 4771 | BJ18: =BI18/BH18 -> 0.29576592 | BK18: 16859 | BL18: 4956 | BM18: =BL18/BK18 -> 0.29396761 | BN18: 7922 | BO18: 1633 | BP18: =BO18/BN18 -> 0.20613481 | BQ18: 8937 | BR18: 3323 | BS18: =BR18/BQ18 -> 0.371825 | BT18: 88635 | BU18: 17897 | BV18: =BU18/BT18 -> 0.20191798 | BW18: =BU18/$BU18 -> 1 | BX18: 77562 | BY18: 17331 | BZ18: =BY18/BX18 -> 0.22344705 | CA18: =BY18/$BU18 -> 0.96837459 | CB18: 2589 | CC18: 63 | CD18: =CC18/CB18 -> 0.02433372 | CE18: =CC18/$BU18 -> 0.003520143 | CF18: 451 | CG18: 60 | CH18: =CG18/CF18 -> 0.13303769 | CI18: =CG18/$BU18 -> 0.0033525172 | CJ18: 662 | CK18: 64 | CL18: =CK18/CJ18 -> 0.096676737 | CM18: =CK18/$BU18 -> 0.0035760183 | CN18: 47 | CO18: 4 | CP18: =CO18/CN18 -> 0.085106383 | CQ18: =CO18/$BU18 -> 0.00022350115 | CR18: 564 | CS18: 15 | CT18: =CS18/CR18 -> 0.026595745 | CU18: =CS18/$BU18 -> 0.0008381293 | CV18: 975 | CW18: 68 | CX18: =CW18/CV18 -> 0.06974359 | CY18: =CW18/$BU18 -> 0.0037995195 | CZ18: 6349 | DA18: 307 | DB18: =DA18/CZ18 -> 0.048354072 | DC18: =DA18/BU18 -> 0.017153713 | DD18: 7922 | DE18: 775 | DF18: 3599 | DG18: 2001 | DH18: 1547 | DI18: =DE18/DD18 -> 0.097828831 | DJ18: =DF18/DD18 -> 0.45430447 | DK18: =SUM(DG18:DH18)/DD18 -> 0.4478667 | DL18: 8937 | DM18: 864 | DN18: 4400 | DO18: 2197 | DP18: 1476 | DQ18: =DM18/DL18 -> 0.096676737 | DR18: =DN18/DL18 -> 0.49233524 | DS18: =SUM(DO18:DP18)/DL18 -> 0.41098803 | DT18: =SUM(DL18,DD18) -> 16859 | DU18: =SUM(DM18,DE18) -> 1639 | DV18: =SUM(DN18,DF18) -> 7999 | DW18: =SUM(DO18,DG18) -> 4198 | DX18: =SUM(DP18,DH18) -> 3023 | DY18: =DU18/DT18 -> 0.097218103 | DZ18: =DV18/DT18 -> 0.47446468 | EA18: =SUM(DW18:DX18)/DT18 -> 0.42831722 | EB18: 10547 | EC18: 781 | ED18: =EC18/$EB18 -> 0.074049493 | EE18: 1975 | EF18: =EE18/$EB18 -> 0.18725704 | EG18: 3365 | EH18: =EG18/$EB18 -> 0.31904807 | EI18: 4995 | EJ18: =EI18/$EB18 -> 0.47359439 | EK18: 7275 | EL18: =EK18/$EB18 -> 0.6897696 | EM18: 8643 | EN18: =EM18/$EB18 -> 0.81947473 | EO18: 75929 | EP18: 48732 | EQ18: 85755 | ER18: 93705 | ES18: 52843 | ET18: 7667 | EU18: 514 | EV18: =EU18/ET18 -> 0.067040563 | EW18: 8464 | EX18: 787 | EY18: =EX18/EW18 -> 0.092982042 | EZ18: =SUM(ET18,EW18) -> 16131 | FA18: =SUM(EU18,EX18) -> 1301 | FB18: =FA18/EZ18 -> 0.08065216 | FC18: 16131 | FD18: 1301 | FE18: =FD18/$FC18 -> 0.08065216 | FF18: 2540 | FG18: =FF18/$FC18 -> 0.15746079 | FH18: 3517 | FI18: =FH18/$FC18 -> 0.2180274 | FJ18: 4192 | FK18: =FJ18/$FC18 -> 0.2598723 | FL18: 7543 | FM18: =FL18/$FC18 -> 0.46760895 | FN18: 1407 | FO18: 0.28 | FP18: 5 | FQ18: 0.00099502488 | FR18: 278 | FS18: 0.095961339 | FT18: 0 | FU18: 0 | FV18: 1219 | FW18: 0.23771451 | FX18: 2 | FY18: 0.0003900156 | FZ18: 115 | GA18: 0.030191651 | GB18: 0 | GC18: 0 | GD18: 3019 | GE18: 0.17907349 | GF18: 7 | GG18: 0.00041520849 | GH18: 10547 | GI18: 2326 | GJ18: =GI18/GH18 -> 0.22053665 | GK18: 980 | GL18: =GK18/GI18 -> 0.42132416 | GM18: 1166 | GN18: =GM18/GI18 -> 0.50128977 | GO18: 8221 | GP18: =GO18/GH18 -> 0.77946335 | GQ18: 6025 | GR18: =GQ18/GO18 -> 0.73287921 | GS18: 2156 | GT18: =GS18/GO18 -> 0.2622552
A19: Door | B19: 30445 | C19: 12622 | D19: 9871 | E19: 3838 | F19: 870 | G19: =C19/B19 -> 0.41458368 | H19: =D19/B19 -> 0.32422401 | I19: =E19/B19 -> 0.12606339 | J19: =F19/B19 -> 0.028576121 | K19: 4679 | L19: =K19/D19 -> 0.47401479 | M19: 5192 | N19: =M19/D19 -> 0.52598521 | O19: 54.3 | P19: 14986 | Q19: 8526 | R19: =Q19/P19 -> 0.568931 | S19: 6827 | T19: =S19/P19 -> 0.45555852 | U19: 4679 | V19: 183 | W19: =V19/U19 -> 0.039110921 | X19: 3437 | Y19: =X19/U19 -> 0.73455867 | Z19: 170 | AA19: =Z19/U19 -> 0.03633255 | AB19: 365 | AC19: =AB19/U19 -> 0.078008121 | AD19: 524 | AE19: =AD19/U19 -> 0.11198974 | AF19: 5192 | AG19: 237 | AH19: =AG19/AF19 -> 0.045647149 | AI19: 3112 | AJ19: =AI19/AF19 -> 0.59938367 | AK19: 32 | AL19: =AK19/AF19 -> 0.0061633282 | AM19: 1204 | AN19: =AM19/AF19 -> 0.23189522 | AO19: 607 | AP19: =AO19/AF19 -> 0.11691063 | AQ19: =SUM(U19,AF19) -> 9871 | AR19: =SUM(V19,AG19) -> 420 | AS19: =AR19/AQ19 -> 0.042548881 | AT19: =SUM(X19,AI19) -> 6549 | AU19: =AT19/AQ19 -> 0.66345862 | AV19: =SUM(Z19,AK19) -> 202 | AW19: =AV19/AQ19 -> 0.020463985 | AX19: =SUM(AB19,AM19) -> 1569 | AY19: =AX19/AQ19 -> 0.15895046 | AZ19: =SUM(AD19,AO19) -> 1131 | BA19: =AZ19/AQ19 -> 0.11457806 | BB19: 4640 | BC19: 1219 | BD19: =BC19/BB19 -> 0.26271552 | BE19: 5098 | BF19: 1060 | BG19: =BF19/BE19 -> 0.20792468 | BH19: =SUM(BB19,BE19) -> 9738 | BI19: =SUM(BC19,BF19) -> 2279 | BJ19: =BI19/BH19 -> 0.23403163 | BK19: 9871 | BL19: 2533 | BM19: =BL19/BK19 -> 0.25661027 | BN19: 4679 | BO19: 950 | BP19: =BO19/BN19 -> 0.20303484 | BQ19: 5192 | BR19: 1583 | BS19: =BR19/BQ19 -> 0.30489214 | BT19: 30512 | BU19: 10435 | BV19: =BU19/BT19 -> 0.34199659 | BW19: =BU19/$BU19 -> 1 | BX19: 28085 | BY19: 10177 | BZ19: =BY19/BX19 -> 0.36236425 | CA19: =BY19/$BU19 -> 0.97527552 | CB19: 262 | CC19: 33 | CD19: =CC19/CB19 -> 0.1259542 | CE19: =CC19/$BU19 -> 0.0031624341 | CF19: 193 | CG19: 39 | CH19: =CG19/CF19 -> 0.20207254 | CI19: =CG19/$BU19 -> 0.0037374221 | CJ19: 182 | CK19: 24 | CL19: =CK19/CJ19 -> 0.13186813 | CM19: =CK19/$BU19 -> 0.0022999521 | CN19: 14 | CO19: 4 | CP19: =CO19/CN19 -> 0.28571429 | CQ19: =CO19/$BU19 -> 0.00038332535 | CR19: 158 | CS19: 5 | CT19: =CS19/CR19 -> 0.03164557 | CU19: =CS19/$BU19 -> 0.00047915668 | CV19: 407 | CW19: 60 | CX19: =CW19/CV19 -> 0.14742015 | CY19: =CW19/$BU19 -> 0.0057498802 | CZ19: 1369 | DA19: 98 | DB19: =DA19/CZ19 -> 0.071585099 | DC19: =DA19/BU19 -> 0.009391471 | DD19: 4679 | DE19: 127 | DF19: 1270 | DG19: 1243 | DH19: 2039 | DI19: =DE19/DD19 -> 0.027142552 | DJ19: =DF19/DD19 -> 0.27142552 | DK19: =SUM(DG19:DH19)/DD19 -> 0.70143193 | DL19: 5192 | DM19: 197 | DN19: 1452 | DO19: 1272 | DP19: 2271 | DQ19: =DM19/DL19 -> 0.037942989 | DR19: =DN19/DL19 -> 0.27966102 | DS19: =SUM(DO19:DP19)/DL19 -> 0.68239599 | DT19: =SUM(DL19,DD19) -> 9871 | DU19: =SUM(DM19,DE19) -> 324 | DV19: =SUM(DN19,DF19) -> 2722 | DW19: =SUM(DO19,DG19) -> 2515 | DX19: =SUM(DP19,DH19) -> 4310 | DY19: =DU19/DT19 -> 0.032823422 | DZ19: =DV19/DT19 -> 0.27575727 | EA19: =SUM(DW19:DX19)/DT19 -> 0.69141931 | EB19: 6319 | EC19: 350 | ED19: =EC19/$EB19 -> 0.055388511 | EE19: 909 | EF19: =EE19/$EB19 -> 0.14385188 | EG19: 1480 | EH19: =EG19/$EB19 -> 0.23421427 | EI19: 2217 | EJ19: =EI19/$EB19 -> 0.35084665 | EK19: 3601 | EL19: =EK19/$EB19 -> 0.56986865 | EM19: 4286 | EN19: =EM19/$EB19 -> 0.67827188 | EO19: 74795 | EP19: 41350 | EQ19: 89472 | ER19: 84492 | ES19: 65046 | ET19: 4640 | EU19: 207 | EV19: =EU19/ET19 -> 0.044612069 | EW19: 5098 | EX19: 349 | EY19: =EX19/EW19 -> 0.068458219 | EZ19: =SUM(ET19,EW19) -> 9738 | FA19: =SUM(EU19,EX19) -> 556 | FB19: =FA19/EZ19 -> 0.057095913 | FC19: 9738 | FD19: 556 | FE19: =FD19/$FC19 -> 0.057095913 | FF19: 1104 | FG19: =FF19/$FC19 -> 0.1133703 | FH19: 1499 | FI19: =FH19/$FC19 -> 0.15393305 | FJ19: 1784 | FK19: =FJ19/$FC19 -> 0.18319984 | FL19: 3368 | FM19: =FL19/$FC19 -> 0.34586157 | FN19: 749 | FO19: 0.25916955 | FP19: 4 | FQ19: 0.001384083 | FR19: 132 | FS19: 0.073784237 | FT19: 7 | FU19: 0.0039128004 | FV19: 739 | FW19: 0.23512568 | FX19: 1 | FY19: 0.00031816736 | FZ19: 112 | GA19: 0.05466081 | GB19: 0 | GC19: 0 | GD19: 1732 | GE19: 0.17546348 | GF19: 12 | GG19: 0.0012156823 | GH19: 6319 | GI19: 620 | GJ19: =GI19/GH19 -> 0.098116791 | GK19: 212 | GL19: =GK19/GI19 -> 0.34193548 | GM19: 319 | GN19: =GM19/GI19 -> 0.51451613 | GO19: 5699 | GP19: =GO19/GH19 -> 0.90188321 | GQ19: 4134 | GR19: =GQ19/GO19 -> 0.72539042 | GS19: 1523 | GT19: =GS19/GO19 -> 0.26723987
A20: Douglas | B20: 44229 | C20: 12703 | D20: 9145 | E20: 3400 | F20: 1002 | G20: =C20/B20 -> 0.28720975 | H20: =D20/B20 -> 0.20676479 | I20: =E20/B20 -> 0.07687264 | J20: =F20/B20 -> 0.022654819 | K20: 4512 | L20: =K20/D20 -> 0.49338436 | M20: 4633 | N20: =M20/D20 -> 0.50661564 | O20: 42.7 | P20: 19160 | Q20: 8673 | R20: =Q20/P20 -> 0.4526618 | S20: 6464 | T20: =S20/P20 -> 0.33736952 | U20: 4512 | V20: 430 | W20: =V20/U20 -> 0.095301418 | X20: 2850 | Y20: =X20/U20 -> 0.63164894 | Z20: 144 | AA20: =Z20/U20 -> 0.031914894 | AB20: 367 | AC20: =AB20/U20 -> 0.081338652 | AD20: 721 | AE20: =AD20/U20 -> 0.1597961 | AF20: 4633 | AG20: 157 | AH20: =AG20/AF20 -> 0.03388733 | AI20: 2225 | AJ20: =AI20/AF20 -> 0.48025038 | AK20: 60 | AL20: =AK20/AF20 -> 0.012950572 | AM20: 1377 | AN20: =AM20/AF20 -> 0.29721563 | AO20: 814 | AP20: =AO20/AF20 -> 0.17569609 | AQ20: =SUM(U20,AF20) -> 9145 | AR20: =SUM(V20,AG20) -> 587 | AS20: =AR20/AQ20 -> 0.064188081 | AT20: =SUM(X20,AI20) -> 5075 | AU20: =AT20/AQ20 -> 0.55494806 | AV20: =SUM(Z20,AK20) -> 204 | AW20: =AV20/AQ20 -> 0.022307272 | AX20: =SUM(AB20,AM20) -> 1744 | AY20: =AX20/AQ20 -> 0.1907053 | AZ20: =SUM(AD20,AO20) -> 1535 | BA20: =AZ20/AQ20 -> 0.16785128 | BB20: 4452 | BC20: 1528 | BD20: =BC20/BB20 -> 0.34321653 | BE20: 4404 | BF20: 1477 | BG20: =BF20/BE20 -> 0.33537693 | BH20: =SUM(BB20,BE20) -> 8856 | BI20: =SUM(BC20,BF20) -> 3005 | BJ20: =BI20/BH20 -> 0.33931798 | BK20: 9145 | BL20: 2880 | BM20: =BL20/BK20 -> 0.31492619 | BN20: 4512 | BO20: 1158 | BP20: =BO20/BN20 -> 0.25664894 | BQ20: 4633 | BR20: 1722 | BS20: =BR20/BQ20 -> 0.37168142 | BT20: 44276 | BU20: 9721 | BV20: =BU20/BT20 -> 0.21955461 | BW20: =BU20/$BU20 -> 1 | BX20: 40210 | BY20: 9313 | BZ20: =BY20/BX20 -> 0.23160905 | CA20: =BY20/$BU20 -> 0.95802901 | CB20: 552 | CC20: 30 | CD20: =CC20/CB20 -> 0.054347826 | CE20: =CC20/$BU20 -> 0.0030861023 | CF20: 754 | CG20: 157 | CH20: =CG20/CF20 -> 0.20822281 | CI20: =CG20/$BU20 -> 0.016150602 | CJ20: 472 | CK20: 35 | CL20: =CK20/CJ20 -> 0.074152542 | CM20: =CK20/$BU20 -> 0.0036004526 | CN20: 21 | CO20: 1 | CP20: =CO20/CN20 -> 0.047619048 | CQ20: =CO20/$BU20 -> 0.00010287008 | CR20: 102 | CS20: 0 | CT20: =CS20/CR20 -> 0 | CU20: =CS20/$BU20 -> 0 | CV20: 1361 | CW20: 121 | CX20: =CW20/CV20 -> 0.088905217 | CY20: =CW20/$BU20 -> 0.012447279 | CZ20: 906 | DA20: 64 | DB20: =DA20/CZ20 -> 0.070640177 | DC20: =DA20/BU20 -> 0.0065836848 | DD20: 4512 | DE20: 335 | DF20: 1811 | DG20: 1263 | DH20: 1103 | DI20: =DE20/DD20 -> 0.074246454 | DJ20: =DF20/DD20 -> 0.40137411 | DK20: =SUM(DG20:DH20)/DD20 -> 0.52437943 | DL20: 4633 | DM20: 206 | DN20: 1585 | DO20: 1548 | DP20: 1294 | DQ20: =DM20/DL20 -> 0.04446363 | DR20: =DN20/DL20 -> 0.34211094 | DS20: =SUM(DO20:DP20)/DL20 -> 0.61342543 | DT20: =SUM(DL20,DD20) -> 9145 | DU20: =SUM(DM20,DE20) -> 541 | DV20: =SUM(DN20,DF20) -> 3396 | DW20: =SUM(DO20,DG20) -> 2811 | DX20: =SUM(DP20,DH20) -> 2397 | DY20: =DU20/DT20 -> 0.05915801 | DZ20: =DV20/DT20 -> 0.37135046 | EA20: =SUM(DW20:DX20)/DT20 -> 0.56949153 | EB20: 5802 | EC20: 602 | ED20: =EC20/$EB20 -> 0.10375733 | EE20: 1205 | EF20: =EE20/$EB20 -> 0.207687 | EG20: 1961 | EH20: =EG20/$EB20 -> 0.3379869 | EI20: 2782 | EJ20: =EI20/$EB20 -> 0.47948983 | EK20: 3960 | EL20: =EK20/$EB20 -> 0.68252327 | EM20: 4677 | EN20: =EM20/$EB20 -> 0.80610134 | EO20: 75099 | EP20: 43676 | EQ20: 93731 | ER20: 83088 | ES20: 51771 | ET20: 4452 | EU20: 307 | EV20: =EU20/ET20 -> 0.068957772 | EW20: 4404 | EX20: 606 | EY20: =EX20/EW20 -> 0.13760218 | EZ20: =SUM(ET20,EW20) -> 8856 | FA20: =SUM(EU20,EX20) -> 913 | FB20: =FA20/EZ20 -> 0.10309395 | FC20: 8856 | FD20: 913 | FE20: =FD20/$FC20 -> 0.10309395 | FF20: 1515 | FG20: =FF20/$FC20 -> 0.17107046 | FH20: 2028 | FI20: =FH20/$FC20 -> 0.22899729 | FJ20: 2452 | FK20: =FJ20/$FC20 -> 0.27687444 | FL20: 3957 | FM20: =FL20/$FC20 -> 0.44681572 | FN20: 526 | FO20: 0.1769852 | FP20: 33 | FQ20: 0.011103634 | FR20: 102 | FS20: 0.066233766 | FT20: 2 | FU20: 0.0012987013 | FV20: 507 | FW20: 0.18283448 | FX20: 5 | FY20: 0.0018031013 | FZ20: 93 | GA20: 0.05 | GB20: 0 | GC20: 0 | GD20: 1228 | GE20: 0.13428103 | GF20: 40 | GG20: 0.0043739748 | GH20: 5802 | GI20: 1453 | GJ20: =GI20/GH20 -> 0.25043089 | GK20: 548 | GL20: =GK20/GI20 -> 0.37715072 | GM20: 681 | GN20: =GM20/GI20 -> 0.46868548 | GO20: 4349 | GP20: =GO20/GH20 -> 0.74956911 | GQ20: 3299 | GR20: =GQ20/GO20 -> 0.75856519 | GS20: 1033 | GT20: =GS20/GO20 -> 0.23752587
A21: Dunn | B21: 45527 | C21: 10609 | D21: 7723 | E21: 3141 | F21: 628 | G21: =C21/B21 -> 0.23302656 | H21: =D21/B21 -> 0.1696356 | I21: =E21/B21 -> 0.068992027 | J21: =F21/B21 -> 0.013794012 | K21: 3623 | L21: =K21/D21 -> 0.46911822 | M21: 4100 | N21: =M21/D21 -> 0.53088178 | O21: 36.1 | P21: 17440 | Q21: 7024 | R21: =Q21/P21 -> 0.40275229 | S21: 5203 | T21: =S21/P21 -> 0.29833716 | U21: 3623 | V21: 153 | W21: =V21/U21 -> 0.042230196 | X21: 2533 | Y21: =X21/U21 -> 0.69914436 | Z21: 45 | AA21: =Z21/U21 -> 0.012420646 | AB21: 376 | AC21: =AB21/U21 -> 0.1037814 | AD21: 516 | AE21: =AD21/U21 -> 0.14242341 | AF21: 4100 | AG21: 248 | AH21: =AG21/AF21 -> 0.060487805 | AI21: 2070 | AJ21: =AI21/AF21 -> 0.50487805 | AK21: 69 | AL21: =AK21/AF21 -> 0.016829268 | AM21: 1073 | AN21: =AM21/AF21 -> 0.26170732 | AO21: 640 | AP21: =AO21/AF21 -> 0.15609756 | AQ21: =SUM(U21,AF21) -> 7723 | AR21: =SUM(V21,AG21) -> 401 | AS21: =AR21/AQ21 -> 0.051922828 | AT21: =SUM(X21,AI21) -> 4603 | AU21: =AT21/AQ21 -> 0.59601191 | AV21: =SUM(Z21,AK21) -> 114 | AW21: =AV21/AQ21 -> 0.014761103 | AX21: =SUM(AB21,AM21) -> 1449 | AY21: =AX21/AQ21 -> 0.18762139 | AZ21: =SUM(AD21,AO21) -> 1156 | BA21: =AZ21/AQ21 -> 0.14968277 | BB21: 3542 | BC21: 1002 | BD21: =BC21/BB21 -> 0.28289102 | BE21: 3944 | BF21: 1132 | BG21: =BF21/BE21 -> 0.28701826 | BH21: =SUM(BB21,BE21) -> 7486 | BI21: =SUM(BC21,BF21) -> 2134 | BJ21: =BI21/BH21 -> 0.28506546 | BK21: 7723 | BL21: 2068 | BM21: =BL21/BK21 -> 0.26777159 | BN21: 3623 | BO21: 766 | BP21: =BO21/BN21 -> 0.21142699 | BQ21: 4100 | BR21: 1302 | BS21: =BR21/BQ21 -> 0.31756098 | BT21: 46135 | BU21: 8263 | BV21: =BU21/BT21 -> 0.1791048 | BW21: =BU21/$BU21 -> 1 | BX21: 42049 | BY21: 8070 | BZ21: =BY21/BX21 -> 0.19191895 | CA21: =BY21/$BU21 -> 0.97664287 | CB21: 395 | CC21: 29 | CD21: =CC21/CB21 -> 0.073417722 | CE21: =CC21/$BU21 -> 0.0035096212 | CF21: 215 | CG21: 27 | CH21: =CG21/CF21 -> 0.1255814 | CI21: =CG21/$BU21 -> 0.0032675784 | CJ21: 1568 | CK21: 49 | CL21: =CK21/CJ21 -> 0.03125 | CM21: =CK21/$BU21 -> 0.0059300496 | CN21: 21 | CO21: 0 | CP21: =CO21/CN21 -> 0 | CQ21: =CO21/$BU21 -> 0 | CR21: 85 | CS21: 0 | CT21: =CS21/CR21 -> 0 | CU21: =CS21/$BU21 -> 0 | CV21: 666 | CW21: 40 | CX21: =CW21/CV21 -> 0.06006006 | CY21: =CW21/$BU21 -> 0.0048408568 | CZ21: 1221 | DA21: 48 | DB21: =DA21/CZ21 -> 0.039312039 | DC21: =DA21/BU21 -> 0.0058090282 | DD21: 3623 | DE21: 302 | DF21: 1408 | DG21: 835 | DH21: 1078 | DI21: =DE21/DD21 -> 0.083356335 | DJ21: =DF21/DD21 -> 0.38862821 | DK21: =SUM(DG21:DH21)/DD21 -> 0.52801546 | DL21: 4100 | DM21: 215 | DN21: 1691 | DO21: 970 | DP21: 1224 | DQ21: =DM21/DL21 -> 0.052439024 | DR21: =DN21/DL21 -> 0.41243902 | DS21: =SUM(DO21:DP21)/DL21 -> 0.53512195 | DT21: =SUM(DL21,DD21) -> 7723 | DU21: =SUM(DM21,DE21) -> 517 | DV21: =SUM(DN21,DF21) -> 3099 | DW21: =SUM(DO21,DG21) -> 1805 | DX21: =SUM(DP21,DH21) -> 2302 | DY21: =DU21/DT21 -> 0.066942898 | DZ21: =DV21/DT21 -> 0.40126894 | EA21: =SUM(DW21:DX21)/DT21 -> 0.53178817 | EB21: 4576 | EC21: 446 | ED21: =EC21/$EB21 -> 0.097465035 | EE21: 952 | EF21: =EE21/$EB21 -> 0.20804196 | EG21: 1440 | EH21: =EG21/$EB21 -> 0.31468531 | EI21: 2080 | EJ21: =EI21/$EB21 -> 0.45454545 | EK21: 2861 | EL21: =EK21/$EB21 -> 0.62521853 | EM21: 3405 | EN21: =EM21/$EB21 -> 0.74409965 | EO21: 74824 | EP21: 45586 | EQ21: 92058 | ER21: 84316 | ES21: 55600 | ET21: 3542 | EU21: 270 | EV21: =EU21/ET21 -> 0.07622812 | EW21: 3944 | EX21: 498 | EY21: =EX21/EW21 -> 0.12626775 | EZ21: =SUM(ET21,EW21) -> 7486 | FA21: =SUM(EU21,EX21) -> 768 | FB21: =FA21/EZ21 -> 0.1025915 | FC21: 7486 | FD21: 768 | FE21: =FD21/$FC21 -> 0.1025915 | FF21: 1328 | FG21: =FF21/$FC21 -> 0.17739781 | FH21: 1952 | FI21: =FH21/$FC21 -> 0.26075341 | FJ21: 2083 | FK21: =FJ21/$FC21 -> 0.27825274 | FL21: 3457 | FM21: =FL21/$FC21 -> 0.46179535 | FN21: 766 | FO21: 0.33304348 | FP21: 28 | FQ21: 0.012173913 | FR21: 159 | FS21: 0.12018141 | FT21: 1 | FU21: 0.0007558579 | FV21: 530 | FW21: 0.23225241 | FX21: 42 | FY21: 0.018404908 | FZ21: 95 | GA21: 0.052255226 | GB21: 0 | GC21: 0 | GD21: 1550 | GE21: 0.20069921 | GF21: 71 | GG21: 0.0091933187 | GH21: 4576 | GI21: 1031 | GJ21: =GI21/GH21 -> 0.22530594 | GK21: 412 | GL21: =GK21/GI21 -> 0.39961203 | GM21: 409 | GN21: =GM21/GI21 -> 0.39670223 | GO21: 3545 | GP21: =GO21/GH21 -> 0.77469406 | GQ21: 2677 | GR21: =GQ21/GO21 -> 0.7551481 | GS21: 854 | GT21: =GS21/GO21 -> 0.24090268
A22: Eau Claire | B22: 107116 | C22: 24867 | D22: 18178 | E22: 7479 | F22: 2246 | G22: =C22/B22 -> 0.23215019 | H22: =D22/B22 -> 0.16970387 | I22: =E22/B22 -> 0.069821502 | J22: =F22/B22 -> 0.020967923 | K22: 8180 | L22: =K22/D22 -> 0.4499945 | M22: 9998 | N22: =M22/D22 -> 0.5500055 | O22: 35.8 | P22: 44726 | Q22: 16899 | R22: =Q22/P22 -> 0.37783392 | S22: 12908 | T22: =S22/P22 -> 0.28860171 | U22: 8180 | V22: 343 | W22: =V22/U22 -> 0.04193154 | X22: 5718 | Y22: =X22/U22 -> 0.699022 | Z22: 116 | AA22: =Z22/U22 -> 0.014180929 | AB22: 729 | AC22: =AB22/U22 -> 0.089119804 | AD22: 1274 | AE22: =AD22/U22 -> 0.15574572 | AF22: 9998 | AG22: 479 | AH22: =AG22/AF22 -> 0.047909582 | AI22: 4579 | AJ22: =AI22/AF22 -> 0.4579916 | AK22: 187 | AL22: =AK22/AF22 -> 0.018703741 | AM22: 3078 | AN22: =AM22/AF22 -> 0.30786157 | AO22: 1675 | AP22: =AO22/AF22 -> 0.16753351 | AQ22: =SUM(U22,AF22) -> 18178 | AR22: =SUM(V22,AG22) -> 822 | AS22: =AR22/AQ22 -> 0.045219496 | AT22: =SUM(X22,AI22) -> 10297 | AU22: =AT22/AQ22 -> 0.56645396 | AV22: =SUM(Z22,AK22) -> 303 | AW22: =AV22/AQ22 -> 0.0166685 | AX22: =SUM(AB22,AM22) -> 3807 | AY22: =AX22/AQ22 -> 0.20942898 | AZ22: =SUM(AD22,AO22) -> 2949 | BA22: =AZ22/AQ22 -> 0.16222907 | BB22: 8036 | BC22: 2169 | BD22: =BC22/BB22 -> 0.2699104 | BE22: 9643 | BF22: 2879 | BG22: =BF22/BE22 -> 0.29855854 | BH22: =SUM(BB22,BE22) -> 17679 | BI22: =SUM(BC22,BF22) -> 5048 | BJ22: =BI22/BH22 -> 0.28553651 | BK22: 18178 | BL22: 5431 | BM22: =BL22/BK22 -> 0.29876774 | BN22: 8180 | BO22: 1542 | BP22: =BO22/BN22 -> 0.18850856 | BQ22: 9998 | BR22: 3889 | BS22: =BR22/BQ22 -> 0.3889778 | BT22: 108830 | BU22: 19458 | BV22: =BU22/BT22 -> 0.17879261 | BW22: =BU22/$BU22 -> 1 | BX22: 95957 | BY22: 18802 | BZ22: =BY22/BX22 -> 0.19594193 | CA22: =BY22/$BU22 -> 0.96628636 | CB22: 1292 | CC22: 86 | CD22: =CC22/CB22 -> 0.066563467 | CE22: =CC22/$BU22 -> 0.0044197759 | CF22: 494 | CG22: 74 | CH22: =CG22/CF22 -> 0.14979757 | CI22: =CG22/$BU22 -> 0.003803063 | CJ22: 5002 | CK22: 263 | CL22: =CK22/CJ22 -> 0.052578968 | CM22: =CK22/$BU22 -> 0.013516291 | CN22: 178 | CO22: 10 | CP22: =CO22/CN22 -> 0.056179775 | CQ22: =CO22/$BU22 -> 0.00051392743 | CR22: 319 | CS22: 0 | CT22: =CS22/CR22 -> 0 | CU22: =CS22/$BU22 -> 0 | CV22: 2171 | CW22: 74 | CX22: =CW22/CV22 -> 0.034085675 | CY22: =CW22/$BU22 -> 0.003803063 | CZ22: 3736 | DA22: 149 | DB22: =DA22/CZ22 -> 0.039882227 | DC22: =DA22/BU22 -> 0.0076575188 | DD22: 8180 | DE22: 344 | DF22: 2186 | DG22: 2574 | DH22: 3076 | DI22: =DE22/DD22 -> 0.04205379 | DJ22: =DF22/DD22 -> 0.26723716 | DK22: =SUM(DG22:DH22)/DD22 -> 0.69070905 | DL22: 9998 | DM22: 417 | DN22: 4154 | DO22: 2621 | DP22: 2806 | DQ22: =DM22/DL22 -> 0.041708342 | DR22: =DN22/DL22 -> 0.4154831 | DS22: =SUM(DO22:DP22)/DL22 -> 0.54280856 | DT22: =SUM(DL22,DD22) -> 18178 | DU22: =SUM(DM22,DE22) -> 761 | DV22: =SUM(DN22,DF22) -> 6340 | DW22: =SUM(DO22,DG22) -> 5195 | DX22: =SUM(DP22,DH22) -> 5882 | DY22: =DU22/DT22 -> 0.041863791 | DZ22: =DV22/DT22 -> 0.34877324 | EA22: =SUM(DW22:DX22)/DT22 -> 0.60936297 | EB22: 11899 | EC22: 828 | ED22: =EC22/$EB22 -> 0.069585679 | EE22: 1810 | EF22: =EE22/$EB22 -> 0.15211362 | EG22: 3151 | EH22: =EG22/$EB22 -> 0.26481217 | EI22: 4816 | EJ22: =EI22/$EB22 -> 0.40473989 | EK22: 7864 | EL22: =EK22/$EB22 -> 0.66089587 | EM22: 9325 | EN22: =EM22/$EB22 -> 0.7836793 | EO22: 74546 | EP22: 44985 | EQ22: 88877 | ER22: 98403 | ES22: 58282 | ET22: 8036 | EU22: 411 | EV22: =EU22/ET22 -> 0.051144848 | EW22: 9643 | EX22: 861 | EY22: =EX22/EW22 -> 0.089287566 | EZ22: =SUM(ET22,EW22) -> 17679 | FA22: =SUM(EU22,EX22) -> 1272 | FB22: =FA22/EZ22 -> 0.071949771 | FC22: 17679 | FD22: 1272 | FE22: =FD22/$FC22 -> 0.071949771 | FF22: 2341 | FG22: =FF22/$FC22 -> 0.13241699 | FH22: 3364 | FI22: =FH22/$FC22 -> 0.19028226 | FJ22: 4115 | FK22: =FJ22/$FC22 -> 0.23276203 | FL22: 7377 | FM22: =FL22/$FC22 -> 0.41727473 | FN22: 1205 | FO22: 0.23856662 | FP22: 14 | FQ22: 0.0027717284 | FR22: 334 | FS22: 0.10674337 | FT22: 0 | FU22: 0 | FV22: 1136 | FW22: 0.20113314 | FX22: 4 | FY22: 0.0007082153 | FZ22: 183 | GA22: 0.042068966 | GB22: 0 | GC22: 0 | GD22: 2858 | GE22: 0.15722302 | GF22: 18 | GG22: 0.00099020794 | GH22: 11899 | GI22: 3107 | GJ22: =GI22/GH22 -> 0.26111438 | GK22: 1244 | GL22: =GK22/GI22 -> 0.40038622 | GM22: 1637 | GN22: =GM22/GI22 -> 0.5268748 | GO22: 8792 | GP22: =GO22/GH22 -> 0.73888562 | GQ22: 7139 | GR22: =GQ22/GO22 -> 0.81198817 | GS22: 1635 | GT22: =GS22/GO22 -> 0.18596451
A23: Florence | B23: 4646 | C23: 1864 | D23: 1361 | E23: 518 | F23: 89 | G23: =C23/B23 -> 0.40120534 | H23: =D23/B23 -> 0.29294016 | I23: =E23/B23 -> 0.11149376 | J23: =F23/B23 -> 0.019156263 | K23: 668 | L23: =K23/D23 -> 0.49081558 | M23: 693 | N23: =M23/D23 -> 0.50918442 | O23: 55.3 | P23: 2197 | Q23: 1192 | R23: =Q23/P23 -> 0.54255803 | S23: 948 | T23: =S23/P23 -> 0.4314975 | U23: 668 | V23: 35 | W23: =V23/U23 -> 0.05239521 | X23: 501 | Y23: =X23/U23 -> 0.75 | Z23: 4 | AA23: =Z23/U23 -> 0.005988024 | AB23: 54 | AC23: =AB23/U23 -> 0.080838323 | AD23: 74 | AE23: =AD23/U23 -> 0.11077844 | AF23: 693 | AG23: 5 | AH23: =AG23/AF23 -> 0.0072150072 | AI23: 440 | AJ23: =AI23/AF23 -> 0.63492063 | AK23: 3 | AL23: =AK23/AF23 -> 0.0043290043 | AM23: 192 | AN23: =AM23/AF23 -> 0.27705628 | AO23: 53 | AP23: =AO23/AF23 -> 0.076479076 | AQ23: =SUM(U23,AF23) -> 1361 | AR23: =SUM(V23,AG23) -> 40 | AS23: =AR23/AQ23 -> 0.029390154 | AT23: =SUM(X23,AI23) -> 941 | AU23: =AT23/AQ23 -> 0.69140338 | AV23: =SUM(Z23,AK23) -> 7 | AW23: =AV23/AQ23 -> 0.005143277 | AX23: =SUM(AB23,AM23) -> 246 | AY23: =AX23/AQ23 -> 0.18074945 | AZ23: =SUM(AD23,AO23) -> 127 | BA23: =AZ23/AQ23 -> 0.09331374 | BB23: 648 | BC23: 244 | BD23: =BC23/BB23 -> 0.37654321 | BE23: 684 | BF23: 139 | BG23: =BF23/BE23 -> 0.20321637 | BH23: =SUM(BB23,BE23) -> 1332 | BI23: =SUM(BC23,BF23) -> 383 | BJ23: =BI23/BH23 -> 0.28753754 | BK23: 1361 | BL23: 290 | BM23: =BL23/BK23 -> 0.21307862 | BN23: 668 | BO23: 105 | BP23: =BO23/BN23 -> 0.15718563 | BQ23: 693 | BR23: 185 | BS23: =BR23/BQ23 -> 0.26695527 | BT23: 4673 | BU23: 1523 | BV23: =BU23/BT23 -> 0.32591483 | BW23: =BU23/$BU23 -> 1 | BX23: 4410 | BY23: 1480 | BZ23: =BY23/BX23 -> 0.33560091 | CA23: =BY23/$BU23 -> 0.97176625 | CB23: 27 | CC23: 6 | CD23: =CC23/CB23 -> 0.22222222 | CE23: =CC23/$BU23 -> 0.0039395929 | CF23: 54 | CG23: 8 | CH23: =CG23/CF23 -> 0.14814815 | CI23: =CG23/$BU23 -> 0.0052527905 | CJ23: 18 | CK23: 6 | CL23: =CK23/CJ23 -> 0.33333333 | CM23: =CK23/$BU23 -> 0.0039395929 | CN23: 1 | CO23: 0 | CP23: =CO23/CN23 -> 0 | CQ23: =CO23/$BU23 -> 0 | CR23: 9 | CS23: 0 | CT23: =CS23/CR23 -> 0 | CU23: =CS23/$BU23 -> 0 | CV23: 80 | CW23: 11 | CX23: =CW23/CV23 -> 0.1375 | CY23: =CW23/$BU23 -> 0.007222587 | CZ23: 83 | DA23: 12 | DB23: =DA23/CZ23 -> 0.14457831 | DC23: =DA23/BU23 -> 0.0078791858 | DD23: 668 | DE23: 93 | DF23: 257 | DG23: 205 | DH23: 113 | DI23: =DE23/DD23 -> 0.13922156 | DJ23: =DF23/DD23 -> 0.38473054 | DK23: =SUM(DG23:DH23)/DD23 -> 0.4760479 | DL23: 693 | DM23: 58 | DN23: 252 | DO23: 207 | DP23: 176 | DQ23: =DM23/DL23 -> 0.083694084 | DR23: =DN23/DL23 -> 0.36363636 | DS23: =SUM(DO23:DP23)/DL23 -> 0.55266955 | DT23: =SUM(DL23,DD23) -> 1361 | DU23: =SUM(DM23,DE23) -> 151 | DV23: =SUM(DN23,DF23) -> 509 | DW23: =SUM(DO23,DG23) -> 412 | DX23: =SUM(DP23,DH23) -> 289 | DY23: =DU23/DT23 -> 0.11094783 | DZ23: =DV23/DT23 -> 0.37398971 | EA23: =SUM(DW23:DX23)/DT23 -> 0.51506245 | EB23: 822 | EC23: 92 | ED23: =EC23/$EB23 -> 0.11192214 | EE23: 183 | EF23: =EE23/$EB23 -> 0.22262774 | EG23: 276 | EH23: =EG23/$EB23 -> 0.33576642 | EI23: 355 | EJ23: =EI23/$EB23 -> 0.43187348 | EK23: 593 | EL23: =EK23/$EB23 -> 0.72141119 | EM23: 678 | EN23: =EM23/$EB23 -> 0.82481752 | EO23: 61086 | EP23: - | EQ23: 100469 | ER23: 60066 | ES23: 53311 | ET23: 648 | EU23: 27 | EV23: =EU23/ET23 -> 0.041666667 | EW23: 684 | EX23: 84 | EY23: =EX23/EW23 -> 0.12280702 | EZ23: =SUM(ET23,EW23) -> 1332 | FA23: =SUM(EU23,EX23) -> 111 | FB23: =FA23/EZ23 -> 0.083333333 | FC23: 1332 | FD23: 111 | FE23: =FD23/$FC23 -> 0.083333333 | FF23: 245 | FG23: =FF23/$FC23 -> 0.18393393 | FH23: 330 | FI23: =FH23/$FC23 -> 0.24774775 | FJ23: 391 | FK23: =FJ23/$FC23 -> 0.29354354 | FL23: 654 | FM23: =FL23/$FC23 -> 0.49099099 | FN23: 86 | FO23: 0.20093458 | FP23: 2 | FQ23: 0.0046728972 | FR23: 13 | FS23: 0.054166667 | FT23: 0 | FU23: 0 | FV23: 63 | FW23: 0.15180723 | FX23: 0 | FY23: 0 | FZ23: 14 | GA23: 0.050359712 | GB23: 0 | GC23: 0 | GD23: 176 | GE23: 0.12931668 | GF23: 2 | GG23: 0.0014695077 | GH23: 822 | GI23: 62 | GJ23: =GI23/GH23 -> 0.075425791 | GK23: 21 | GL23: =GK23/GI23 -> 0.33870968 | GM23: 33 | GN23: =GM23/GI23 -> 0.53225806 | GO23: 760 | GP23: =GO23/GH23 -> 0.92457421 | GQ23: 634 | GR23: =GQ23/GO23 -> 0.83421053 | GS23: 126 | GT23: =GS23/GO23 -> 0.16578947
A24: Fond du Lac | B24: 104137 | C24: 28303 | D24: 20614 | E24: 8440 | F24: 2250 | G24: =C24/B24 -> 0.2717862 | H24: =D24/B24 -> 0.19795078 | I24: =E24/B24 -> 0.081047082 | J24: =F24/B24 -> 0.021606153 | K24: 9397 | L24: =K24/D24 -> 0.45585524 | M24: 11217 | N24: =M24/D24 -> 0.54414476 | O24: 41.9 | P24: 43243 | Q24: 18876 | R24: =Q24/P24 -> 0.43650996 | S24: 14228 | T24: =S24/P24 -> 0.32902435 | U24: 9397 | V24: 619 | W24: =V24/U24 -> 0.065872087 | X24: 6599 | Y24: =X24/U24 -> 0.7022454 | Z24: 321 | AA24: =Z24/U24 -> 0.034159838 | AB24: 855 | AC24: =AB24/U24 -> 0.090986485 | AD24: 1003 | AE24: =AD24/U24 -> 0.10673619 | AF24: 11217 | AG24: 780 | AH24: =AG24/AF24 -> 0.069537309 | AI24: 5087 | AJ24: =AI24/AF24 -> 0.45350807 | AK24: 263 | AL24: =AK24/AF24 -> 0.023446554 | AM24: 3360 | AN24: =AM24/AF24 -> 0.29954533 | AO24: 1727 | AP24: =AO24/AF24 -> 0.15396274 | AQ24: =SUM(U24,AF24) -> 20614 | AR24: =SUM(V24,AG24) -> 1399 | AS24: =AR24/AQ24 -> 0.067866498 | AT24: =SUM(X24,AI24) -> 11686 | AU24: =AT24/AQ24 -> 0.56689628 | AV24: =SUM(Z24,AK24) -> 584 | AW24: =AV24/AQ24 -> 0.028330261 | AX24: =SUM(AB24,AM24) -> 4215 | AY24: =AX24/AQ24 -> 0.20447269 | AZ24: =SUM(AD24,AO24) -> 2730 | BA24: =AZ24/AQ24 -> 0.13243427 | BB24: 9253 | BC24: 2064 | BD24: =BC24/BB24 -> 0.22306279 | BE24: 10741 | BF24: 2761 | BG24: =BF24/BE24 -> 0.25705242 | BH24: =SUM(BB24,BE24) -> 19994 | BI24: =SUM(BC24,BF24) -> 4825 | BJ24: =BI24/BH24 -> 0.2413224 | BK24: 20614 | BL24: 5793 | BM24: =BL24/BK24 -> 0.28102261 | BN24: 9397 | BO24: 1951 | BP24: =BO24/BN24 -> 0.20761945 | BQ24: 11217 | BR24: 3842 | BS24: =BR24/BQ24 -> 0.34251582 | BT24: 104269 | BU24: 21821 | BV24: =BU24/BT24 -> 0.20927601 | BW24: =BU24/$BU24 -> 1 | BX24: 89800 | BY24: 21060 | BZ24: =BY24/BX24 -> 0.23452116 | CA24: =BY24/$BU24 -> 0.96512534 | CB24: 2433 | CC24: 71 | CD24: =CC24/CB24 -> 0.02918208 | CE24: =CC24/$BU24 -> 0.0032537464 | CF24: 478 | CG24: 80 | CH24: =CG24/CF24 -> 0.16736402 | CI24: =CG24/$BU24 -> 0.0036661931 | CJ24: 2318 | CK24: 133 | CL24: =CK24/CJ24 -> 0.057377049 | CM24: =CK24/$BU24 -> 0.0060950461 | CN24: 40 | CO24: 5 | CP24: =CO24/CN24 -> 0.125 | CQ24: =CO24/$BU24 -> 0.00022913707 | CR24: 1754 | CS24: 21 | CT24: =CS24/CR24 -> 0.011972634 | CU24: =CS24/$BU24 -> 0.00096237569 | CV24: 1672 | CW24: 80 | CX24: =CW24/CV24 -> 0.04784689 | CY24: =CW24/$BU24 -> 0.0036661931 | CZ24: 7528 | DA24: 392 | DB24: =DA24/CZ24 -> 0.052072264 | DC24: =DA24/BU24 -> 0.017964346 | DD24: 9397 | DE24: 751 | DF24: 4012 | DG24: 2629 | DH24: 2005 | DI24: =DE24/DD24 -> 0.079919123 | DJ24: =DF24/DD24 -> 0.42694477 | DK24: =SUM(DG24:DH24)/DD24 -> 0.49313611 | DL24: 11217 | DM24: 729 | DN24: 5496 | DO24: 2693 | DP24: 2299 | DQ24: =DM24/DL24 -> 0.064990639 | DR24: =DN24/DL24 -> 0.48997058 | DS24: =SUM(DO24:DP24)/DL24 -> 0.44503878 | DT24: =SUM(DL24,DD24) -> 20614 | DU24: =SUM(DM24,DE24) -> 1480 | DV24: =SUM(DN24,DF24) -> 9508 | DW24: =SUM(DO24,DG24) -> 5322 | DX24: =SUM(DP24,DH24) -> 4304 | DY24: =DU24/DT24 -> 0.071795867 | DZ24: =DV24/DT24 -> 0.46123993 | EA24: =SUM(DW24:DX24)/DT24 -> 0.4669642 | EB24: 12936 | EC24: 1056 | ED24: =EC24/$EB24 -> 0.081632653 | EE24: 2548 | EF24: =EE24/$EB24 -> 0.1969697 | EG24: 3785 | EH24: =EG24/$EB24 -> 0.29259431 | EI24: 5658 | EJ24: =EI24/$EB24 -> 0.43738404 | EK24: 8628 | EL24: =EK24/$EB24 -> 0.66697588 | EM24: 10292 | EN24: =EM24/$EB24 -> 0.79560915 | EO24: 74275 | EP24: 58894 | EQ24: 86498 | ER24: 90376 | ES24: 55400 | ET24: 9253 | EU24: 586 | EV24: =EU24/ET24 -> 0.063330812 | EW24: 10741 | EX24: 1337 | EY24: =EX24/EW24 -> 0.12447631 | EZ24: =SUM(ET24,EW24) -> 19994 | FA24: =SUM(EU24,EX24) -> 1923 | FB24: =FA24/EZ24 -> 0.096178854 | FC24: 19994 | FD24: 1923 | FE24: =FD24/$FC24 -> 0.096178854 | FF24: 3416 | FG24: =FF24/$FC24 -> 0.17085126 | FH24: 4396 | FI24: =FH24/$FC24 -> 0.21986596 | FJ24: 4963 | FK24: =FJ24/$FC24 -> 0.24822447 | FL24: 8777 | FM24: =FL24/$FC24 -> 0.43898169 | FN24: 1567 | FO24: 0.26327285 | FP24: 16 | FQ24: 0.002688172 | FR24: 190 | FS24: 0.055152395 | FT24: 0 | FU24: 0 | FV24: 1120 | FW24: 0.18000643 | FX24: 68 | FY24: 0.010928962 | FZ24: 343 | GA24: 0.068668669 | GB24: 0 | GC24: 0 | GD24: 3220 | GE24: 0.15620452 | GF24: 84 | GG24: 0.0040749006 | GH24: 12936 | GI24: 2845 | GJ24: =GI24/GH24 -> 0.21992888 | GK24: 1057 | GL24: =GK24/GI24 -> 0.371529 | GM24: 1616 | GN24: =GM24/GI24 -> 0.56801406 | GO24: 10091 | GP24: =GO24/GH24 -> 0.78007112 | GQ24: 7713 | GR24: =GQ24/GO24 -> 0.76434447 | GS24: 2350 | GT24: =GS24/GO24 -> 0.23288078
A25: Forest | B25: 9369 | C25: 3284 | D25: 2376 | E25: 899 | F25: 267 | G25: =C25/B25 -> 0.35051766 | H25: =D25/B25 -> 0.25360231 | I25: =E25/B25 -> 0.095954744 | J25: =F25/B25 -> 0.028498239 | K25: 1184 | L25: =K25/D25 -> 0.4983165 | M25: 1192 | N25: =M25/D25 -> 0.5016835 | O25: 49.3 | P25: 4006 | Q25: 2167 | R25: =Q25/P25 -> 0.54093859 | S25: 1624 | T25: =S25/P25 -> 0.40539191 | U25: 1184 | V25: 47 | W25: =V25/U25 -> 0.039695946 | X25: 736 | Y25: =X25/U25 -> 0.62162162 | Z25: 39 | AA25: =Z25/U25 -> 0.032939189 | AB25: 126 | AC25: =AB25/U25 -> 0.10641892 | AD25: 236 | AE25: =AD25/U25 -> 0.19932432 | AF25: 1192 | AG25: 59 | AH25: =AG25/AF25 -> 0.049496644 | AI25: 668 | AJ25: =AI25/AF25 -> 0.56040268 | AK25: 33 | AL25: =AK25/AF25 -> 0.027684564 | AM25: 315 | AN25: =AM25/AF25 -> 0.26426174 | AO25: 117 | AP25: =AO25/AF25 -> 0.098154362 | AQ25: =SUM(U25,AF25) -> 2376 | AR25: =SUM(V25,AG25) -> 106 | AS25: =AR25/AQ25 -> 0.044612795 | AT25: =SUM(X25,AI25) -> 1404 | AU25: =AT25/AQ25 -> 0.59090909 | AV25: =SUM(Z25,AK25) -> 72 | AW25: =AV25/AQ25 -> 0.03030303 | AX25: =SUM(AB25,AM25) -> 441 | AY25: =AX25/AQ25 -> 0.18560606 | AZ25: =SUM(AD25,AO25) -> 353 | BA25: =AZ25/AQ25 -> 0.14856902 | BB25: 1143 | BC25: 470 | BD25: =BC25/BB25 -> 0.4111986 | BE25: 1119 | BF25: 320 | BG25: =BF25/BE25 -> 0.28596962 | BH25: =SUM(BB25,BE25) -> 2262 | BI25: =SUM(BC25,BF25) -> 790 | BJ25: =BI25/BH25 -> 0.34924845 | BK25: 2376 | BL25: 622 | BM25: =BL25/BK25 -> 0.26178451 | BN25: 1184 | BO25: 309 | BP25: =BO25/BN25 -> 0.26097973 | BQ25: 1192 | BR25: 313 | BS25: =BR25/BQ25 -> 0.26258389 | BT25: 9506 | BU25: 2518 | BV25: =BU25/BT25 -> 0.26488534 | BW25: =BU25/$BU25 -> 1 | BX25: 7610 | BY25: 2327 | BZ25: =BY25/BX25 -> 0.30578187 | CA25: =BY25/$BU25 -> 0.92414615 | CB25: 87 | CC25: 4 | CD25: =CC25/CB25 -> 0.045977011 | CE25: =CC25/$BU25 -> 0.0015885624 | CF25: 1269 | CG25: 144 | CH25: =CG25/CF25 -> 0.11347518 | CI25: =CG25/$BU25 -> 0.057188245 | CJ25: 33 | CK25: 5 | CL25: =CK25/CJ25 -> 0.15151515 | CM25: =CK25/$BU25 -> 0.0019857029 | CN25: 13 | CO25: 3 | CP25: =CO25/CN25 -> 0.23076923 | CQ25: =CO25/$BU25 -> 0.0011914218 | CR25: 9 | CS25: 0 | CT25: =CS25/CR25 -> 0 | CU25: =CS25/$BU25 -> 0 | CV25: 269 | CW25: 24 | CX25: =CW25/CV25 -> 0.089219331 | CY25: =CW25/$BU25 -> 0.0095313741 | CZ25: 225 | DA25: 11 | DB25: =DA25/CZ25 -> 0.048888889 | DC25: =DA25/BU25 -> 0.0043685465 | DD25: 1184 | DE25: 140 | DF25: 405 | DG25: 438 | DH25: 201 | DI25: =DE25/DD25 -> 0.11824324 | DJ25: =DF25/DD25 -> 0.34206081 | DK25: =SUM(DG25:DH25)/DD25 -> 0.53969595 | DL25: 1192 | DM25: 95 | DN25: 510 | DO25: 377 | DP25: 210 | DQ25: =DM25/DL25 -> 0.079697987 | DR25: =DN25/DL25 -> 0.42785235 | DS25: =SUM(DO25:DP25)/DL25 -> 0.49244966 | DT25: =SUM(DL25,DD25) -> 2376 | DU25: =SUM(DM25,DE25) -> 235 | DV25: =SUM(DN25,DF25) -> 915 | DW25: =SUM(DO25,DG25) -> 815 | DX25: =SUM(DP25,DH25) -> 411 | DY25: =DU25/DT25 -> 0.098905724 | DZ25: =DV25/DT25 -> 0.38510101 | EA25: =SUM(DW25:DX25)/DT25 -> 0.51599327 | EB25: 1446 | EC25: 160 | ED25: =EC25/$EB25 -> 0.11065007 | EE25: 353 | EF25: =EE25/$EB25 -> 0.24412172 | EG25: 589 | EH25: =EG25/$EB25 -> 0.40733057 | EI25: 821 | EJ25: =EI25/$EB25 -> 0.56777317 | EK25: 1102 | EL25: =EK25/$EB25 -> 0.76210235 | EM25: 1238 | EN25: =EM25/$EB25 -> 0.85615491 | EO25: 61071 | EP25: 67750 | EQ25: 72879 | ER25: 81726 | ES25: 43456 | ET25: 1143 | EU25: 102 | EV25: =EU25/ET25 -> 0.089238845 | EW25: 1119 | EX25: 133 | EY25: =EX25/EW25 -> 0.11885612 | EZ25: =SUM(ET25,EW25) -> 2262 | FA25: =SUM(EU25,EX25) -> 235 | FB25: =FA25/EZ25 -> 0.10389036 | FC25: 2262 | FD25: 235 | FE25: =FD25/$FC25 -> 0.10389036 | FF25: 439 | FG25: =FF25/$FC25 -> 0.19407604 | FH25: 690 | FI25: =FH25/$FC25 -> 0.30503979 | FJ25: 797 | FK25: =FJ25/$FC25 -> 0.35234306 | FL25: 1266 | FM25: =FL25/$FC25 -> 0.5596817 | FN25: 90 | FO25: 0.12064343 | FP25: 5 | FQ25: 0.0067024129 | FR25: 46 | FS25: 0.10502283 | FT25: 0 | FU25: 0 | FV25: 75 | FW25: 0.10259918 | FX25: 0 | FY25: 0 | FZ25: 19 | GA25: 0.041214751 | GB25: 0 | GC25: 0 | GD25: 230 | GE25: 0.096801347 | GF25: 5 | GG25: 0.0021043771 | GH25: 1446 | GI25: 214 | GJ25: =GI25/GH25 -> 0.14799447 | GK25: 80 | GL25: =GK25/GI25 -> 0.37383178 | GM25: 23 | GN25: =GM25/GI25 -> 0.10747664 | GO25: 1232 | GP25: =GO25/GH25 -> 0.85200553 | GQ25: 936 | GR25: =GQ25/GO25 -> 0.75974026 | GS25: 274 | GT25: =GS25/GO25 -> 0.2224026
A26: Grant | B26: 51770 | C26: 13192 | D26: 9591 | E26: 4001 | F26: 1118 | G26: =C26/B26 -> 0.25481939 | H26: =D26/B26 -> 0.18526173 | I26: =E26/B26 -> 0.077284141 | J26: =F26/B26 -> 0.021595519 | K26: 4407 | L26: =K26/D26 -> 0.45949327 | M26: 5184 | N26: =M26/D26 -> 0.54050673 | O26: 36.8 | P26: 19960 | Q26: 8540 | R26: =Q26/P26 -> 0.42785571 | S26: 6410 | T26: =S26/P26 -> 0.32114228 | U26: 4407 | V26: 286 | W26: =V26/U26 -> 0.064896755 | X26: 3085 | Y26: =X26/U26 -> 0.70002269 | Z26: 118 | AA26: =Z26/U26 -> 0.026775584 | AB26: 403 | AC26: =AB26/U26 -> 0.091445428 | AD26: 515 | AE26: =AD26/U26 -> 0.11685954 | AF26: 5184 | AG26: 515 | AH26: =AG26/AF26 -> 0.099344136 | AI26: 2510 | AJ26: =AI26/AF26 -> 0.4841821 | AK26: 138 | AL26: =AK26/AF26 -> 0.02662037 | AM26: 1500 | AN26: =AM26/AF26 -> 0.28935185 | AO26: 521 | AP26: =AO26/AF26 -> 0.10050154 | AQ26: =SUM(U26,AF26) -> 9591 | AR26: =SUM(V26,AG26) -> 801 | AS26: =AR26/AQ26 -> 0.083515796 | AT26: =SUM(X26,AI26) -> 5595 | AU26: =AT26/AQ26 -> 0.5833594 | AV26: =SUM(Z26,AK26) -> 256 | AW26: =AV26/AQ26 -> 0.02669169 | AX26: =SUM(AB26,AM26) -> 1903 | AY26: =AX26/AQ26 -> 0.19841518 | AZ26: =SUM(AD26,AO26) -> 1036 | BA26: =AZ26/AQ26 -> 0.10801793 | BB26: 4259 | BC26: 1275 | BD26: =BC26/BB26 -> 0.29936605 | BE26: 4916 | BF26: 1139 | BG26: =BF26/BE26 -> 0.23169243 | BH26: =SUM(BB26,BE26) -> 9175 | BI26: =SUM(BC26,BF26) -> 2414 | BJ26: =BI26/BH26 -> 0.26310627 | BK26: 9591 | BL26: 2534 | BM26: =BL26/BK26 -> 0.26420603 | BN26: 4407 | BO26: 812 | BP26: =BO26/BN26 -> 0.18425233 | BQ26: 5184 | BR26: 1722 | BS26: =BR26/BQ26 -> 0.33217593 | BT26: 52330 | BU26: 10100 | BV26: =BU26/BT26 -> 0.19300592 | BW26: =BU26/$BU26 -> 1 | BX26: 48985 | BY26: 9917 | BZ26: =BY26/BX26 -> 0.20244973 | CA26: =BY26/$BU26 -> 0.98188119 | CB26: 776 | CC26: 34 | CD26: =CC26/CB26 -> 0.043814433 | CE26: =CC26/$BU26 -> 0.0033663366 | CF26: 113 | CG26: 26 | CH26: =CG26/CF26 -> 0.2300885 | CI26: =CG26/$BU26 -> 0.0025742574 | CJ26: 517 | CK26: 31 | CL26: =CK26/CJ26 -> 0.059961315 | CM26: =CK26/$BU26 -> 0.0030693069 | CN26: 19 | CO26: 2 | CP26: =CO26/CN26 -> 0.10526316 | CQ26: =CO26/$BU26 -> 0.0001980198 | CR26: 149 | CS26: 0 | CT26: =CS26/CR26 -> 0 | CU26: =CS26/$BU26 -> 0 | CV26: 478 | CW26: 39 | CX26: =CW26/CV26 -> 0.081589958 | CY26: =CW26/$BU26 -> 0.0038613861 | CZ26: 1442 | DA26: 51 | DB26: =DA26/CZ26 -> 0.035367545 | DC26: =DA26/BU26 -> 0.005049505 | DD26: 4407 | DE26: 309 | DF26: 2162 | DG26: 1047 | DH26: 889 | DI26: =DE26/DD26 -> 0.070115725 | DJ26: =DF26/DD26 -> 0.49058316 | DK26: =SUM(DG26:DH26)/DD26 -> 0.43930111 | DL26: 5184 | DM26: 212 | DN26: 2383 | DO26: 1421 | DP26: 1168 | DQ26: =DM26/DL26 -> 0.040895062 | DR26: =DN26/DL26 -> 0.45968364 | DS26: =SUM(DO26:DP26)/DL26 -> 0.4994213 | DT26: =SUM(DL26,DD26) -> 9591 | DU26: =SUM(DM26,DE26) -> 521 | DV26: =SUM(DN26,DF26) -> 4545 | DW26: =SUM(DO26,DG26) -> 2468 | DX26: =SUM(DP26,DH26) -> 2057 | DY26: =DU26/DT26 -> 0.05432176 | DZ26: =DV26/DT26 -> 0.47388176 | EA26: =SUM(DW26:DX26)/DT26 -> 0.47179648 | EB26: 5831 | EC26: 477 | ED26: =EC26/$EB26 -> 0.08180415 | EE26: 1094 | EF26: =EE26/$EB26 -> 0.1876179 | EG26: 1843 | EH26: =EG26/$EB26 -> 0.31606928 | EI26: 2686 | EJ26: =EI26/$EB26 -> 0.4606414 | EK26: 4067 | EL26: =EK26/$EB26 -> 0.69747899 | EM26: 4780 | EN26: =EM26/$EB26 -> 0.81975647 | EO26: 66858 | EP26: 32319 | EQ26: 79621 | ER26: 88212 | ES26: 53912 | ET26: 4259 | EU26: 250 | EV26: =EU26/ET26 -> 0.058699225 | EW26: 4916 | EX26: 536 | EY26: =EX26/EW26 -> 0.10903173 | EZ26: =SUM(ET26,EW26) -> 9175 | FA26: =SUM(EU26,EX26) -> 786 | FB26: =FA26/EZ26 -> 0.085667575 | FC26: 9175 | FD26: 786 | FE26: =FD26/$FC26 -> 0.085667575 | FF26: 1644 | FG26: =FF26/$FC26 -> 0.17918256 | FH26: 2299 | FI26: =FH26/$FC26 -> 0.25057221 | FJ26: 2617 | FK26: =FJ26/$FC26 -> 0.28523161 | FL26: 4314 | FM26: =FL26/$FC26 -> 0.47019074 | FN26: 873 | FO26: 0.31459459 | FP26: 30 | FQ26: 0.010810811 | FR26: 105 | FS26: 0.064338235 | FT26: 0 | FU26: 0 | FV26: 700 | FW26: 0.24866785 | FX26: 45 | FY26: 0.01598579 | FZ26: 139 | GA26: 0.058674546 | GB26: 3 | GC26: 0.0012663571 | GD26: 1817 | GE26: 0.18944844 | GF26: 78 | GG26: 0.0081326243 | GH26: 5831 | GI26: 925 | GJ26: =GI26/GH26 -> 0.15863488 | GK26: 323 | GL26: =GK26/GI26 -> 0.34918919 | GM26: 394 | GN26: =GM26/GI26 -> 0.42594595 | GO26: 4906 | GP26: =GO26/GH26 -> 0.84136512 | GQ26: 3905 | GR26: =GQ26/GO26 -> 0.79596413 | GS26: 932 | GT26: =GS26/GO26 -> 0.18997146
A27: Green | B27: 37017 | C27: 10579 | D27: 7634 | E27: 3001 | F27: 1005 | G27: =C27/B27 -> 0.28578761 | H27: =D27/B27 -> 0.20622957 | I27: =E27/B27 -> 0.081070859 | J27: =F27/B27 -> 0.027149688 | K27: 3674 | L27: =K27/D27 -> 0.48126801 | M27: 3960 | N27: =M27/D27 -> 0.51873199 | O27: 43.6 | P27: 15775 | Q27: 7326 | R27: =Q27/P27 -> 0.46440571 | S27: 5491 | T27: =S27/P27 -> 0.34808241 | U27: 3674 | V27: 164 | W27: =V27/U27 -> 0.044637997 | X27: 2438 | Y27: =X27/U27 -> 0.66358193 | Z27: 110 | AA27: =Z27/U27 -> 0.02994012 | AB27: 488 | AC27: =AB27/U27 -> 0.13282526 | AD27: 474 | AE27: =AD27/U27 -> 0.1290147 | AF27: 3960 | AG27: 164 | AH27: =AG27/AF27 -> 0.041414141 | AI27: 1779 | AJ27: =AI27/AF27 -> 0.44924242 | AK27: 147 | AL27: =AK27/AF27 -> 0.037121212 | AM27: 1252 | AN27: =AM27/AF27 -> 0.31616162 | AO27: 618 | AP27: =AO27/AF27 -> 0.15606061 | AQ27: =SUM(U27,AF27) -> 7634 | AR27: =SUM(V27,AG27) -> 328 | AS27: =AR27/AQ27 -> 0.04296568 | AT27: =SUM(X27,AI27) -> 4217 | AU27: =AT27/AQ27 -> 0.55239717 | AV27: =SUM(Z27,AK27) -> 257 | AW27: =AV27/AQ27 -> 0.033665182 | AX27: =SUM(AB27,AM27) -> 1740 | AY27: =AX27/AQ27 -> 0.22792769 | AZ27: =SUM(AD27,AO27) -> 1092 | BA27: =AZ27/AQ27 -> 0.14304428 | BB27: 3617 | BC27: 1132 | BD27: =BC27/BB27 -> 0.31296655 | BE27: 3780 | BF27: 915 | BG27: =BF27/BE27 -> 0.24206349 | BH27: =SUM(BB27,BE27) -> 7397 | BI27: =SUM(BC27,BF27) -> 2047 | BJ27: =BI27/BH27 -> 0.27673381 | BK27: 7634 | BL27: 2442 | BM27: =BL27/BK27 -> 0.31988473 | BN27: 3674 | BO27: 863 | BP27: =BO27/BN27 -> 0.23489385 | BQ27: 3960 | BR27: 1579 | BS27: =BR27/BQ27 -> 0.39873737 | BT27: 37183 | BU27: 8210 | BV27: =BU27/BT27 -> 0.22079983 | BW27: =BU27/$BU27 -> 1 | BX27: 34416 | BY27: 8034 | BZ27: =BY27/BX27 -> 0.23343794 | CA27: =BY27/$BU27 -> 0.97856273 | CB27: 279 | CC27: 20 | CD27: =CC27/CB27 -> 0.071684588 | CE27: =CC27/$BU27 -> 0.0024360536 | CF27: 93 | CG27: 13 | CH27: =CG27/CF27 -> 0.13978495 | CI27: =CG27/$BU27 -> 0.0015834348 | CJ27: 235 | CK27: 24 | CL27: =CK27/CJ27 -> 0.10212766 | CM27: =CK27/$BU27 -> 0.0029232643 | CN27: 21 | CO27: 0 | CP27: =CO27/CN27 -> 0 | CQ27: =CO27/$BU27 -> 0 | CR27: 134 | CS27: 0 | CT27: =CS27/CR27 -> 0 | CU27: =CS27/$BU27 -> 0 | CV27: 480 | CW27: 30 | CX27: =CW27/CV27 -> 0.0625 | CY27: =CW27/$BU27 -> 0.0036540804 | CZ27: 1659 | DA27: 89 | DB27: =DA27/CZ27 -> 0.053646775 | DC27: =DA27/BU27 -> 0.010840438 | DD27: 3674 | DE27: 289 | DF27: 1581 | DG27: 1006 | DH27: 798 | DI27: =DE27/DD27 -> 0.07866086 | DJ27: =DF27/DD27 -> 0.43032118 | DK27: =SUM(DG27:DH27)/DD27 -> 0.49101796 | DL27: 3960 | DM27: 356 | DN27: 1724 | DO27: 1098 | DP27: 782 | DQ27: =DM27/DL27 -> 0.08989899 | DR27: =DN27/DL27 -> 0.43535354 | DS27: =SUM(DO27:DP27)/DL27 -> 0.47474747 | DT27: =SUM(DL27,DD27) -> 7634 | DU27: =SUM(DM27,DE27) -> 645 | DV27: =SUM(DN27,DF27) -> 3305 | DW27: =SUM(DO27,DG27) -> 2104 | DX27: =SUM(DP27,DH27) -> 1580 | DY27: =DU27/DT27 -> 0.084490438 | DZ27: =DV27/DT27 -> 0.43293162 | EA27: =SUM(DW27:DX27)/DT27 -> 0.48257794 | EB27: 4968 | EC27: 489 | ED27: =EC27/$EB27 -> 0.098429952 | EE27: 962 | EF27: =EE27/$EB27 -> 0.19363929 | EG27: 1502 | EH27: =EG27/$EB27 -> 0.30233494 | EI27: 2110 | EJ27: =EI27/$EB27 -> 0.4247182 | EK27: 3158 | EL27: =EK27/$EB27 -> 0.63566828 | EM27: 3845 | EN27: =EM27/$EB27 -> 0.7739533 | EO27: 82852 | EP27: 60000 | EQ27: 94803 | ER27: 97264 | ES27: 56372 | ET27: 3617 | EU27: 168 | EV27: =EU27/ET27 -> 0.046447332 | EW27: 3780 | EX27: 479 | EY27: =EX27/EW27 -> 0.12671958 | EZ27: =SUM(ET27,EW27) -> 7397 | FA27: =SUM(EU27,EX27) -> 647 | FB27: =FA27/EZ27 -> 0.087467892 | FC27: 7397 | FD27: 647 | FE27: =FD27/$FC27 -> 0.087467892 | FF27: 1103 | FG27: =FF27/$FC27 -> 0.14911451 | FH27: 1641 | FI27: =FH27/$FC27 -> 0.22184669 | FJ27: 1867 | FK27: =FJ27/$FC27 -> 0.25239962 | FL27: 3048 | FM27: =FL27/$FC27 -> 0.41205894 | FN27: 735 | FO27: 0.31504501 | FP27: 4 | FQ27: 0.0017145306 | FR27: 150 | FS27: 0.11185682 | FT27: 1 | FU27: 0.00074571216 | FV27: 538 | FW27: 0.23391304 | FX27: 8 | FY27: 0.0034782609 | FZ27: 78 | GA27: 0.046987952 | GB27: 4 | GC27: 0.0024096386 | GD27: 1501 | GE27: 0.19662038 | GF27: 17 | GG27: 0.0022268797 | GH27: 4968 | GI27: 1038 | GJ27: =GI27/GH27 -> 0.2089372 | GK27: 401 | GL27: =GK27/GI27 -> 0.38631985 | GM27: 501 | GN27: =GM27/GI27 -> 0.48265896 | GO27: 3930 | GP27: =GO27/GH27 -> 0.7910628 | GQ27: 3034 | GR27: =GQ27/GO27 -> 0.77201018 | GS27: 821 | GT27: =GS27/GO27 -> 0.20890585
A28: Green Lake | B28: 19263 | C28: 6268 | D28: 4527 | E28: 1852 | F28: 558 | G28: =C28/B28 -> 0.32539065 | H28: =D28/B28 -> 0.23501012 | I28: =E28/B28 -> 0.096142865 | J28: =F28/B28 -> 0.028967451 | K28: 2137 | L28: =K28/D28 -> 0.47205655 | M28: 2390 | N28: =M28/D28 -> 0.52794345 | O28: 45.6 | P28: 8285 | Q28: 4173 | R28: =Q28/P28 -> 0.50368135 | S28: 3161 | T28: =S28/P28 -> 0.38153289 | U28: 2137 | V28: 111 | W28: =V28/U28 -> 0.051941975 | X28: 1494 | Y28: =X28/U28 -> 0.6991109 | Z28: 58 | AA28: =Z28/U28 -> 0.027140852 | AB28: 238 | AC28: =AB28/U28 -> 0.11137108 | AD28: 236 | AE28: =AD28/U28 -> 0.11043519 | AF28: 2390 | AG28: 161 | AH28: =AG28/AF28 -> 0.067364017 | AI28: 1106 | AJ28: =AI28/AF28 -> 0.46276151 | AK28: 47 | AL28: =AK28/AF28 -> 0.019665272 | AM28: 665 | AN28: =AM28/AF28 -> 0.27824268 | AO28: 411 | AP28: =AO28/AF28 -> 0.17196653 | AQ28: =SUM(U28,AF28) -> 4527 | AR28: =SUM(V28,AG28) -> 272 | AS28: =AR28/AQ28 -> 0.060083941 | AT28: =SUM(X28,AI28) -> 2600 | AU28: =AT28/AQ28 -> 0.57433179 | AV28: =SUM(Z28,AK28) -> 105 | AW28: =AV28/AQ28 -> 0.023194168 | AX28: =SUM(AB28,AM28) -> 903 | AY28: =AX28/AQ28 -> 0.19946985 | AZ28: =SUM(AD28,AO28) -> 647 | BA28: =AZ28/AQ28 -> 0.14292026 | BB28: 2112 | BC28: 591 | BD28: =BC28/BB28 -> 0.27982955 | BE28: 2320 | BF28: 875 | BG28: =BF28/BE28 -> 0.37715517 | BH28: =SUM(BB28,BE28) -> 4432 | BI28: =SUM(BC28,BF28) -> 1466 | BJ28: =BI28/BH28 -> 0.33077617 | BK28: 4527 | BL28: 1276 | BM28: =BL28/BK28 -> 0.28186437 | BN28: 2137 | BO28: 501 | BP28: =BO28/BN28 -> 0.2344408 | BQ28: 2390 | BR28: 775 | BS28: =BR28/BQ28 -> 0.32426778 | BT28: 19370 | BU28: 4833 | BV28: =BU28/BT28 -> 0.24950955 | BW28: =BU28/$BU28 -> 1 | BX28: 17624 | BY28: 4674 | BZ28: =BY28/BX28 -> 0.26520654 | CA28: =BY28/$BU28 -> 0.96710118 | CB28: 141 | CC28: 12 | CD28: =CC28/CB28 -> 0.085106383 | CE28: =CC28/$BU28 -> 0.0024829299 | CF28: 90 | CG28: 19 | CH28: =CG28/CF28 -> 0.21111111 | CI28: =CG28/$BU28 -> 0.0039313056 | CJ28: 160 | CK28: 16 | CL28: =CK28/CJ28 -> 0.1 | CM28: =CK28/$BU28 -> 0.0033105731 | CN28: 8 | CO28: 1 | CP28: =CO28/CN28 -> 0.125 | CQ28: =CO28/$BU28 -> 0.00020691082 | CR28: 356 | CS28: 12 | CT28: =CS28/CR28 -> 0.033707865 | CU28: =CS28/$BU28 -> 0.0024829299 | CV28: 208 | CW28: 28 | CX28: =CW28/CV28 -> 0.13461538 | CY28: =CW28/$BU28 -> 0.005793503 | CZ28: 1139 | DA28: 83 | DB28: =DA28/CZ28 -> 0.072870939 | DC28: =DA28/BU28 -> 0.017173598 | DD28: 2137 | DE28: 165 | DF28: 956 | DG28: 498 | DH28: 518 | DI28: =DE28/DD28 -> 0.077211044 | DJ28: =DF28/DD28 -> 0.44735611 | DK28: =SUM(DG28:DH28)/DD28 -> 0.47543285 | DL28: 2390 | DM28: 164 | DN28: 977 | DO28: 739 | DP28: 510 | DQ28: =DM28/DL28 -> 0.068619247 | DR28: =DN28/DL28 -> 0.40878661 | DS28: =SUM(DO28:DP28)/DL28 -> 0.52259414 | DT28: =SUM(DL28,DD28) -> 4527 | DU28: =SUM(DM28,DE28) -> 329 | DV28: =SUM(DN28,DF28) -> 1933 | DW28: =SUM(DO28,DG28) -> 1237 | DX28: =SUM(DP28,DH28) -> 1028 | DY28: =DU28/DT28 -> 0.072675061 | DZ28: =DV28/DT28 -> 0.42699359 | EA28: =SUM(DW28:DX28)/DT28 -> 0.50033135 | EB28: 2895 | EC28: 235 | ED28: =EC28/$EB28 -> 0.081174439 | EE28: 624 | EF28: =EE28/$EB28 -> 0.21554404 | EG28: 1050 | EH28: =EG28/$EB28 -> 0.3626943 | EI28: 1415 | EJ28: =EI28/$EB28 -> 0.48877375 | EK28: 1948 | EL28: =EK28/$EB28 -> 0.67288428 | EM28: 2237 | EN28: =EM28/$EB28 -> 0.77271157 | EO28: 68196 | EP28: 62500 | EQ28: 80735 | ER28: 85196 | ES28: 51563 | ET28: 2112 | EU28: 138 | EV28: =EU28/ET28 -> 0.065340909 | EW28: 2320 | EX28: 362 | EY28: =EX28/EW28 -> 0.15603448 | EZ28: =SUM(ET28,EW28) -> 4432 | FA28: =SUM(EU28,EX28) -> 500 | FB28: =FA28/EZ28 -> 0.11281588 | FC28: 4432 | FD28: 500 | FE28: =FD28/$FC28 -> 0.11281588 | FF28: 976 | FG28: =FF28/$FC28 -> 0.22021661 | FH28: 1234 | FI28: =FH28/$FC28 -> 0.2784296 | FJ28: 1413 | FK28: =FJ28/$FC28 -> 0.31881769 | FL28: 2092 | FM28: =FL28/$FC28 -> 0.47202166 | FN28: 356 | FO28: 0.26350851 | FP28: 27 | FQ28: 0.019985196 | FR28: 77 | FS28: 0.097964377 | FT28: 0 | FU28: 0 | FV28: 420 | FW28: 0.31722054 | FX28: 9 | FY28: 0.0067975831 | FZ28: 38 | GA28: 0.03564728 | GB28: 0 | GC28: 0 | GD28: 891 | GE28: 0.19681909 | GF28: 36 | GG28: 0.0079522863 | GH28: 2895 | GI28: 559 | GJ28: =GI28/GH28 -> 0.19309154 | GK28: 148 | GL28: =GK28/GI28 -> 0.2647585 | GM28: 307 | GN28: =GM28/GI28 -> 0.54919499 | GO28: 2336 | GP28: =GO28/GH28 -> 0.80690846 | GQ28: 1732 | GR28: =GQ28/GO28 -> 0.74143836 | GS28: 592 | GT28: =GS28/GO28 -> 0.25342466
A29: Iowa | B29: 23867 | C29: 6872 | D29: 4889 | E29: 1779 | F29: 475 | G29: =C29/B29 -> 0.28792894 | H29: =D29/B29 -> 0.20484351 | I29: =E29/B29 -> 0.074538065 | J29: =F29/B29 -> 0.019901957 | K29: 2412 | L29: =K29/D29 -> 0.49335242 | M29: 2477 | N29: =M29/D29 -> 0.50664758 | O29: 44 | P29: 10118 | Q29: 4698 | R29: =Q29/P29 -> 0.46432101 | S29: 3451 | T29: =S29/P29 -> 0.34107531 | U29: 2412 | V29: 195 | W29: =V29/U29 -> 0.080845771 | X29: 1649 | Y29: =X29/U29 -> 0.68366501 | Z29: 74 | AA29: =Z29/U29 -> 0.030679934 | AB29: 215 | AC29: =AB29/U29 -> 0.089137645 | AD29: 279 | AE29: =AD29/U29 -> 0.11567164 | AF29: 2477 | AG29: 122 | AH29: =AG29/AF29 -> 0.049253129 | AI29: 1223 | AJ29: =AI29/AF29 -> 0.49374243 | AK29: 35 | AL29: =AK29/AF29 -> 0.014129996 | AM29: 694 | AN29: =AM29/AF29 -> 0.28017763 | AO29: 403 | AP29: =AO29/AF29 -> 0.16269681 | AQ29: =SUM(U29,AF29) -> 4889 | AR29: =SUM(V29,AG29) -> 317 | AS29: =AR29/AQ29 -> 0.064839435 | AT29: =SUM(X29,AI29) -> 2872 | AU29: =AT29/AQ29 -> 0.58744119 | AV29: =SUM(Z29,AK29) -> 109 | AW29: =AV29/AQ29 -> 0.022294948 | AX29: =SUM(AB29,AM29) -> 909 | AY29: =AX29/AQ29 -> 0.18592759 | AZ29: =SUM(AD29,AO29) -> 682 | BA29: =AZ29/AQ29 -> 0.13949683 | BB29: 2383 | BC29: 601 | BD29: =BC29/BB29 -> 0.25220311 | BE29: 2408 | BF29: 623 | BG29: =BF29/BE29 -> 0.25872093 | BH29: =SUM(BB29,BE29) -> 4791 | BI29: =SUM(BC29,BF29) -> 1224 | BJ29: =BI29/BH29 -> 0.25547902 | BK29: 4889 | BL29: 1440 | BM29: =BL29/BK29 -> 0.29453876 | BN29: 2412 | BO29: 537 | BP29: =BO29/BN29 -> 0.22263682 | BQ29: 2477 | BR29: 903 | BS29: =BR29/BQ29 -> 0.3645539 | BT29: 23963 | BU29: 5336 | BV29: =BU29/BT29 -> 0.22267663 | BW29: =BU29/$BU29 -> 1 | BX29: 22468 | BY29: 5214 | BZ29: =BY29/BX29 -> 0.23206338 | CA29: =BY29/$BU29 -> 0.97713643 | CB29: 235 | CC29: 15 | CD29: =CC29/CB29 -> 0.063829787 | CE29: =CC29/$BU29 -> 0.0028110945 | CF29: 57 | CG29: 11 | CH29: =CG29/CF29 -> 0.19298246 | CI29: =CG29/$BU29 -> 0.0020614693 | CJ29: 199 | CK29: 37 | CL29: =CK29/CJ29 -> 0.18592965 | CM29: =CK29/$BU29 -> 0.006934033 | CN29: 11 | CO29: 1 | CP29: =CO29/CN29 -> 0.090909091 | CQ29: =CO29/$BU29 -> 0.0001874063 | CR29: 176 | CS29: 0 | CT29: =CS29/CR29 -> 0 | CU29: =CS29/$BU29 -> 0 | CV29: 378 | CW29: 29 | CX29: =CW29/CV29 -> 0.076719577 | CY29: =CW29/$BU29 -> 0.0054347826 | CZ29: 615 | DA29: 29 | DB29: =DA29/CZ29 -> 0.047154472 | DC29: =DA29/BU29 -> 0.0054347826 | DD29: 2412 | DE29: 130 | DF29: 880 | DG29: 709 | DH29: 693 | DI29: =DE29/DD29 -> 0.053897181 | DJ29: =DF29/DD29 -> 0.36484245 | DK29: =SUM(DG29:DH29)/DD29 -> 0.58126036 | DL29: 2477 | DM29: 148 | DN29: 1058 | DO29: 615 | DP29: 656 | DQ29: =DM29/DL29 -> 0.059749697 | DR29: =DN29/DL29 -> 0.42712959 | DS29: =SUM(DO29:DP29)/DL29 -> 0.51312071 | DT29: =SUM(DL29,DD29) -> 4889 | DU29: =SUM(DM29,DE29) -> 278 | DV29: =SUM(DN29,DF29) -> 1938 | DW29: =SUM(DO29,DG29) -> 1324 | DX29: =SUM(DP29,DH29) -> 1349 | DY29: =DU29/DT29 -> 0.056862344 | DZ29: =DV29/DT29 -> 0.39640008 | EA29: =SUM(DW29:DX29)/DT29 -> 0.54673757 | EB29: 3199 | EC29: 435 | ED29: =EC29/$EB29 -> 0.13597999 | EE29: 665 | EF29: =EE29/$EB29 -> 0.20787746 | EG29: 993 | EH29: =EG29/$EB29 -> 0.3104095 | EI29: 1464 | EJ29: =EI29/$EB29 -> 0.45764301 | EK29: 2033 | EL29: =EK29/$EB29 -> 0.6355111 | EM29: 2450 | EN29: =EM29/$EB29 -> 0.76586433 | EO29: 82182 | EP29: 56932 | EQ29: 93620 | ER29: 99201 | ES29: 57697 | ET29: 2383 | EU29: 270 | EV29: =EU29/ET29 -> 0.11330256 | EW29: 2408 | EX29: 236 | EY29: =EX29/EW29 -> 0.098006645 | EZ29: =SUM(ET29,EW29) -> 4791 | FA29: =SUM(EU29,EX29) -> 506 | FB29: =FA29/EZ29 -> 0.10561469 | FC29: 4791 | FD29: 506 | FE29: =FD29/$FC29 -> 0.10561469 | FF29: 832 | FG29: =FF29/$FC29 -> 0.17365894 | FH29: 1115 | FI29: =FH29/$FC29 -> 0.23272803 | FJ29: 1289 | FK29: =FJ29/$FC29 -> 0.26904613 | FL29: 2002 | FM29: =FL29/$FC29 -> 0.41786683 | FN29: 495 | FO29: 0.31348955 | FP29: 0 | FQ29: 0 | FR29: 88 | FS29: 0.10564226 | FT29: 0 | FU29: 0 | FV29: 439 | FW29: 0.28674069 | FX29: 3 | FY29: 0.0019595036 | FZ29: 49 | GA29: 0.05179704 | GB29: 0 | GC29: 0 | GD29: 1071 | GE29: 0.2190632 | GF29: 3 | GG29: 0.00061362242 | GH29: 3199 | GI29: 512 | GJ29: =GI29/GH29 -> 0.16005002 | GK29: 117 | GL29: =GK29/GI29 -> 0.22851562 | GM29: 316 | GN29: =GM29/GI29 -> 0.6171875 | GO29: 2687 | GP29: =GO29/GH29 -> 0.83994998 | GQ29: 1895 | GR29: =GQ29/GO29 -> 0.70524749 | GS29: 707 | GT29: =GS29/GO29 -> 0.26311872
A30: Iron | B30: 6210 | C30: 2732 | D30: 2051 | E30: 866 | F30: 184 | G30: =C30/B30 -> 0.43993559 | H30: =D30/B30 -> 0.33027375 | I30: =E30/B30 -> 0.1394525 | J30: =F30/B30 -> 0.02962963 | K30: 1039 | L30: =K30/D30 -> 0.50658216 | M30: 1012 | N30: =M30/D30 -> 0.49341784 | O30: 56.1 | P30: 3109 | Q30: 1856 | R30: =Q30/P30 -> 0.59697652 | S30: 1431 | T30: =S30/P30 -> 0.46027662 | U30: 1039 | V30: 61 | W30: =V30/U30 -> 0.058710298 | X30: 735 | Y30: =X30/U30 -> 0.70741097 | Z30: 32 | AA30: =Z30/U30 -> 0.030798845 | AB30: 65 | AC30: =AB30/U30 -> 0.062560154 | AD30: 146 | AE30: =AD30/U30 -> 0.14051973 | AF30: 1012 | AG30: 36 | AH30: =AG30/AF30 -> 0.035573123 | AI30: 549 | AJ30: =AI30/AF30 -> 0.54249012 | AK30: 6 | AL30: =AK30/AF30 -> 0.0059288538 | AM30: 311 | AN30: =AM30/AF30 -> 0.30731225 | AO30: 110 | AP30: =AO30/AF30 -> 0.10869565 | AQ30: =SUM(U30,AF30) -> 2051 | AR30: =SUM(V30,AG30) -> 97 | AS30: =AR30/AQ30 -> 0.047294003 | AT30: =SUM(X30,AI30) -> 1284 | AU30: =AT30/AQ30 -> 0.62603608 | AV30: =SUM(Z30,AK30) -> 38 | AW30: =AV30/AQ30 -> 0.018527548 | AX30: =SUM(AB30,AM30) -> 376 | AY30: =AX30/AQ30 -> 0.18332521 | AZ30: =SUM(AD30,AO30) -> 256 | BA30: =AZ30/AQ30 -> 0.12481716 | BB30: 1016 | BC30: 258 | BD30: =BC30/BB30 -> 0.25393701 | BE30: 961 | BF30: 192 | BG30: =BF30/BE30 -> 0.19979188 | BH30: =SUM(BB30,BE30) -> 1977 | BI30: =SUM(BC30,BF30) -> 450 | BJ30: =BI30/BH30 -> 0.2276176 | BK30: 2051 | BL30: 523 | BM30: =BL30/BK30 -> 0.25499756 | BN30: 1039 | BO30: 242 | BP30: =BO30/BN30 -> 0.23291627 | BQ30: 1012 | BR30: 281 | BS30: =BR30/BQ30 -> 0.27766798 | BT30: 6235 | BU30: 2149 | BV30: =BU30/BT30 -> 0.3446672 | BW30: =BU30/$BU30 -> 1 | BX30: 5871 | BY30: 2104 | BZ30: =BY30/BX30 -> 0.35837166 | CA30: =BY30/$BU30 -> 0.97906003 | CB30: 26 | CC30: 7 | CD30: =CC30/CB30 -> 0.26923077 | CE30: =CC30/$BU30 -> 0.003257329 | CF30: 91 | CG30: 11 | CH30: =CG30/CF30 -> 0.12087912 | CI30: =CG30/$BU30 -> 0.0051186598 | CJ30: 26 | CK30: 3 | CL30: =CK30/CJ30 -> 0.11538462 | CM30: =CK30/$BU30 -> 0.0013959981 | CN30: 0 | CO30: 0 | CP30: 0 | CQ30: =CO30/$BU30 -> 0 | CR30: 24 | CS30: 0 | CT30: =CS30/CR30 -> 0 | CU30: =CS30/$BU30 -> 0 | CV30: 110 | CW30: 18 | CX30: =CW30/CV30 -> 0.16363636 | CY30: =CW30/$BU30 -> 0.0083759888 | CZ30: 111 | DA30: 6 | DB30: =DA30/CZ30 -> 0.054054054 | DC30: =DA30/BU30 -> 0.0027919963 | DD30: 1039 | DE30: 60 | DF30: 335 | DG30: 368 | DH30: 276 | DI30: =DE30/DD30 -> 0.057747834 | DJ30: =DF30/DD30 -> 0.32242541 | DK30: =SUM(DG30:DH30)/DD30 -> 0.61982676 | DL30: 1012 | DM30: 60 | DN30: 383 | DO30: 318 | DP30: 251 | DQ30: =DM30/DL30 -> 0.059288538 | DR30: =DN30/DL30 -> 0.3784585 | DS30: =SUM(DO30:DP30)/DL30 -> 0.56225296 | DT30: =SUM(DL30,DD30) -> 2051 | DU30: =SUM(DM30,DE30) -> 120 | DV30: =SUM(DN30,DF30) -> 718 | DW30: =SUM(DO30,DG30) -> 686 | DX30: =SUM(DP30,DH30) -> 527 | DY30: =DU30/DT30 -> 0.058508045 | DZ30: =DV30/DT30 -> 0.35007314 | EA30: =SUM(DW30:DX30)/DT30 -> 0.59141882 | EB30: 1299 | EC30: 111 | ED30: =EC30/$EB30 -> 0.085450346 | EE30: 266 | EF30: =EE30/$EB30 -> 0.2047729 | EG30: 479 | EH30: =EG30/$EB30 -> 0.36874519 | EI30: 646 | EJ30: =EI30/$EB30 -> 0.49730562 | EK30: 894 | EL30: =EK30/$EB30 -> 0.68822171 | EM30: 1038 | EN30: =EM30/$EB30 -> 0.79907621 | EO30: 60625 | EP30: - | EQ30: 68966 | ER30: 64167 | ES30: 50729 | ET30: 1016 | EU30: 68 | EV30: =EU30/ET30 -> 0.066929134 | EW30: 961 | EX30: 100 | EY30: =EX30/EW30 -> 0.10405827 | EZ30: =SUM(ET30,EW30) -> 1977 | FA30: =SUM(EU30,EX30) -> 168 | FB30: =FA30/EZ30 -> 0.084977238 | FC30: 1977 | FD30: 168 | FE30: =FD30/$FC30 -> 0.084977238 | FF30: 360 | FG30: =FF30/$FC30 -> 0.18209408 | FH30: 477 | FI30: =FH30/$FC30 -> 0.24127466 | FJ30: 610 | FK30: =FJ30/$FC30 -> 0.30854831 | FL30: 927 | FM30: =FL30/$FC30 -> 0.46889226 | FN30: 129 | FO30: 0.2044374 | FP30: 0 | FQ30: 0 | FR30: 19 | FS30: 0.046568627 | FT30: 0 | FU30: 0 | FV30: 118 | FW30: 0.21299639 | FX30: 5 | FY30: 0.0090252708 | FZ30: 34 | GA30: 0.074235808 | GB30: 0 | GC30: 0 | GD30: 300 | GE30: 0.14627011 | GF30: 5 | GG30: 0.0024378352 | GH30: 1299 | GI30: 134 | GJ30: =GI30/GH30 -> 0.10315627 | GK30: 44 | GL30: =GK30/GI30 -> 0.32835821 | GM30: 68 | GN30: =GM30/GI30 -> 0.50746269 | GO30: 1165 | GP30: =GO30/GH30 -> 0.89684373 | GQ30: 934 | GR30: =GQ30/GO30 -> 0.80171674 | GS30: 228 | GT30: =GS30/GO30 -> 0.19570815
A31: Jackson | B31: 20981 | C31: 6017 | D31: 4292 | E31: 1752 | F31: 457 | G31: =C31/B31 -> 0.28678328 | H31: =D31/B31 -> 0.20456604 | I31: =E31/B31 -> 0.083504123 | J31: =F31/B31 -> 0.021781612 | K31: 2154 | L31: =K31/D31 -> 0.50186393 | M31: 2138 | N31: =M31/D31 -> 0.49813607 | O31: 43.4 | P31: 8274 | Q31: 4100 | R31: =Q31/P31 -> 0.49552816 | S31: 3075 | T31: =S31/P31 -> 0.37164612 | U31: 2154 | V31: 109 | W31: =V31/U31 -> 0.050603528 | X31: 1447 | Y31: =X31/U31 -> 0.67177344 | Z31: 26 | AA31: =Z31/U31 -> 0.012070566 | AB31: 211 | AC31: =AB31/U31 -> 0.097957289 | AD31: 361 | AE31: =AD31/U31 -> 0.16759517 | AF31: 2138 | AG31: 40 | AH31: =AG31/AF31 -> 0.018709074 | AI31: 1050 | AJ31: =AI31/AF31 -> 0.49111319 | AK31: 49 | AL31: =AK31/AF31 -> 0.022918616 | AM31: 682 | AN31: =AM31/AF31 -> 0.31898971 | AO31: 317 | AP31: =AO31/AF31 -> 0.14826941 | AQ31: =SUM(U31,AF31) -> 4292 | AR31: =SUM(V31,AG31) -> 149 | AS31: =AR31/AQ31 -> 0.03471575 | AT31: =SUM(X31,AI31) -> 2497 | AU31: =AT31/AQ31 -> 0.58178006 | AV31: =SUM(Z31,AK31) -> 75 | AW31: =AV31/AQ31 -> 0.017474371 | AX31: =SUM(AB31,AM31) -> 893 | AY31: =AX31/AQ31 -> 0.20806151 | AZ31: =SUM(AD31,AO31) -> 678 | BA31: =AZ31/AQ31 -> 0.15796831 | BB31: 2086 | BC31: 630 | BD31: =BC31/BB31 -> 0.30201342 | BE31: 2091 | BF31: 567 | BG31: =BF31/BE31 -> 0.27116212 | BH31: =SUM(BB31,BE31) -> 4177 | BI31: =SUM(BC31,BF31) -> 1197 | BJ31: =BI31/BH31 -> 0.28656931 | BK31: 4292 | BL31: 1238 | BM31: =BL31/BK31 -> 0.28844362 | BN31: 2154 | BO31: 481 | BP31: =BO31/BN31 -> 0.22330548 | BQ31: 2138 | BR31: 757 | BS31: =BR31/BQ31 -> 0.35406922 | BT31: 21027 | BU31: 4560 | BV31: =BU31/BT31 -> 0.21686403 | BW31: =BU31/$BU31 -> 1 | BX31: 18010 | BY31: 4290 | BZ31: =BY31/BX31 -> 0.238201 | CA31: =BY31/$BU31 -> 0.94078947 | CB31: 508 | CC31: 18 | CD31: =CC31/CB31 -> 0.035433071 | CE31: =CC31/$BU31 -> 0.0039473684 | CF31: 1130 | CG31: 162 | CH31: =CG31/CF31 -> 0.14336283 | CI31: =CG31/$BU31 -> 0.035526316 | CJ31: 120 | CK31: 13 | CL31: =CK31/CJ31 -> 0.10833333 | CM31: =CK31/$BU31 -> 0.0028508772 | CN31: 22 | CO31: 2 | CP31: =CO31/CN31 -> 0.090909091 | CQ31: =CO31/$BU31 -> 0.00043859649 | CR31: 138 | CS31: 2 | CT31: =CS31/CR31 -> 0.014492754 | CU31: =CS31/$BU31 -> 0.00043859649 | CV31: 362 | CW31: 20 | CX31: =CW31/CV31 -> 0.055248619 | CY31: =CW31/$BU31 -> 0.0043859649 | CZ31: 875 | DA31: 55 | DB31: =DA31/CZ31 -> 0.062857143 | DC31: =DA31/BU31 -> 0.012061404 | DD31: 2154 | DE31: 163 | DF31: 1039 | DG31: 600 | DH31: 352 | DI31: =DE31/DD31 -> 0.075673166 | DJ31: =DF31/DD31 -> 0.4823584 | DK31: =SUM(DG31:DH31)/DD31 -> 0.44196843 | DL31: 2138 | DM31: 156 | DN31: 958 | DO31: 669 | DP31: 355 | DQ31: =DM31/DL31 -> 0.072965388 | DR31: =DN31/DL31 -> 0.44808232 | DS31: =SUM(DO31:DP31)/DL31 -> 0.47895229 | DT31: =SUM(DL31,DD31) -> 4292 | DU31: =SUM(DM31,DE31) -> 319 | DV31: =SUM(DN31,DF31) -> 1997 | DW31: =SUM(DO31,DG31) -> 1269 | DX31: =SUM(DP31,DH31) -> 707 | DY31: =DU31/DT31 -> 0.074324324 | DZ31: =DV31/DT31 -> 0.46528425 | EA31: =SUM(DW31:DX31)/DT31 -> 0.46039143 | EB31: 2741 | EC31: 335 | ED31: =EC31/$EB31 -> 0.12221817 | EE31: 702 | EF31: =EE31/$EB31 -> 0.25611091 | EG31: 977 | EH31: =EG31/$EB31 -> 0.35643926 | EI31: 1370 | EJ31: =EI31/$EB31 -> 0.49981758 | EK31: 1975 | EL31: =EK31/$EB31 -> 0.72053995 | EM31: 2333 | EN31: =EM31/$EB31 -> 0.85114922 | EO31: 68110 | EP31: 51625 | EQ31: 75192 | ER31: 80645 | ES31: 50032 | ET31: 2086 | EU31: 169 | EV31: =EU31/ET31 -> 0.081016299 | EW31: 2091 | EX31: 315 | EY31: =EX31/EW31 -> 0.15064562 | EZ31: =SUM(ET31,EW31) -> 4177 | FA31: =SUM(EU31,EX31) -> 484 | FB31: =FA31/EZ31 -> 0.11587264 | FC31: 4177 | FD31: 484 | FE31: =FD31/$FC31 -> 0.11587264 | FF31: 863 | FG31: =FF31/$FC31 -> 0.20660761 | FH31: 1161 | FI31: =FH31/$FC31 -> 0.27795068 | FJ31: 1305 | FK31: =FJ31/$FC31 -> 0.31242519 | FL31: 2116 | FM31: =FL31/$FC31 -> 0.50658367 | FN31: 251 | FO31: 0.18703428 | FP31: 0 | FQ31: 0 | FR31: 102 | FS31: 0.12561576 | FT31: 0 | FU31: 0 | FV31: 226 | FW31: 0.18864775 | FX31: 0 | FY31: 0 | FZ31: 18 | GA31: 0.019148936 | GB31: 0 | GC31: 0 | GD31: 597 | GE31: 0.13909599 | GF31: 0 | GG31: 0 | GH31: 2741 | GI31: 407 | GJ31: =GI31/GH31 -> 0.14848595 | GK31: 140 | GL31: =GK31/GI31 -> 0.34398034 | GM31: 193 | GN31: =GM31/GI31 -> 0.47420147 | GO31: 2334 | GP31: =GO31/GH31 -> 0.85151405 | GQ31: 1524 | GR31: =GQ31/GO31 -> 0.6529563 | GS31: 806 | GT31: =GS31/GO31 -> 0.34532991
A32: Jefferson | B32: 86003 | C32: 22390 | D32: 15933 | E32: 6237 | F32: 1250 | G32: =C32/B32 -> 0.26033976 | H32: =D32/B32 -> 0.18526098 | I32: =E32/B32 -> 0.072520726 | J32: =F32/B32 -> 0.014534377 | K32: 7515 | L32: =K32/D32 -> 0.47166259 | M32: 8418 | N32: =M32/D32 -> 0.52833741 | O32: 41.5 | P32: 34873 | Q32: 15624 | R32: =Q32/P32 -> 0.44802569 | S32: 11386 | T32: =S32/P32 -> 0.32649901 | U32: 7515 | V32: 476 | W32: =V32/U32 -> 0.063339987 | X32: 5149 | Y32: =X32/U32 -> 0.68516301 | Z32: 263 | AA32: =Z32/U32 -> 0.034996673 | AB32: 776 | AC32: =AB32/U32 -> 0.10326015 | AD32: 851 | AE32: =AD32/U32 -> 0.11324019 | AF32: 8418 | AG32: 356 | AH32: =AG32/AF32 -> 0.04229033 | AI32: 4388 | AJ32: =AI32/AF32 -> 0.52126396 | AK32: 67 | AL32: =AK32/AF32 -> 0.0079591352 | AM32: 2328 | AN32: =AM32/AF32 -> 0.27655025 | AO32: 1279 | AP32: =AO32/AF32 -> 0.15193633 | AQ32: =SUM(U32,AF32) -> 15933 | AR32: =SUM(V32,AG32) -> 832 | AS32: =AR32/AQ32 -> 0.052218666 | AT32: =SUM(X32,AI32) -> 9537 | AU32: =AT32/AQ32 -> 0.59856901 | AV32: =SUM(Z32,AK32) -> 330 | AW32: =AV32/AQ32 -> 0.02071173 | AX32: =SUM(AB32,AM32) -> 3104 | AY32: =AX32/AQ32 -> 0.19481579 | AZ32: =SUM(AD32,AO32) -> 2130 | BA32: =AZ32/AQ32 -> 0.13368481 | BB32: 7427 | BC32: 2142 | BD32: =BC32/BB32 -> 0.28840716 | BE32: 8344 | BF32: 2062 | BG32: =BF32/BE32 -> 0.24712368 | BH32: =SUM(BB32,BE32) -> 15771 | BI32: =SUM(BC32,BF32) -> 4204 | BJ32: =BI32/BH32 -> 0.26656521 | BK32: 15933 | BL32: 4698 | BM32: =BL32/BK32 -> 0.29485973 | BN32: 7515 | BO32: 1663 | BP32: =BO32/BN32 -> 0.22129075 | BQ32: 8418 | BR32: 3035 | BS32: =BR32/BQ32 -> 0.36053694 | BT32: 86245 | BU32: 17061 | BV32: =BU32/BT32 -> 0.19782016 | BW32: =BU32/$BU32 -> 1 | BX32: 75373 | BY32: 16410 | BZ32: =BY32/BX32 -> 0.21771722 | CA32: =BY32/$BU32 -> 0.9618428 | CB32: 943 | CC32: 46 | CD32: =CC32/CB32 -> 0.048780488 | CE32: =CC32/$BU32 -> 0.0026962077 | CF32: 270 | CG32: 51 | CH32: =CG32/CF32 -> 0.18888889 | CI32: =CG32/$BU32 -> 0.0029892738 | CJ32: 862 | CK32: 69 | CL32: =CK32/CJ32 -> 0.080046404 | CM32: =CK32/$BU32 -> 0.0040443116 | CN32: 24 | CO32: 4 | CP32: =CO32/CN32 -> 0.16666667 | CQ32: =CO32/$BU32 -> 0.00023445285 | CR32: 1591 | CS32: 0 | CT32: =CS32/CR32 -> 0 | CU32: =CS32/$BU32 -> 0 | CV32: 1216 | CW32: 71 | CX32: =CW32/CV32 -> 0.058388158 | CY32: =CW32/$BU32 -> 0.004161538 | CZ32: 7557 | DA32: 410 | DB32: =DA32/CZ32 -> 0.054254334 | DC32: =DA32/BU32 -> 0.024031417 | DD32: 7515 | DE32: 462 | DF32: 3207 | DG32: 2010 | DH32: 1836 | DI32: =DE32/DD32 -> 0.061477046 | DJ32: =DF32/DD32 -> 0.42674651 | DK32: =SUM(DG32:DH32)/DD32 -> 0.51177645 | DL32: 8418 | DM32: 507 | DN32: 3458 | DO32: 2211 | DP32: 2242 | DQ32: =DM32/DL32 -> 0.060228083 | DR32: =DN32/DL32 -> 0.41078641 | DS32: =SUM(DO32:DP32)/DL32 -> 0.52898551 | DT32: =SUM(DL32,DD32) -> 15933 | DU32: =SUM(DM32,DE32) -> 969 | DV32: =SUM(DN32,DF32) -> 6665 | DW32: =SUM(DO32,DG32) -> 4221 | DX32: =SUM(DP32,DH32) -> 4078 | DY32: =DU32/DT32 -> 0.060817172 | DZ32: =DV32/DT32 -> 0.41831419 | EA32: =SUM(DW32:DX32)/DT32 -> 0.52086864 | EB32: 10375 | EC32: 857 | ED32: =EC32/$EB32 -> 0.08260241 | EE32: 1738 | EF32: =EE32/$EB32 -> 0.16751807 | EG32: 2786 | EH32: =EG32/$EB32 -> 0.26853012 | EI32: 4111 | EJ32: =EI32/$EB32 -> 0.39624096 | EK32: 6416 | EL32: =EK32/$EB32 -> 0.61840964 | EM32: 7845 | EN32: =EM32/$EB32 -> 0.75614458 | EO32: 83750 | EP32: 37316 | EQ32: 99022 | ER32: 97855 | ES32: 59050 | ET32: 7427 | EU32: 517 | EV32: =EU32/ET32 -> 0.069610879 | EW32: 8344 | EX32: 772 | EY32: =EX32/EW32 -> 0.092521572 | EZ32: =SUM(ET32,EW32) -> 15771 | FA32: =SUM(EU32,EX32) -> 1289 | FB32: =FA32/EZ32 -> 0.081732293 | FC32: 15771 | FD32: 1289 | FE32: =FD32/$FC32 -> 0.081732293 | FF32: 2132 | FG32: =FF32/$FC32 -> 0.13518483 | FH32: 2845 | FI32: =FH32/$FC32 -> 0.18039439 | FJ32: 3337 | FK32: =FJ32/$FC32 -> 0.21159089 | FL32: 6283 | FM32: =FL32/$FC32 -> 0.39838945 | FN32: 1532 | FO32: 0.32010029 | FP32: 39 | FQ32: 0.0081487672 | FR32: 344 | FS32: 0.1260535 | FT32: 0 | FU32: 0 | FV32: 1017 | FW32: 0.20712831 | FX32: 9 | FY32: 0.0018329939 | FZ32: 214 | GA32: 0.061003421 | GB32: 2 | GC32: 0.00057012543 | GD32: 3107 | GE32: 0.19500408 | GF32: 50 | GG32: 0.003138141 | GH32: 10375 | GI32: 1793 | GJ32: =GI32/GH32 -> 0.17281928 | GK32: 522 | GL32: =GK32/GI32 -> 0.29113218 | GM32: 998 | GN32: =GM32/GI32 -> 0.55660904 | GO32: 8582 | GP32: =GO32/GH32 -> 0.82718072 | GQ32: 6647 | GR32: =GQ32/GO32 -> 0.77452808 | GS32: 1898 | GT32: =GS32/GO32 -> 0.22116057
A33: Juneau | B33: 26689 | C33: 8295 | D33: 5822 | E33: 2275 | F33: 628 | G33: =C33/B33 -> 0.3108022 | H33: =D33/B33 -> 0.21814231 | I33: =E33/B33 -> 0.085241111 | J33: =F33/B33 -> 0.023530293 | K33: 2871 | L33: =K33/D33 -> 0.49312951 | M33: 2951 | N33: =M33/D33 -> 0.50687049 | O33: 45.8 | P33: 10955 | Q33: 5447 | R33: =Q33/P33 -> 0.49721588 | S33: 4142 | T33: =S33/P33 -> 0.3780922 | U33: 2871 | V33: 172 | W33: =V33/U33 -> 0.059909439 | X33: 1747 | Y33: =X33/U33 -> 0.60849878 | Z33: 110 | AA33: =Z33/U33 -> 0.038314176 | AB33: 380 | AC33: =AB33/U33 -> 0.13235806 | AD33: 462 | AE33: =AD33/U33 -> 0.16091954 | AF33: 2951 | AG33: 137 | AH33: =AG33/AF33 -> 0.046424941 | AI33: 1517 | AJ33: =AI33/AF33 -> 0.51406303 | AK33: 81 | AL33: =AK33/AF33 -> 0.027448323 | AM33: 842 | AN33: =AM33/AF33 -> 0.28532701 | AO33: 374 | AP33: =AO33/AF33 -> 0.1267367 | AQ33: =SUM(U33,AF33) -> 5822 | AR33: =SUM(V33,AG33) -> 309 | AS33: =AR33/AQ33 -> 0.053074545 | AT33: =SUM(X33,AI33) -> 3264 | AU33: =AT33/AQ33 -> 0.56063209 | AV33: =SUM(Z33,AK33) -> 191 | AW33: =AV33/AQ33 -> 0.032806596 | AX33: =SUM(AB33,AM33) -> 1222 | AY33: =AX33/AQ33 -> 0.20989351 | AZ33: =SUM(AD33,AO33) -> 836 | BA33: =AZ33/AQ33 -> 0.14359327 | BB33: 2803 | BC33: 911 | BD33: =BC33/BB33 -> 0.32500892 | BE33: 2841 | BF33: 882 | BG33: =BF33/BE33 -> 0.31045407 | BH33: =SUM(BB33,BE33) -> 5644 | BI33: =SUM(BC33,BF33) -> 1793 | BJ33: =BI33/BH33 -> 0.31768249 | BK33: 5822 | BL33: 1634 | BM33: =BL33/BK33 -> 0.28065957 | BN33: 2871 | BO33: 697 | BP33: =BO33/BN33 -> 0.24277255 | BQ33: 2951 | BR33: 937 | BS33: =BR33/BQ33 -> 0.31751948 | BT33: 26590 | BU33: 6136 | BV33: =BU33/BT33 -> 0.23076344 | BW33: =BU33/$BU33 -> 1 | BX33: 24163 | BY33: 5910 | BZ33: =BY33/BX33 -> 0.24458883 | CA33: =BY33/$BU33 -> 0.96316819 | CB33: 721 | CC33: 21 | CD33: =CC33/CB33 -> 0.029126214 | CE33: =CC33/$BU33 -> 0.003422425 | CF33: 326 | CG33: 55 | CH33: =CG33/CF33 -> 0.16871166 | CI33: =CG33/$BU33 -> 0.0089634941 | CJ33: 174 | CK33: 22 | CL33: =CK33/CJ33 -> 0.12643678 | CM33: =CK33/$BU33 -> 0.0035853977 | CN33: 6 | CO33: 2 | CP33: =CO33/CN33 -> 0.33333333 | CQ33: =CO33/$BU33 -> 0.00032594524 | CR33: 114 | CS33: 7 | CT33: =CS33/CR33 -> 0.061403509 | CU33: =CS33/$BU33 -> 0.0011408083 | CV33: 340 | CW33: 48 | CX33: =CW33/CV33 -> 0.14117647 | CY33: =CW33/$BU33 -> 0.0078226858 | CZ33: 860 | DA33: 78 | DB33: =DA33/CZ33 -> 0.090697674 | DC33: =DA33/BU33 -> 0.012711864 | DD33: 2871 | DE33: 362 | DF33: 1197 | DG33: 807 | DH33: 505 | DI33: =DE33/DD33 -> 0.12608847 | DJ33: =DF33/DD33 -> 0.4169279 | DK33: =SUM(DG33:DH33)/DD33 -> 0.45698363 | DL33: 2951 | DM33: 209 | DN33: 1357 | DO33: 866 | DP33: 519 | DQ33: =DM33/DL33 -> 0.07082345 | DR33: =DN33/DL33 -> 0.45984412 | DS33: =SUM(DO33:DP33)/DL33 -> 0.46933243 | DT33: =SUM(DL33,DD33) -> 5822 | DU33: =SUM(DM33,DE33) -> 571 | DV33: =SUM(DN33,DF33) -> 2554 | DW33: =SUM(DO33,DG33) -> 1673 | DX33: =SUM(DP33,DH33) -> 1024 | DY33: =DU33/DT33 -> 0.098076262 | DZ33: =DV33/DT33 -> 0.43868087 | EA33: =SUM(DW33:DX33)/DT33 -> 0.46324287 | EB33: 3737 | EC33: 423 | ED33: =EC33/$EB33 -> 0.1131924 | EE33: 821 | EF33: =EE33/$EB33 -> 0.21969494 | EG33: 1407 | EH33: =EG33/$EB33 -> 0.37650522 | EI33: 1976 | EJ33: =EI33/$EB33 -> 0.52876639 | EK33: 2675 | EL33: =EK33/$EB33 -> 0.71581482 | EM33: 3113 | EN33: =EM33/$EB33 -> 0.83302114 | EO33: 67270 | EP33: 61375 | EQ33: 84067 | ER33: 77512 | ES33: 45516 | ET33: 2803 | EU33: 349 | EV33: =EU33/ET33 -> 0.12450945 | EW33: 2841 | EX33: 312 | EY33: =EX33/EW33 -> 0.10982049 | EZ33: =SUM(ET33,EW33) -> 5644 | FA33: =SUM(EU33,EX33) -> 661 | FB33: =FA33/EZ33 -> 0.11711552 | FC33: 5644 | FD33: 661 | FE33: =FD33/$FC33 -> 0.11711552 | FF33: 1134 | FG33: =FF33/$FC33 -> 0.20092133 | FH33: 1614 | FI33: =FH33/$FC33 -> 0.2859674 | FJ33: 1831 | FK33: =FJ33/$FC33 -> 0.32441531 | FL33: 3007 | FM33: =FL33/$FC33 -> 0.53277817 | FN33: 447 | FO33: 0.24520022 | FP33: 45 | FQ33: 0.024684586 | FR33: 109 | FS33: 0.10400763 | FT33: 2 | FU33: 0.0019083969 | FV33: 478 | FW33: 0.27726218 | FX33: 3 | FY33: 0.0017401392 | FZ33: 44 | GA33: 0.035859821 | GB33: 1 | GC33: 0.00081499593 | GD33: 1078 | GE33: 0.18515974 | GF33: 51 | GG33: 0.0087598763 | GH33: 3737 | GI33: 606 | GJ33: =GI33/GH33 -> 0.16216216 | GK33: 283 | GL33: =GK33/GI33 -> 0.4669967 | GM33: 227 | GN33: =GM33/GI33 -> 0.37458746 | GO33: 3131 | GP33: =GO33/GH33 -> 0.83783784 | GQ33: 2304 | GR33: =GQ33/GO33 -> 0.73586714 | GS33: 801 | GT33: =GS33/GO33 -> 0.25582881
A34: Kenosha | B34: 168438 | C34: 38793 | D34: 26664 | E34: 10145 | F34: 2511 | G34: =C34/B34 -> 0.23031026 | H34: =D34/B34 -> 0.15830157 | I34: =E34/B34 -> 0.060229877 | J34: =F34/B34 -> 0.014907562 | K34: 12162 | L34: =K34/D34 -> 0.45612061 | M34: 14502 | N34: =M34/D34 -> 0.54387939 | O34: 39.4 | P34: 68904 | Q34: 27119 | R34: =Q34/P34 -> 0.39357657 | S34: 19820 | T34: =S34/P34 -> 0.28764658 | U34: 12162 | V34: 1089 | W34: =V34/U34 -> 0.089541194 | X34: 7871 | Y34: =X34/U34 -> 0.64717974 | Z34: 227 | AA34: =Z34/U34 -> 0.018664693 | AB34: 1369 | AC34: =AB34/U34 -> 0.11256372 | AD34: 1606 | AE34: =AD34/U34 -> 0.13205065 | AF34: 14502 | AG34: 611 | AH34: =AG34/AF34 -> 0.04213212 | AI34: 7092 | AJ34: =AI34/AF34 -> 0.489036 | AK34: 379 | AL34: =AK34/AF34 -> 0.026134326 | AM34: 4004 | AN34: =AM34/AF34 -> 0.27609985 | AO34: 2416 | AP34: =AO34/AF34 -> 0.16659771 | AQ34: =SUM(U34,AF34) -> 26664 | AR34: =SUM(V34,AG34) -> 1700 | AS34: =AR34/AQ34 -> 0.063756376 | AT34: =SUM(X34,AI34) -> 14963 | AU34: =AT34/AQ34 -> 0.56116862 | AV34: =SUM(Z34,AK34) -> 606 | AW34: =AV34/AQ34 -> 0.022727273 | AX34: =SUM(AB34,AM34) -> 5373 | AY34: =AX34/AQ34 -> 0.20150765 | AZ34: =SUM(AD34,AO34) -> 4022 | BA34: =AZ34/AQ34 -> 0.15084008 | BB34: 11908 | BC34: 4042 | BD34: =BC34/BB34 -> 0.33943567 | BE34: 14179 | BF34: 4873 | BG34: =BF34/BE34 -> 0.34367727 | BH34: =SUM(BB34,BE34) -> 26087 | BI34: =SUM(BC34,BF34) -> 8915 | BJ34: =BI34/BH34 -> 0.3417411 | BK34: 26664 | BL34: 7602 | BM34: =BL34/BK34 -> 0.28510351 | BN34: 12162 | BO34: 2625 | BP34: =BO34/BN34 -> 0.21583621 | BQ34: 14502 | BR34: 4977 | BS34: =BR34/BQ34 -> 0.34319404 | BT34: 168754 | BU34: 28821 | BV34: =BU34/BT34 -> 0.17078706 | BW34: =BU34/$BU34 -> 1 | BX34: 121698 | BY34: 25603 | BZ34: =BY34/BX34 -> 0.21038144 | CA34: =BY34/$BU34 -> 0.8883453 | CB34: 11934 | CC34: 989 | CD34: =CC34/CB34 -> 0.082872465 | CE34: =CC34/$BU34 -> 0.034315256 | CF34: 504 | CG34: 109 | CH34: =CG34/CF34 -> 0.21626984 | CI34: =CG34/$BU34 -> 0.0037819645 | CJ34: 3539 | CK34: 432 | CL34: =CK34/CJ34 -> 0.12206838 | CM34: =CK34/$BU34 -> 0.01498907 | CN34: 98 | CO34: 20 | CP34: =CO34/CN34 -> 0.20408163 | CQ34: =CO34/$BU34 -> 0.00069393845 | CR34: 2256 | CS34: 91 | CT34: =CS34/CR34 -> 0.040336879 | CU34: =CS34/$BU34 -> 0.0031574199 | CV34: 4270 | CW34: 202 | CX34: =CW34/CV34 -> 0.047306792 | CY34: =CW34/$BU34 -> 0.0070087783 | CZ34: 26711 | DA34: 1466 | DB34: =DA34/CZ34 -> 0.054883756 | DC34: =DA34/BU34 -> 0.050865688 | DD34: 12162 | DE34: 1115 | DF34: 3896 | DG34: 4023 | DH34: 3128 | DI34: =DE34/DD34 -> 0.091679 | DJ34: =DF34/DD34 -> 0.32034205 | DK34: =SUM(DG34:DH34)/DD34 -> 0.58797895 | DL34: 14502 | DM34: 1434 | DN34: 4912 | DO34: 5034 | DP34: 3122 | DQ34: =DM34/DL34 -> 0.098882913 | DR34: =DN34/DL34 -> 0.3387119 | DS34: =SUM(DO34:DP34)/DL34 -> 0.56240519 | DT34: =SUM(DL34,DD34) -> 26664 | DU34: =SUM(DM34,DE34) -> 2549 | DV34: =SUM(DN34,DF34) -> 8808 | DW34: =SUM(DO34,DG34) -> 9057 | DX34: =SUM(DP34,DH34) -> 6250 | DY34: =DU34/DT34 -> 0.09559706 | DZ34: =DV34/DT34 -> 0.33033303 | EA34: =SUM(DW34:DX34)/DT34 -> 0.57406991 | EB34: 17498 | EC34: 1544 | ED34: =EC34/$EB34 -> 0.088238656 | EE34: 3170 | EF34: =EE34/$EB34 -> 0.18116356 | EG34: 5005 | EH34: =EG34/$EB34 -> 0.28603269 | EI34: 7119 | EJ34: =EI34/$EB34 -> 0.4068465 | EK34: 10275 | EL34: =EK34/$EB34 -> 0.58720997 | EM34: 12806 | EN34: =EM34/$EB34 -> 0.73185507 | EO34: 81239 | EP34: 41306 | EQ34: 84757 | ER34: 99729 | ES34: 60926 | ET34: 11908 | EU34: 907 | EV34: =EU34/ET34 -> 0.076167282 | EW34: 14179 | EX34: 1543 | EY34: =EX34/EW34 -> 0.10882291 | EZ34: =SUM(ET34,EW34) -> 26087 | FA34: =SUM(EU34,EX34) -> 2450 | FB34: =FA34/EZ34 -> 0.09391651 | FC34: 26087 | FD34: 2450 | FE34: =FD34/$FC34 -> 0.09391651 | FF34: 4026 | FG34: =FF34/$FC34 -> 0.15432974 | FH34: 5446 | FI34: =FH34/$FC34 -> 0.20876299 | FJ34: 6078 | FK34: =FJ34/$FC34 -> 0.23298961 | FL34: 10023 | FM34: =FL34/$FC34 -> 0.38421436 | FN34: 2365 | FO34: 0.29662611 | FP34: 59 | FQ34: 0.0073999749 | FR34: 337 | FS34: 0.080448794 | FT34: 7 | FU34: 0.0016710432 | FV34: 2151 | FW34: 0.2516967 | FX34: 48 | FY34: 0.0056166628 | FZ34: 186 | GA34: 0.031229013 | GB34: 9 | GC34: 0.0015110813 | GD34: 5039 | GE34: 0.1889814 | GF34: 123 | GG34: 0.0046129613 | GH34: 17498 | GI34: 3834 | GJ34: =GI34/GH34 -> 0.21911076 | GK34: 1288 | GL34: =GK34/GI34 -> 0.33594158 | GM34: 2198 | GN34: =GM34/GI34 -> 0.5732916 | GO34: 13664 | GP34: =GO34/GH34 -> 0.78088924 | GQ34: 10381 | GR34: =GQ34/GO34 -> 0.75973361 | GS34: 3206 | GT34: =GS34/GO34 -> 0.23463115
A35: Kewaunee | B35: 20664 | C35: 6250 | D35: 4582 | E35: 1933 | F35: 485 | G35: =C35/B35 -> 0.30245838 | H35: =D35/B35 -> 0.22173829 | I35: =E35/B35 -> 0.093544328 | J35: =F35/B35 -> 0.02347077 | K35: 2209 | L35: =K35/D35 -> 0.48210388 | M35: 2373 | N35: =M35/D35 -> 0.51789612 | O35: 44.6 | P35: 8357 | Q35: 4166 | R35: =Q35/P35 -> 0.49850425 | S35: 3180 | T35: =S35/P35 -> 0.38051933 | U35: 2209 | V35: 123 | W35: =V35/U35 -> 0.055681304 | X35: 1617 | Y35: =X35/U35 -> 0.73200543 | Z35: 30 | AA35: =Z35/U35 -> 0.013580806 | AB35: 207 | AC35: =AB35/U35 -> 0.09370756 | AD35: 232 | AE35: =AD35/U35 -> 0.1050249 | AF35: 2373 | AG35: 39 | AH35: =AG35/AF35 -> 0.016434893 | AI35: 1241 | AJ35: =AI35/AF35 -> 0.52296671 | AK35: 52 | AL35: =AK35/AF35 -> 0.02191319 | AM35: 744 | AN35: =AM35/AF35 -> 0.31352718 | AO35: 297 | AP35: =AO35/AF35 -> 0.12515803 | AQ35: =SUM(U35,AF35) -> 4582 | AR35: =SUM(V35,AG35) -> 162 | AS35: =AR35/AQ35 -> 0.03535574 | AT35: =SUM(X35,AI35) -> 2858 | AU35: =AT35/AQ35 -> 0.62374509 | AV35: =SUM(Z35,AK35) -> 82 | AW35: =AV35/AQ35 -> 0.017896115 | AX35: =SUM(AB35,AM35) -> 951 | AY35: =AX35/AQ35 -> 0.20755129 | AZ35: =SUM(AD35,AO35) -> 529 | BA35: =AZ35/AQ35 -> 0.11545177 | BB35: 2181 | BC35: 496 | BD35: =BC35/BB35 -> 0.22741862 | BE35: 2325 | BF35: 540 | BG35: =BF35/BE35 -> 0.23225806 | BH35: =SUM(BB35,BE35) -> 4506 | BI35: =SUM(BC35,BF35) -> 1036 | BJ35: =BI35/BH35 -> 0.22991567 | BK35: 4582 | BL35: 1240 | BM35: =BL35/BK35 -> 0.27062418 | BN35: 2209 | BO35: 397 | BP35: =BO35/BN35 -> 0.17971933 | BQ35: 2373 | BR35: 843 | BS35: =BR35/BQ35 -> 0.35524652 | BT35: 20751 | BU35: 4868 | BV35: =BU35/BT35 -> 0.2345911 | BW35: =BU35/$BU35 -> 1 | BX35: 19193 | BY35: 4761 | BZ35: =BY35/BX35 -> 0.24805919 | CA35: =BY35/$BU35 -> 0.97801972 | CB35: 118 | CC35: 15 | CD35: =CC35/CB35 -> 0.12711864 | CE35: =CC35/$BU35 -> 0.0030813476 | CF35: 147 | CG35: 13 | CH35: =CG35/CF35 -> 0.088435374 | CI35: =CG35/$BU35 -> 0.0026705012 | CJ35: 133 | CK35: 19 | CL35: =CK35/CJ35 -> 0.14285714 | CM35: =CK35/$BU35 -> 0.0039030403 | CN35: 9 | CO35: 3 | CP35: =CO35/CN35 -> 0.33333333 | CQ35: =CO35/$BU35 -> 0.00061626952 | CR35: 118 | CS35: 0 | CT35: =CS35/CR35 -> 0 | CU35: =CS35/$BU35 -> 0 | CV35: 268 | CW35: 17 | CX35: =CW35/CV35 -> 0.063432836 | CY35: =CW35/$BU35 -> 0.0034921939 | CZ35: 883 | DA35: 40 | DB35: =DA35/CZ35 -> 0.045300113 | DC35: =DA35/BU35 -> 0.0082169269 | DD35: 2209 | DE35: 166 | DF35: 1078 | DG35: 581 | DH35: 384 | DI35: =DE35/DD35 -> 0.075147125 | DJ35: =DF35/DD35 -> 0.48800362 | DK35: =SUM(DG35:DH35)/DD35 -> 0.43684925 | DL35: 2373 | DM35: 203 | DN35: 1068 | DO35: 521 | DP35: 581 | DQ35: =DM35/DL35 -> 0.085545723 | DR35: =DN35/DL35 -> 0.45006321 | DS35: =SUM(DO35:DP35)/DL35 -> 0.46439107 | DT35: =SUM(DL35,DD35) -> 4582 | DU35: =SUM(DM35,DE35) -> 369 | DV35: =SUM(DN35,DF35) -> 2146 | DW35: =SUM(DO35,DG35) -> 1102 | DX35: =SUM(DP35,DH35) -> 965 | DY35: =DU35/DT35 -> 0.080532519 | DZ35: =DV35/DT35 -> 0.46835443 | EA35: =SUM(DW35:DX35)/DT35 -> 0.45111305 | EB35: 2893 | EC35: 300 | ED35: =EC35/$EB35 -> 0.10369858 | EE35: 511 | EF35: =EE35/$EB35 -> 0.17663325 | EG35: 764 | EH35: =EG35/$EB35 -> 0.26408572 | EI35: 1213 | EJ35: =EI35/$EB35 -> 0.41928794 | EK35: 1909 | EL35: =EK35/$EB35 -> 0.65986865 | EM35: 2251 | EN35: =EM35/$EB35 -> 0.77808503 | EO35: 82725 | EP35: 78295 | EQ35: 101205 | ER35: 96295 | ES35: 57052 | ET35: 2181 | EU35: 143 | EV35: =EU35/ET35 -> 0.065566254 | EW35: 2325 | EX35: 261 | EY35: =EX35/EW35 -> 0.11225806 | EZ35: =SUM(ET35,EW35) -> 4506 | FA35: =SUM(EU35,EX35) -> 404 | FB35: =FA35/EZ35 -> 0.089658233 | FC35: 4506 | FD35: 404 | FE35: =FD35/$FC35 -> 0.089658233 | FF35: 696 | FG35: =FF35/$FC35 -> 0.15446072 | FH35: 878 | FI35: =FH35/$FC35 -> 0.19485131 | FJ35: 946 | FK35: =FJ35/$FC35 -> 0.2099423 | FL35: 1794 | FM35: =FL35/$FC35 -> 0.39813582 | FN35: 385 | FO35: 0.28122717 | FP35: 5 | FQ35: 0.0036523009 | FR35: 75 | FS35: 0.089285714 | FT35: 0 | FU35: 0 | FV35: 278 | FW35: 0.2171875 | FX35: 2 | FY35: 0.0015625 | FZ35: 50 | GA35: 0.045745654 | GB35: 0 | GC35: 0 | GD35: 788 | GE35: 0.1719773 | GF35: 7 | GG35: 0.0015277172 | GH35: 2893 | GI35: 293 | GJ35: =GI35/GH35 -> 0.10127895 | GK35: 107 | GL35: =GK35/GI35 -> 0.36518771 | GM35: 90 | GN35: =GM35/GI35 -> 0.30716724 | GO35: 2600 | GP35: =GO35/GH35 -> 0.89872105 | GQ35: 2053 | GR35: =GQ35/GO35 -> 0.78961538 | GS35: 542 | GT35: =GS35/GO35 -> 0.20846154
A36: La Crosse | B36: 120488 | C36: 29225 | D36: 21784 | E36: 8889 | F36: 2937 | G36: =C36/B36 -> 0.24255528 | H36: =D36/B36 -> 0.18079809 | I36: =E36/B36 -> 0.073774982 | J36: =F36/B36 -> 0.024375871 | K36: 9937 | L36: =K36/D36 -> 0.45616048 | M36: 11847 | N36: =M36/D36 -> 0.54383952 | O36: 37.5 | P36: 51497 | Q36: 19611 | R36: =Q36/P36 -> 0.3808183 | S36: 15300 | T36: =S36/P36 -> 0.29710469 | U36: 9937 | V36: 697 | W36: =V36/U36 -> 0.070141894 | X36: 6921 | Y36: =X36/U36 -> 0.69648787 | Z36: 219 | AA36: =Z36/U36 -> 0.022038845 | AB36: 927 | AC36: =AB36/U36 -> 0.093287713 | AD36: 1173 | AE36: =AD36/U36 -> 0.11804368 | AF36: 11847 | AG36: 825 | AH36: =AG36/AF36 -> 0.069637883 | AI36: 5146 | AJ36: =AI36/AF36 -> 0.43437157 | AK36: 222 | AL36: =AK36/AF36 -> 0.018738921 | AM36: 3741 | AN36: =AM36/AF36 -> 0.31577615 | AO36: 1913 | AP36: =AO36/AF36 -> 0.16147548 | AQ36: =SUM(U36,AF36) -> 21784 | AR36: =SUM(V36,AG36) -> 1522 | AS36: =AR36/AQ36 -> 0.069867793 | AT36: =SUM(X36,AI36) -> 12067 | AU36: =AT36/AQ36 -> 0.55393867 | AV36: =SUM(Z36,AK36) -> 441 | AW36: =AV36/AQ36 -> 0.020244216 | AX36: =SUM(AB36,AM36) -> 4668 | AY36: =AX36/AQ36 -> 0.21428571 | AZ36: =SUM(AD36,AO36) -> 3086 | BA36: =AZ36/AQ36 -> 0.14166361 | BB36: 9756 | BC36: 3143 | BD36: =BC36/BB36 -> 0.32216072 | BE36: 11485 | BF36: 3661 | BG36: =BF36/BE36 -> 0.3187636 | BH36: =SUM(BB36,BE36) -> 21241 | BI36: =SUM(BC36,BF36) -> 6804 | BJ36: =BI36/BH36 -> 0.3203239 | BK36: 21784 | BL36: 6360 | BM36: =BL36/BK36 -> 0.2919574 | BN36: 9937 | BO36: 1964 | BP36: =BO36/BN36 -> 0.19764516 | BQ36: 11847 | BR36: 4396 | BS36: =BR36/BQ36 -> 0.3710644 | BT36: 121060 | BU36: 23130 | BV36: =BU36/BT36 -> 0.19106228 | BW36: =BU36/$BU36 -> 1 | BX36: 106273 | BY36: 22319 | BZ36: =BY36/BX36 -> 0.21001571 | CA36: =BY36/$BU36 -> 0.96493731 | CB36: 2087 | CC36: 112 | CD36: =CC36/CB36 -> 0.053665549 | CE36: =CC36/$BU36 -> 0.0048421963 | CF36: 443 | CG36: 71 | CH36: =CG36/CF36 -> 0.16027088 | CI36: =CG36/$BU36 -> 0.0030696066 | CJ36: 6078 | CK36: 351 | CL36: =CK36/CJ36 -> 0.05774926 | CM36: =CK36/$BU36 -> 0.015175097 | CN36: 59 | CO36: 11 | CP36: =CO36/CN36 -> 0.18644068 | CQ36: =CO36/$BU36 -> 0.00047557285 | CR36: 619 | CS36: 4 | CT36: =CS36/CR36 -> 0.0064620355 | CU36: =CS36/$BU36 -> 0.00017293558 | CV36: 2609 | CW36: 88 | CX36: =CW36/CV36 -> 0.033729398 | CY36: =CW36/$BU36 -> 0.0038045828 | CZ36: 3511 | DA36: 178 | DB36: =DA36/CZ36 -> 0.050697807 | DC36: =DA36/BU36 -> 0.0076956334 | DD36: 9937 | DE36: 683 | DF36: 3093 | DG36: 2910 | DH36: 3251 | DI36: =DE36/DD36 -> 0.068733018 | DJ36: =DF36/DD36 -> 0.31126094 | DK36: =SUM(DG36:DH36)/DD36 -> 0.62000604 | DL36: 11847 | DM36: 473 | DN36: 3992 | DO36: 3892 | DP36: 3490 | DQ36: =DM36/DL36 -> 0.03992572 | DR36: =DN36/DL36 -> 0.33696294 | DS36: =SUM(DO36:DP36)/DL36 -> 0.62311134 | DT36: =SUM(DL36,DD36) -> 21784 | DU36: =SUM(DM36,DE36) -> 1156 | DV36: =SUM(DN36,DF36) -> 7085 | DW36: =SUM(DO36,DG36) -> 6802 | DX36: =SUM(DP36,DH36) -> 6741 | DY36: =DU36/DT36 -> 0.053066471 | DZ36: =DV36/DT36 -> 0.32523871 | EA36: =SUM(DW36:DX36)/DT36 -> 0.62169482 | EB36: 13725 | EC36: 1244 | ED36: =EC36/$EB36 -> 0.090637523 | EE36: 2663 | EF36: =EE36/$EB36 -> 0.1940255 | EG36: 4325 | EH36: =EG36/$EB36 -> 0.3151184 | EI36: 6074 | EJ36: =EI36/$EB36 -> 0.44255009 | EK36: 8843 | EL36: =EK36/$EB36 -> 0.64429872 | EM36: 10635 | EN36: =EM36/$EB36 -> 0.77486339 | EO36: 73013 | EP36: 40817 | EQ36: 83711 | ER36: 94236 | ES36: 55379 | ET36: 9756 | EU36: 809 | EV36: =EU36/ET36 -> 0.082923329 | EW36: 11485 | EX36: 1249 | EY36: =EX36/EW36 -> 0.10875054 | EZ36: =SUM(ET36,EW36) -> 21241 | FA36: =SUM(EU36,EX36) -> 2058 | FB36: =FA36/EZ36 -> 0.096888094 | FC36: 21241 | FD36: 2058 | FE36: =FD36/$FC36 -> 0.096888094 | FF36: 3383 | FG36: =FF36/$FC36 -> 0.15926745 | FH36: 4906 | FI36: =FH36/$FC36 -> 0.23096841 | FJ36: 5771 | FK36: =FJ36/$FC36 -> 0.27169154 | FL36: 9113 | FM36: =FL36/$FC36 -> 0.42902877 | FN36: 1522 | FO36: 0.24580103 | FP36: 22 | FQ36: 0.0035529716 | FR36: 321 | FS36: 0.085714286 | FT36: 11 | FU36: 0.0029372497 | FV36: 1295 | FW36: 0.19319708 | FX36: 0 | FY36: 0 | FZ36: 232 | GA36: 0.045101089 | GB36: 1 | GC36: 0.00019440124 | GD36: 3370 | GE36: 0.1547007 | GF36: 34 | GG36: 0.0015607786 | GH36: 13725 | GI36: 3804 | GJ36: =GI36/GH36 -> 0.27715847 | GK36: 1451 | GL36: =GK36/GI36 -> 0.38144059 | GM36: 2129 | GN36: =GM36/GI36 -> 0.55967403 | GO36: 9921 | GP36: =GO36/GH36 -> 0.72284153 | GQ36: 7462 | GR36: =GQ36/GO36 -> 0.75214192 | GS36: 2371 | GT36: =GS36/GO36 -> 0.23898801
A37: Lafayette | B37: 16942 | C37: 4746 | D37: 3450 | E37: 1402 | F37: 426 | G37: =C37/B37 -> 0.28013222 | H37: =D37/B37 -> 0.20363593 | I37: =E37/B37 -> 0.082752922 | J37: =F37/B37 -> 0.025144611 | K37: 1677 | L37: =K37/D37 -> 0.48608696 | M37: 1773 | N37: =M37/D37 -> 0.51391304 | O37: 40.8 | P37: 6763 | Q37: 3209 | R37: =Q37/P37 -> 0.47449357 | S37: 2487 | T37: =S37/P37 -> 0.36773621 | U37: 1677 | V37: 107 | W37: =V37/U37 -> 0.063804413 | X37: 1081 | Y37: =X37/U37 -> 0.64460346 | Z37: 28 | AA37: =Z37/U37 -> 0.016696482 | AB37: 223 | AC37: =AB37/U37 -> 0.13297555 | AD37: 238 | AE37: =AD37/U37 -> 0.1419201 | AF37: 1773 | AG37: 60 | AH37: =AG37/AF37 -> 0.033840948 | AI37: 914 | AJ37: =AI37/AF37 -> 0.51551043 | AK37: 47 | AL37: =AK37/AF37 -> 0.026508742 | AM37: 545 | AN37: =AM37/AF37 -> 0.30738861 | AO37: 207 | AP37: =AO37/AF37 -> 0.11675127 | AQ37: =SUM(U37,AF37) -> 3450 | AR37: =SUM(V37,AG37) -> 167 | AS37: =AR37/AQ37 -> 0.048405797 | AT37: =SUM(X37,AI37) -> 1995 | AU37: =AT37/AQ37 -> 0.57826087 | AV37: =SUM(Z37,AK37) -> 75 | AW37: =AV37/AQ37 -> 0.02173913 | AX37: =SUM(AB37,AM37) -> 768 | AY37: =AX37/AQ37 -> 0.2226087 | AZ37: =SUM(AD37,AO37) -> 445 | BA37: =AZ37/AQ37 -> 0.12898551 | BB37: 1655 | BC37: 424 | BD37: =BC37/BB37 -> 0.25619335 | BE37: 1758 | BF37: 528 | BG37: =BF37/BE37 -> 0.3003413 | BH37: =SUM(BB37,BE37) -> 3413 | BI37: =SUM(BC37,BF37) -> 952 | BJ37: =BI37/BH37 -> 0.27893349 | BK37: 3450 | BL37: 1112 | BM37: =BL37/BK37 -> 0.32231884 | BN37: 1677 | BO37: 460 | BP37: =BO37/BN37 -> 0.27429934 | BQ37: 1773 | BR37: 652 | BS37: =BR37/BQ37 -> 0.3677383 | BT37: 17306 | BU37: 3667 | BV37: =BU37/BT37 -> 0.21189183 | BW37: =BU37/$BU37 -> 1 | BX37: 15456 | BY37: 3593 | BZ37: =BY37/BX37 -> 0.23246636 | CA37: =BY37/$BU37 -> 0.97982002 | CB37: 105 | CC37: 5 | CD37: =CC37/CB37 -> 0.047619048 | CE37: =CC37/$BU37 -> 0.0013635124 | CF37: 53 | CG37: 4 | CH37: =CG37/CF37 -> 0.075471698 | CI37: =CG37/$BU37 -> 0.0010908099 | CJ37: 98 | CK37: 8 | CL37: =CK37/CJ37 -> 0.081632653 | CM37: =CK37/$BU37 -> 0.0021816199 | CN37: 0 | CO37: 0 | CP37: 0 | CQ37: =CO37/$BU37 -> 0 | CR37: 284 | CS37: 13 | CT37: =CS37/CR37 -> 0.045774648 | CU37: =CS37/$BU37 -> 0.0035451323 | CV37: 158 | CW37: 17 | CX37: =CW37/CV37 -> 0.10759494 | CY37: =CW37/$BU37 -> 0.0046359422 | CZ37: 1436 | DA37: 40 | DB37: =DA37/CZ37 -> 0.027855153 | DC37: =DA37/BU37 -> 0.010908099 | DD37: 1677 | DE37: 124 | DF37: 859 | DG37: 410 | DH37: 284 | DI37: =DE37/DD37 -> 0.073941562 | DJ37: =DF37/DD37 -> 0.51222421 | DK37: =SUM(DG37:DH37)/DD37 -> 0.41383423 | DL37: 1773 | DM37: 148 | DN37: 879 | DO37: 463 | DP37: 283 | DQ37: =DM37/DL37 -> 0.083474337 | DR37: =DN37/DL37 -> 0.49576988 | DS37: =SUM(DO37:DP37)/DL37 -> 0.42075578 | DT37: =SUM(DL37,DD37) -> 3450 | DU37: =SUM(DM37,DE37) -> 272 | DV37: =SUM(DN37,DF37) -> 1738 | DW37: =SUM(DO37,DG37) -> 873 | DX37: =SUM(DP37,DH37) -> 567 | DY37: =DU37/DT37 -> 0.07884058 | DZ37: =DV37/DT37 -> 0.50376812 | EA37: =SUM(DW37:DX37)/DT37 -> 0.4173913 | EB37: 2286 | EC37: 249 | ED37: =EC37/$EB37 -> 0.10892388 | EE37: 497 | EF37: =EE37/$EB37 -> 0.21741032 | EG37: 889 | EH37: =EG37/$EB37 -> 0.38888889 | EI37: 1200 | EJ37: =EI37/$EB37 -> 0.52493438 | EK37: 1605 | EL37: =EK37/$EB37 -> 0.70209974 | EM37: 1929 | EN37: =EM37/$EB37 -> 0.84383202 | EO37: 76462 | EP37: 66389 | EQ37: 98081 | ER37: 93341 | ES37: 47361 | ET37: 1655 | EU37: 137 | EV37: =EU37/ET37 -> 0.082779456 | EW37: 1758 | EX37: 208 | EY37: =EX37/EW37 -> 0.11831627 | EZ37: =SUM(ET37,EW37) -> 3413 | FA37: =SUM(EU37,EX37) -> 345 | FB37: =FA37/EZ37 -> 0.10108409 | FC37: 3413 | FD37: 345 | FE37: =FD37/$FC37 -> 0.10108409 | FF37: 603 | FG37: =FF37/$FC37 -> 0.17667741 | FH37: 887 | FI37: =FH37/$FC37 -> 0.25988866 | FJ37: 1074 | FK37: =FJ37/$FC37 -> 0.31467917 | FL37: 1654 | FM37: =FL37/$FC37 -> 0.48461764 | FN37: 412 | FO37: 0.38397018 | FP37: 2 | FQ37: 0.0018639329 | FR37: 69 | FS37: 0.11423841 | FT37: 0 | FU37: 0 | FV37: 282 | FW37: 0.28923077 | FX37: 12 | FY37: 0.012307692 | FZ37: 51 | GA37: 0.063909774 | GB37: 0 | GC37: 0 | GD37: 814 | GE37: 0.23594203 | GF37: 14 | GG37: 0.004057971 | GH37: 2286 | GI37: 361 | GJ37: =GI37/GH37 -> 0.15791776 | GK37: 139 | GL37: =GK37/GI37 -> 0.38504155 | GM37: 115 | GN37: =GM37/GI37 -> 0.31855956 | GO37: 1925 | GP37: =GO37/GH37 -> 0.84208224 | GQ37: 1482 | GR37: =GQ37/GO37 -> 0.76987013 | GS37: 416 | GT37: =GS37/GO37 -> 0.2161039
A38: Langlade | B38: 19490 | C38: 6781 | D38: 4990 | E38: 2032 | F38: 713 | G38: =C38/B38 -> 0.34792201 | H38: =D38/B38 -> 0.25602873 | I38: =E38/B38 -> 0.10425859 | J38: =F38/B38 -> 0.036582863 | K38: 2417 | L38: =K38/D38 -> 0.48436874 | M38: 2573 | N38: =M38/D38 -> 0.51563126 | O38: 48.7 | P38: 8881 | Q38: 4635 | R38: =Q38/P38 -> 0.52190069 | S38: 3602 | T38: =S38/P38 -> 0.40558496 | U38: 2417 | V38: 119 | W38: =V38/U38 -> 0.049234588 | X38: 1674 | Y38: =X38/U38 -> 0.69259412 | Z38: 68 | AA38: =Z38/U38 -> 0.02813405 | AB38: 216 | AC38: =AB38/U38 -> 0.089366984 | AD38: 340 | AE38: =AD38/U38 -> 0.14067025 | AF38: 2573 | AG38: 59 | AH38: =AG38/AF38 -> 0.022930431 | AI38: 1364 | AJ38: =AI38/AF38 -> 0.53012048 | AK38: 90 | AL38: =AK38/AF38 -> 0.034978624 | AM38: 757 | AN38: =AM38/AF38 -> 0.29420909 | AO38: 303 | AP38: =AO38/AF38 -> 0.11776137 | AQ38: =SUM(U38,AF38) -> 4990 | AR38: =SUM(V38,AG38) -> 178 | AS38: =AR38/AQ38 -> 0.035671343 | AT38: =SUM(X38,AI38) -> 3038 | AU38: =AT38/AQ38 -> 0.60881764 | AV38: =SUM(Z38,AK38) -> 158 | AW38: =AV38/AQ38 -> 0.031663327 | AX38: =SUM(AB38,AM38) -> 973 | AY38: =AX38/AQ38 -> 0.19498998 | AZ38: =SUM(AD38,AO38) -> 643 | BA38: =AZ38/AQ38 -> 0.12885772 | BB38: 2354 | BC38: 802 | BD38: =BC38/BB38 -> 0.34069669 | BE38: 2490 | BF38: 573 | BG38: =BF38/BE38 -> 0.23012048 | BH38: =SUM(BB38,BE38) -> 4844 | BI38: =SUM(BC38,BF38) -> 1375 | BJ38: =BI38/BH38 -> 0.28385632 | BK38: 4990 | BL38: 1470 | BM38: =BL38/BK38 -> 0.29458918 | BN38: 2417 | BO38: 502 | BP38: =BO38/BN38 -> 0.20769549 | BQ38: 2573 | BR38: 968 | BS38: =BR38/BQ38 -> 0.37621454 | BT38: 19535 | BU38: 5282 | BV38: =BU38/BT38 -> 0.27038649 | BW38: =BU38/$BU38 -> 1 | BX38: 18042 | BY38: 5124 | BZ38: =BY38/BX38 -> 0.28400399 | CA38: =BY38/$BU38 -> 0.97008709 | CB38: 225 | CC38: 16 | CD38: =CC38/CB38 -> 0.071111111 | CE38: =CC38/$BU38 -> 0.0030291556 | CF38: 276 | CG38: 42 | CH38: =CG38/CF38 -> 0.15217391 | CI38: =CG38/$BU38 -> 0.0079515335 | CJ38: 119 | CK38: 17 | CL38: =CK38/CJ38 -> 0.14285714 | CM38: =CK38/$BU38 -> 0.0032184778 | CN38: 1 | CO38: 0 | CP38: 0 | CQ38: =CO38/$BU38 -> 0 | CR38: 187 | CS38: 0 | CT38: =CS38/CR38 -> 0 | CU38: =CS38/$BU38 -> 0 | CV38: 320 | CW38: 47 | CX38: =CW38/CV38 -> 0.146875 | CY38: =CW38/$BU38 -> 0.0088981446 | CZ38: 552 | DA38: 36 | DB38: =DA38/CZ38 -> 0.065217391 | DC38: =DA38/BU38 -> 0.0068156002 | DD38: 2417 | DE38: 202 | DF38: 1097 | DG38: 703 | DH38: 415 | DI38: =DE38/DD38 -> 0.083574679 | DJ38: =DF38/DD38 -> 0.45386843 | DK38: =SUM(DG38:DH38)/DD38 -> 0.46255689 | DL38: 2573 | DM38: 244 | DN38: 1260 | DO38: 708 | DP38: 361 | DQ38: =DM38/DL38 -> 0.094830937 | DR38: =DN38/DL38 -> 0.48970074 | DS38: =SUM(DO38:DP38)/DL38 -> 0.41546832 | DT38: =SUM(DL38,DD38) -> 4990 | DU38: =SUM(DM38,DE38) -> 446 | DV38: =SUM(DN38,DF38) -> 2357 | DW38: =SUM(DO38,DG38) -> 1411 | DX38: =SUM(DP38,DH38) -> 776 | DY38: =DU38/DT38 -> 0.089378758 | DZ38: =DV38/DT38 -> 0.47234469 | EA38: =SUM(DW38:DX38)/DT38 -> 0.43827655 | EB38: 3221 | EC38: 336 | ED38: =EC38/$EB38 -> 0.10431543 | EE38: 729 | EF38: =EE38/$EB38 -> 0.22632723 | EG38: 1256 | EH38: =EG38/$EB38 -> 0.38994101 | EI38: 1837 | EJ38: =EI38/$EB38 -> 0.57031978 | EK38: 2419 | EL38: =EK38/$EB38 -> 0.751009 | EM38: 2784 | EN38: =EM38/$EB38 -> 0.86432785 | EO38: 55878 | EP38: 48750 | EQ38: 63625 | ER38: 75625 | ES38: 44432 | ET38: 2354 | EU38: 146 | EV38: =EU38/ET38 -> 0.06202209 | EW38: 2490 | EX38: 300 | EY38: =EX38/EW38 -> 0.12048193 | EZ38: =SUM(ET38,EW38) -> 4844 | FA38: =SUM(EU38,EX38) -> 446 | FB38: =FA38/EZ38 -> 0.092072667 | FC38: 4844 | FD38: 446 | FE38: =FD38/$FC38 -> 0.092072667 | FF38: 922 | FG38: =FF38/$FC38 -> 0.19033856 | FH38: 1251 | FI38: =FH38/$FC38 -> 0.25825764 | FJ38: 1434 | FK38: =FJ38/$FC38 -> 0.29603633 | FL38: 2776 | FM38: =FL38/$FC38 -> 0.5730801 | FN38: 347 | FO38: 0.22949735 | FP38: 0 | FQ38: 0 | FR38: 50 | FS38: 0.055248619 | FT38: 0 | FU38: 0 | FV38: 314 | FW38: 0.21715076 | FX38: 0 | FY38: 0 | FZ38: 24 | GA38: 0.021295475 | GB38: 0 | GC38: 0 | GD38: 735 | GE38: 0.14729459 | GF38: 0 | GG38: 0 | GH38: 3221 | GI38: 539 | GJ38: =GI38/GH38 -> 0.16733934 | GK38: 113 | GL38: =GK38/GI38 -> 0.2096475 | GM38: 281 | GN38: =GM38/GI38 -> 0.52133581 | GO38: 2682 | GP38: =GO38/GH38 -> 0.83266066 | GQ38: 2174 | GR38: =GQ38/GO38 -> 0.81058911 | GS38: 485 | GT38: =GS38/GO38 -> 0.1808352
A39: Lincoln | B39: 28426 | C39: 9330 | D39: 6721 | E39: 2671 | F39: 830 | G39: =C39/B39 -> 0.32822064 | H39: =D39/B39 -> 0.23643847 | I39: =E39/B39 -> 0.093963273 | J39: =F39/B39 -> 0.029198621 | K39: 3236 | L39: =K39/D39 -> 0.48147597 | M39: 3485 | N39: =M39/D39 -> 0.51852403 | O39: 49.3 | P39: 12772 | Q39: 6281 | R39: =Q39/P39 -> 0.49177889 | S39: 4616 | T39: =S39/P39 -> 0.3614156 | U39: 3236 | V39: 151 | W39: =V39/U39 -> 0.046662546 | X39: 2038 | Y39: =X39/U39 -> 0.62978986 | Z39: 28 | AA39: =Z39/U39 -> 0.0086526576 | AB39: 333 | AC39: =AB39/U39 -> 0.10290482 | AD39: 686 | AE39: =AD39/U39 -> 0.21199011 | AF39: 3485 | AG39: 102 | AH39: =AG39/AF39 -> 0.029268293 | AI39: 1707 | AJ39: =AI39/AF39 -> 0.48981349 | AK39: 77 | AL39: =AK39/AF39 -> 0.022094692 | AM39: 1085 | AN39: =AM39/AF39 -> 0.31133429 | AO39: 514 | AP39: =AO39/AF39 -> 0.14748924 | AQ39: =SUM(U39,AF39) -> 6721 | AR39: =SUM(V39,AG39) -> 253 | AS39: =AR39/AQ39 -> 0.037643208 | AT39: =SUM(X39,AI39) -> 3745 | AU39: =AT39/AQ39 -> 0.55720875 | AV39: =SUM(Z39,AK39) -> 105 | AW39: =AV39/AQ39 -> 0.015622675 | AX39: =SUM(AB39,AM39) -> 1418 | AY39: =AX39/AQ39 -> 0.21098051 | AZ39: =SUM(AD39,AO39) -> 1200 | BA39: =AZ39/AQ39 -> 0.17854486 | BB39: 3193 | BC39: 1059 | BD39: =BC39/BB39 -> 0.33166301 | BE39: 3302 | BF39: 868 | BG39: =BF39/BE39 -> 0.26287099 | BH39: =SUM(BB39,BE39) -> 6495 | BI39: =SUM(BC39,BF39) -> 1927 | BJ39: =BI39/BH39 -> 0.29668976 | BK39: 6721 | BL39: 1884 | BM39: =BL39/BK39 -> 0.28031543 | BN39: 3236 | BO39: 722 | BP39: =BO39/BN39 -> 0.22311496 | BQ39: 3485 | BR39: 1162 | BS39: =BR39/BQ39 -> 0.33342898 | BT39: 28461 | BU39: 7159 | BV39: =BU39/BT39 -> 0.25153719 | BW39: =BU39/$BU39 -> 1 | BX39: 26663 | BY39: 7007 | BZ39: =BY39/BX39 -> 0.26279863 | CA39: =BY39/$BU39 -> 0.97876798 | CB39: 184 | CC39: 9 | CD39: =CC39/CB39 -> 0.048913043 | CE39: =CC39/$BU39 -> 0.0012571588 | CF39: 163 | CG39: 29 | CH39: =CG39/CF39 -> 0.17791411 | CI39: =CG39/$BU39 -> 0.0040508451 | CJ39: 201 | CK39: 27 | CL39: =CK39/CJ39 -> 0.13432836 | CM39: =CK39/$BU39 -> 0.0037714765 | CN39: 13 | CO39: 5 | CP39: =CO39/CN39 -> 0.38461538 | CQ39: =CO39/$BU39 -> 0.00069842157 | CR39: 104 | CS39: 4 | CT39: =CS39/CR39 -> 0.038461538 | CU39: =CS39/$BU39 -> 0.00055873725 | CV39: 465 | CW39: 38 | CX39: =CW39/CV39 -> 0.08172043 | CY39: =CW39/$BU39 -> 0.0053080039 | CZ39: 772 | DA39: 44 | DB39: =DA39/CZ39 -> 0.056994819 | DC39: =DA39/BU39 -> 0.0061461098 | DD39: 3236 | DE39: 260 | DF39: 1334 | DG39: 998 | DH39: 644 | DI39: =DE39/DD39 -> 0.080346106 | DJ39: =DF39/DD39 -> 0.41223733 | DK39: =SUM(DG39:DH39)/DD39 -> 0.50741656 | DL39: 3485 | DM39: 278 | DN39: 1694 | DO39: 849 | DP39: 664 | DQ39: =DM39/DL39 -> 0.079770445 | DR39: =DN39/DL39 -> 0.48608321 | DS39: =SUM(DO39:DP39)/DL39 -> 0.43414634 | DT39: =SUM(DL39,DD39) -> 6721 | DU39: =SUM(DM39,DE39) -> 538 | DV39: =SUM(DN39,DF39) -> 3028 | DW39: =SUM(DO39,DG39) -> 1847 | DX39: =SUM(DP39,DH39) -> 1308 | DY39: =DU39/DT39 -> 0.080047612 | DZ39: =DV39/DT39 -> 0.4505282 | EA39: =SUM(DW39:DX39)/DT39 -> 0.46942419 | EB39: 4303 | EC39: 499 | ED39: =EC39/$EB39 -> 0.11596561 | EE39: 988 | EF39: =EE39/$EB39 -> 0.22960725 | EG39: 1577 | EH39: =EG39/$EB39 -> 0.3664885 | EI39: 2099 | EJ39: =EI39/$EB39 -> 0.48779921 | EK39: 2990 | EL39: =EK39/$EB39 -> 0.69486405 | EM39: 3548 | EN39: =EM39/$EB39 -> 0.82454102 | EO39: 68164 | EP39: 48445 | EQ39: 79245 | ER39: 82621 | ES39: 51661 | ET39: 3193 | EU39: 296 | EV39: =EU39/ET39 -> 0.092702787 | EW39: 3302 | EX39: 493 | EY39: =EX39/EW39 -> 0.14930345 | EZ39: =SUM(ET39,EW39) -> 6495 | FA39: =SUM(EU39,EX39) -> 789 | FB39: =FA39/EZ39 -> 0.12147806 | FC39: 6495 | FD39: 789 | FE39: =FD39/$FC39 -> 0.12147806 | FF39: 1451 | FG39: =FF39/$FC39 -> 0.22340262 | FH39: 1906 | FI39: =FH39/$FC39 -> 0.29345651 | FJ39: 2166 | FK39: =FJ39/$FC39 -> 0.3334873 | FL39: 3264 | FM39: =FL39/$FC39 -> 0.50254042 | FN39: 376 | FO39: 0.18305745 | FP39: 5 | FQ39: 0.0024342746 | FR39: 80 | FS39: 0.067681895 | FT39: 0 | FU39: 0 | FV39: 288 | FW39: 0.14428858 | FX39: 3 | FY39: 0.001503006 | FZ39: 52 | GA39: 0.034922767 | GB39: 0 | GC39: 0 | GD39: 796 | GE39: 0.11843476 | GF39: 8 | GG39: 0.0011902991 | GH39: 4303 | GI39: 713 | GJ39: =GI39/GH39 -> 0.16569835 | GK39: 293 | GL39: =GK39/GI39 -> 0.41093969 | GM39: 312 | GN39: =GM39/GI39 -> 0.43758766 | GO39: 3590 | GP39: =GO39/GH39 -> 0.83430165 | GQ39: 2684 | GR39: =GQ39/GO39 -> 0.74763231 | GS39: 829 | GT39: =GS39/GO39 -> 0.23091922
A40: Manitowoc | B40: 81406 | C40: 25254 | D40: 18118 | E40: 7356 | F40: 1796 | G40: =C40/B40 -> 0.31022283 | H40: =D40/B40 -> 0.22256345 | I40: =E40/B40 -> 0.09036189 | J40: =F40/B40 -> 0.022062256 | K40: 8480 | L40: =K40/D40 -> 0.46804283 | M40: 9638 | N40: =M40/D40 -> 0.53195717 | O40: 45.1 | P40: 35188 | Q40: 16897 | R40: =Q40/P40 -> 0.48019211 | S40: 12111 | T40: =S40/P40 -> 0.34417983 | U40: 8480 | V40: 571 | W40: =V40/U40 -> 0.067334906 | X40: 5783 | Y40: =X40/U40 -> 0.68195755 | Z40: 186 | AA40: =Z40/U40 -> 0.021933962 | AB40: 986 | AC40: =AB40/U40 -> 0.11627358 | AD40: 954 | AE40: =AD40/U40 -> 0.1125 | AF40: 9638 | AG40: 608 | AH40: =AG40/AF40 -> 0.063083627 | AI40: 4958 | AJ40: =AI40/AF40 -> 0.51442208 | AK40: 208 | AL40: =AK40/AF40 -> 0.021581241 | AM40: 2800 | AN40: =AM40/AF40 -> 0.2905167 | AO40: 1064 | AP40: =AO40/AF40 -> 0.11039635 | AQ40: =SUM(U40,AF40) -> 18118 | AR40: =SUM(V40,AG40) -> 1179 | AS40: =AR40/AQ40 -> 0.065073408 | AT40: =SUM(X40,AI40) -> 10741 | AU40: =AT40/AQ40 -> 0.59283585 | AV40: =SUM(Z40,AK40) -> 394 | AW40: =AV40/AQ40 -> 0.02174633 | AX40: =SUM(AB40,AM40) -> 3786 | AY40: =AX40/AQ40 -> 0.20896346 | AZ40: =SUM(AD40,AO40) -> 2018 | BA40: =AZ40/AQ40 -> 0.11138095 | BB40: 8385 | BC40: 2117 | BD40: =BC40/BB40 -> 0.25247466 | BE40: 9292 | BF40: 1908 | BG40: =BF40/BE40 -> 0.20533793 | BH40: =SUM(BB40,BE40) -> 17677 | BI40: =SUM(BC40,BF40) -> 4025 | BJ40: =BI40/BH40 -> 0.22769701 | BK40: 18118 | BL40: 4816 | BM40: =BL40/BK40 -> 0.265813 | BN40: 8480 | BO40: 1811 | BP40: =BO40/BN40 -> 0.21356132 | BQ40: 9638 | BR40: 3005 | BS40: =BR40/BQ40 -> 0.31178668 | BT40: 81513 | BU40: 19368 | BV40: =BU40/BT40 -> 0.23760627 | BW40: =BU40/$BU40 -> 1 | BX40: 71192 | BY40: 18791 | BZ40: =BY40/BX40 -> 0.2639482 | CA40: =BY40/$BU40 -> 0.97020859 | CB40: 1055 | CC40: 52 | CD40: =CC40/CB40 -> 0.0492891 | CE40: =CC40/$BU40 -> 0.002684841 | CF40: 462 | CG40: 80 | CH40: =CG40/CF40 -> 0.17316017 | CI40: =CG40/$BU40 -> 0.0041305246 | CJ40: 2558 | CK40: 190 | CL40: =CK40/CJ40 -> 0.074276779 | CM40: =CK40/$BU40 -> 0.0098099959 | CN40: 59 | CO40: 2 | CP40: =CO40/CN40 -> 0.033898305 | CQ40: =CO40/$BU40 -> 0.00010326311 | CR40: 656 | CS40: 0 | CT40: =CS40/CR40 -> 0 | CU40: =CS40/$BU40 -> 0 | CV40: 1230 | CW40: 45 | CX40: =CW40/CV40 -> 0.036585366 | CY40: =CW40/$BU40 -> 0.0023234201 | CZ40: 4957 | DA40: 208 | DB40: =DA40/CZ40 -> 0.041960863 | DC40: =DA40/BU40 -> 0.010739364 | DD40: 8480 | DE40: 755 | DF40: 3580 | DG40: 2188 | DH40: 1957 | DI40: =DE40/DD40 -> 0.089033019 | DJ40: =DF40/DD40 -> 0.42216981 | DK40: =SUM(DG40:DH40)/DD40 -> 0.48879717 | DL40: 9638 | DM40: 583 | DN40: 4733 | DO40: 2421 | DP40: 1901 | DQ40: =DM40/DL40 -> 0.060489728 | DR40: =DN40/DL40 -> 0.49107699 | DS40: =SUM(DO40:DP40)/DL40 -> 0.44843328 | DT40: =SUM(DL40,DD40) -> 18118 | DU40: =SUM(DM40,DE40) -> 1338 | DV40: =SUM(DN40,DF40) -> 8313 | DW40: =SUM(DO40,DG40) -> 4609 | DX40: =SUM(DP40,DH40) -> 3858 | DY40: =DU40/DT40 -> 0.073849211 | DZ40: =DV40/DT40 -> 0.45882548 | EA40: =SUM(DW40:DX40)/DT40 -> 0.46732531 | EB40: 11196 | EC40: 853 | ED40: =EC40/$EB40 -> 0.076187924 | EE40: 1964 | EF40: =EE40/$EB40 -> 0.17541979 | EG40: 3334 | EH40: =EG40/$EB40 -> 0.29778492 | EI40: 5130 | EJ40: =EI40/$EB40 -> 0.45819936 | EK40: 7745 | EL40: =EK40/$EB40 -> 0.69176492 | EM40: 9276 | EN40: =EM40/$EB40 -> 0.82851018 | EO40: 69148 | EP40: 42421 | EQ40: 80940 | ER40: 84769 | ES40: 52992 | ET40: 8385 | EU40: 468 | EV40: =EU40/ET40 -> 0.055813953 | EW40: 9292 | EX40: 1142 | EY40: =EX40/EW40 -> 0.12290142 | EZ40: =SUM(ET40,EW40) -> 17677 | FA40: =SUM(EU40,EX40) -> 1610 | FB40: =FA40/EZ40 -> 0.091078803 | FC40: 17677 | FD40: 1610 | FE40: =FD40/$FC40 -> 0.091078803 | FF40: 2783 | FG40: =FF40/$FC40 -> 0.15743622 | FH40: 3813 | FI40: =FH40/$FC40 -> 0.21570402 | FJ40: 4458 | FK40: =FJ40/$FC40 -> 0.25219211 | FL40: 8034 | FM40: =FL40/$FC40 -> 0.45448888 | FN40: 1375 | FO40: 0.25505472 | FP40: 22 | FQ40: 0.0040808755 | FR40: 240 | FS40: 0.077695047 | FT40: 8 | FU40: 0.0025898349 | FV40: 1023 | FW40: 0.19046732 | FX40: 4 | FY40: 0.00074474027 | FZ40: 124 | GA40: 0.02906023 | GB40: 11 | GC40: 0.0025779236 | GD40: 2762 | GE40: 0.15244508 | GF40: 45 | GG40: 0.0024837178 | GH40: 11196 | GI40: 1646 | GJ40: =GI40/GH40 -> 0.14701679 | GK40: 672 | GL40: =GK40/GI40 -> 0.40826245 | GM40: 666 | GN40: =GM40/GI40 -> 0.40461725 | GO40: 9550 | GP40: =GO40/GH40 -> 0.85298321 | GQ40: 7775 | GR40: =GQ40/GO40 -> 0.81413613 | GS40: 1705 | GT40: =GS40/GO40 -> 0.17853403
A41: Marathon | B41: 138403 | C41: 36893 | D41: 26553 | E41: 11009 | F41: 3309 | G41: =C41/B41 -> 0.26656214 | H41: =D41/B41 -> 0.19185278 | I41: =E41/B41 -> 0.079543073 | J41: =F41/B41 -> 0.023908441 | K41: 12538 | L41: =K41/D41 -> 0.4721877 | M41: 14015 | N41: =M41/D41 -> 0.5278123 | O41: 41.3 | P41: 57866 | Q41: 24934 | R41: =Q41/P41 -> 0.43089206 | S41: 18509 | T41: =S41/P41 -> 0.31985968 | U41: 12538 | V41: 644 | W41: =V41/U41 -> 0.051363854 | X41: 8964 | Y41: =X41/U41 -> 0.71494656 | Z41: 300 | AA41: =Z41/U41 -> 0.023927261 | AB41: 993 | AC41: =AB41/U41 -> 0.079199234 | AD41: 1637 | AE41: =AD41/U41 -> 0.13056309 | AF41: 14015 | AG41: 762 | AH41: =AG41/AF41 -> 0.054370318 | AI41: 6830 | AJ41: =AI41/AF41 -> 0.487335 | AK41: 235 | AL41: =AK41/AF41 -> 0.016767749 | AM41: 4130 | AN41: =AM41/AF41 -> 0.29468427 | AO41: 2058 | AP41: =AO41/AF41 -> 0.14684267 | AQ41: =SUM(U41,AF41) -> 26553 | AR41: =SUM(V41,AG41) -> 1406 | AS41: =AR41/AQ41 -> 0.052950702 | AT41: =SUM(X41,AI41) -> 15794 | AU41: =AT41/AQ41 -> 0.59481038 | AV41: =SUM(Z41,AK41) -> 535 | AW41: =AV41/AQ41 -> 0.020148382 | AX41: =SUM(AB41,AM41) -> 5123 | AY41: =AX41/AQ41 -> 0.19293488 | AZ41: =SUM(AD41,AO41) -> 3695 | BA41: =AZ41/AQ41 -> 0.13915565 | BB41: 12361 | BC41: 3701 | BD41: =BC41/BB41 -> 0.29940943 | BE41: 13499 | BF41: 4179 | BG41: =BF41/BE41 -> 0.30957849 | BH41: =SUM(BB41,BE41) -> 25860 | BI41: =SUM(BC41,BF41) -> 7880 | BJ41: =BI41/BH41 -> 0.30471771 | BK41: 26553 | BL41: 7367 | BM41: =BL41/BK41 -> 0.27744511 | BN41: 12538 | BO41: 2263 | BP41: =BO41/BN41 -> 0.18049131 | BQ41: 14015 | BR41: 5104 | BS41: =BR41/BQ41 -> 0.36418123 | BT41: 139091 | BU41: 28126 | BV41: =BU41/BT41 -> 0.20221294 | BW41: =BU41/$BU41 -> 1 | BX41: 120120 | BY41: 27143 | BZ41: =BY41/BX41 -> 0.2259657 | CA41: =BY41/$BU41 -> 0.96505013 | CB41: 1381 | CC41: 57 | CD41: =CC41/CB41 -> 0.041274439 | CE41: =CC41/$BU41 -> 0.0020265946 | CF41: 653 | CG41: 97 | CH41: =CG41/CF41 -> 0.14854518 | CI41: =CG41/$BU41 -> 0.0034487663 | CJ41: 9124 | CK41: 542 | CL41: =CK41/CJ41 -> 0.05940377 | CM41: =CK41/$BU41 -> 0.019270426 | CN41: 43 | CO41: 7 | CP41: =CO41/CN41 -> 0.1627907 | CQ41: =CO41/$BU41 -> 0.00024888004 | CR41: 364 | CS41: 0 | CT41: =CS41/CR41 -> 0 | CU41: =CS41/$BU41 -> 0 | CV41: 2309 | CW41: 78 | CX41: =CW41/CV41 -> 0.033780858 | CY41: =CW41/$BU41 -> 0.0027732347 | CZ41: 5461 | DA41: 202 | DB41: =DA41/CZ41 -> 0.036989562 | DC41: =DA41/BU41 -> 0.0071819669 | DD41: 12538 | DE41: 961 | DF41: 5321 | DG41: 3422 | DH41: 2834 | DI41: =DE41/DD41 -> 0.076646993 | DJ41: =DF41/DD41 -> 0.42438985 | DK41: =SUM(DG41:DH41)/DD41 -> 0.49896315 | DL41: 14015 | DM41: 1105 | DN41: 6489 | DO41: 3796 | DP41: 2625 | DQ41: =DM41/DL41 -> 0.078844096 | DR41: =DN41/DL41 -> 0.46300392 | DS41: =SUM(DO41:DP41)/DL41 -> 0.45815198 | DT41: =SUM(DL41,DD41) -> 26553 | DU41: =SUM(DM41,DE41) -> 2066 | DV41: =SUM(DN41,DF41) -> 11810 | DW41: =SUM(DO41,DG41) -> 7218 | DX41: =SUM(DP41,DH41) -> 5459 | DY41: =DU41/DT41 -> 0.077806651 | DZ41: =DV41/DT41 -> 0.44477084 | EA41: =SUM(DW41:DX41)/DT41 -> 0.47742251 | EB41: 16959 | EC41: 1393 | ED41: =EC41/$EB41 -> 0.082139277 | EE41: 3026 | EF41: =EE41/$EB41 -> 0.17843033 | EG41: 5571 | EH41: =EG41/$EB41 -> 0.32849814 | EI41: 7985 | EJ41: =EI41/$EB41 -> 0.47084144 | EK41: 11563 | EL41: =EK41/$EB41 -> 0.68182086 | EM41: 13906 | EN41: =EM41/$EB41 -> 0.81997759 | EO41: 77884 | EP41: 66385 | EQ41: 91686 | ER41: 98098 | ES41: 53258 | ET41: 12361 | EU41: 850 | EV41: =EU41/ET41 -> 0.068764663 | EW41: 13499 | EX41: 1517 | EY41: =EX41/EW41 -> 0.11237869 | EZ41: =SUM(ET41,EW41) -> 25860 | FA41: =SUM(EU41,EX41) -> 2367 | FB41: =FA41/EZ41 -> 0.091531323 | FC41: 25860 | FD41: 2367 | FE41: =FD41/$FC41 -> 0.091531323 | FF41: 4185 | FG41: =FF41/$FC41 -> 0.16183295 | FH41: 5879 | FI41: =FH41/$FC41 -> 0.22733952 | FJ41: 6726 | FK41: =FJ41/$FC41 -> 0.26009281 | FL41: 12322 | FM41: =FL41/$FC41 -> 0.47648879 | FN41: 1868 | FO41: 0.24200026 | FP41: 39 | FQ41: 0.0050524679 | FR41: 314 | FS41: 0.065158747 | FT41: 6 | FU41: 0.0012450716 | FV41: 1740 | FW41: 0.22236422 | FX41: 62 | FY41: 0.0079233227 | FZ41: 221 | GA41: 0.035702746 | GB41: 0 | GC41: 0 | GD41: 4143 | GE41: 0.15602757 | GF41: 107 | GG41: 0.0040296765 | GH41: 16959 | GI41: 3735 | GJ41: =GI41/GH41 -> 0.22023704 | GK41: 1287 | GL41: =GK41/GI41 -> 0.34457831 | GM41: 2091 | GN41: =GM41/GI41 -> 0.55983936 | GO41: 13224 | GP41: =GO41/GH41 -> 0.77976296 | GQ41: 10680 | GR41: =GQ41/GO41 -> 0.8076225 | GS41: 2480 | GT41: =GS41/GO41 -> 0.18753781
A42: Marinette | B42: 42046 | C42: 14539 | D42: 10636 | E42: 4315 | F42: 1294 | G42: =C42/B42 -> 0.34578795 | H42: =D42/B42 -> 0.25296104 | I42: =E42/B42 -> 0.1026257 | J42: =F42/B42 -> 0.030775817 | K42: 5177 | L42: =K42/D42 -> 0.48674314 | M42: 5459 | N42: =M42/D42 -> 0.51325686 | O42: 48.7 | P42: 19051 | Q42: 9778 | R42: =Q42/P42 -> 0.5132539 | S42: 7503 | T42: =S42/P42 -> 0.39383759 | U42: 5177 | V42: 323 | W42: =V42/U42 -> 0.062391346 | X42: 3347 | Y42: =X42/U42 -> 0.64651342 | Z42: 261 | AA42: =Z42/U42 -> 0.050415298 | AB42: 463 | AC42: =AB42/U42 -> 0.089434035 | AD42: 783 | AE42: =AD42/U42 -> 0.1512459 | AF42: 5459 | AG42: 159 | AH42: =AG42/AF42 -> 0.029126214 | AI42: 3063 | AJ42: =AI42/AF42 -> 0.56109178 | AK42: 152 | AL42: =AK42/AF42 -> 0.027843927 | AM42: 1551 | AN42: =AM42/AF42 -> 0.28411797 | AO42: 534 | AP42: =AO42/AF42 -> 0.097820114 | AQ42: =SUM(U42,AF42) -> 10636 | AR42: =SUM(V42,AG42) -> 482 | AS42: =AR42/AQ42 -> 0.045317789 | AT42: =SUM(X42,AI42) -> 6410 | AU42: =AT42/AQ42 -> 0.60267018 | AV42: =SUM(Z42,AK42) -> 413 | AW42: =AV42/AQ42 -> 0.038830387 | AX42: =SUM(AB42,AM42) -> 2014 | AY42: =AX42/AQ42 -> 0.1893569 | AZ42: =SUM(AD42,AO42) -> 1317 | BA42: =AZ42/AQ42 -> 0.12382475 | BB42: 5010 | BC42: 1727 | BD42: =BC42/BB42 -> 0.34471058 | BE42: 5236 | BF42: 1247 | BG42: =BF42/BE42 -> 0.2381589 | BH42: =SUM(BB42,BE42) -> 10246 | BI42: =SUM(BC42,BF42) -> 2974 | BJ42: =BI42/BH42 -> 0.29025961 | BK42: 10636 | BL42: 2876 | BM42: =BL42/BK42 -> 0.27040241 | BN42: 5177 | BO42: 1327 | BP42: =BO42/BN42 -> 0.25632606 | BQ42: 5459 | BR42: 1549 | BS42: =BR42/BQ42 -> 0.2837516 | BT42: 42343 | BU42: 11155 | BV42: =BU42/BT42 -> 0.26344378 | BW42: =BU42/$BU42 -> 1 | BX42: 39498 | BY42: 10858 | BZ42: =BY42/BX42 -> 0.27489999 | CA42: =BY42/$BU42 -> 0.97337517 | CB42: 328 | CC42: 17 | CD42: =CC42/CB42 -> 0.051829268 | CE42: =CC42/$BU42 -> 0.0015239803 | CF42: 306 | CG42: 72 | CH42: =CG42/CF42 -> 0.23529412 | CI42: =CG42/$BU42 -> 0.0064545047 | CJ42: 237 | CK42: 41 | CL42: =CK42/CJ42 -> 0.17299578 | CM42: =CK42/$BU42 -> 0.0036754818 | CN42: 12 | CO42: 4 | CP42: =CO42/CN42 -> 0.33333333 | CQ42: =CO42/$BU42 -> 0.00035858359 | CR42: 227 | CS42: 0 | CT42: =CS42/CR42 -> 0 | CU42: =CS42/$BU42 -> 0 | CV42: 548 | CW42: 56 | CX42: =CW42/CV42 -> 0.10218978 | CY42: =CW42/$BU42 -> 0.0050201703 | CZ42: 1414 | DA42: 107 | DB42: =DA42/CZ42 -> 0.075671853 | DC42: =DA42/BU42 -> 0.0095921112 | DD42: 5177 | DE42: 445 | DF42: 2117 | DG42: 1753 | DH42: 862 | DI42: =DE42/DD42 -> 0.085957118 | DJ42: =DF42/DD42 -> 0.40892409 | DK42: =SUM(DG42:DH42)/DD42 -> 0.50511879 | DL42: 5459 | DM42: 480 | DN42: 2443 | DO42: 1492 | DP42: 1044 | DQ42: =DM42/DL42 -> 0.087928192 | DR42: =DN42/DL42 -> 0.44751786 | DS42: =SUM(DO42:DP42)/DL42 -> 0.46455395 | DT42: =SUM(DL42,DD42) -> 10636 | DU42: =SUM(DM42,DE42) -> 925 | DV42: =SUM(DN42,DF42) -> 4560 | DW42: =SUM(DO42,DG42) -> 3245 | DX42: =SUM(DP42,DH42) -> 1906 | DY42: =DU42/DT42 -> 0.086968785 | DZ42: =DV42/DT42 -> 0.42873261 | EA42: =SUM(DW42:DX42)/DT42 -> 0.48429861 | EB42: 6882 | EC42: 494 | ED42: =EC42/$EB42 -> 0.071781459 | EE42: 1422 | EF42: =EE42/$EB42 -> 0.20662598 | EG42: 2392 | EH42: =EG42/$EB42 -> 0.34757338 | EI42: 3547 | EJ42: =EI42/$EB42 -> 0.5154025 | EK42: 5282 | EL42: =EK42/$EB42 -> 0.76750944 | EM42: 6053 | EN42: =EM42/$EB42 -> 0.87954083 | EO42: 63809 | EP42: 50564 | EQ42: 81821 | ER42: 76825 | ES42: 48134 | ET42: 5010 | EU42: 471 | EV42: =EU42/ET42 -> 0.094011976 | EW42: 5236 | EX42: 472 | EY42: =EX42/EW42 -> 0.090145149 | EZ42: =SUM(ET42,EW42) -> 10246 | FA42: =SUM(EU42,EX42) -> 943 | FB42: =FA42/EZ42 -> 0.092035916 | FC42: 10246 | FD42: 943 | FE42: =FD42/$FC42 -> 0.092035916 | FF42: 1934 | FG42: =FF42/$FC42 -> 0.18875659 | FH42: 2925 | FI42: =FH42/$FC42 -> 0.28547726 | FJ42: 3403 | FK42: =FJ42/$FC42 -> 0.33212961 | FL42: 5769 | FM42: =FL42/$FC42 -> 0.56304899 | FN42: 509 | FO42: 0.15797641 | FP42: 18 | FQ42: 0.0055865922 | FR42: 102 | FS42: 0.052173913 | FT42: 18 | FU42: 0.0092071611 | FV42: 708 | FW42: 0.22846079 | FX42: 8 | FY42: 0.0025814779 | FZ42: 65 | GA42: 0.027542373 | GB42: 0 | GC42: 0 | GD42: 1384 | GE42: 0.13012411 | GF42: 44 | GG42: 0.0041368936 | GH42: 6882 | GI42: 1057 | GJ42: =GI42/GH42 -> 0.15358907 | GK42: 526 | GL42: =GK42/GI42 -> 0.49763482 | GM42: 374 | GN42: =GM42/GI42 -> 0.3538316 | GO42: 5825 | GP42: =GO42/GH42 -> 0.84641093 | GQ42: 4630 | GR42: =GQ42/GO42 -> 0.79484979 | GS42: 1189 | GT42: =GS42/GO42 -> 0.20412017
A43: Marquette | B43: 15746 | C43: 5739 | D43: 4183 | E43: 1567 | F43: 419 | G43: =C43/B43 -> 0.36447352 | H43: =D43/B43 -> 0.26565477 | I43: =E43/B43 -> 0.099517338 | J43: =F43/B43 -> 0.026609933 | K43: 2105 | L43: =K43/D43 -> 0.50322735 | M43: 2078 | N43: =M43/D43 -> 0.49677265 | O43: 50.7 | P43: 6987 | Q43: 3978 | R43: =Q43/P43 -> 0.56934307 | S43: 3065 | T43: =S43/P43 -> 0.43867182 | U43: 2105 | V43: 96 | W43: =V43/U43 -> 0.045605701 | X43: 1312 | Y43: =X43/U43 -> 0.62327791 | Z43: 41 | AA43: =Z43/U43 -> 0.019477435 | AB43: 316 | AC43: =AB43/U43 -> 0.15011876 | AD43: 340 | AE43: =AD43/U43 -> 0.16152019 | AF43: 2078 | AG43: 62 | AH43: =AG43/AF43 -> 0.029836381 | AI43: 1109 | AJ43: =AI43/AF43 -> 0.53368624 | AK43: 11 | AL43: =AK43/AF43 -> 0.0052935515 | AM43: 640 | AN43: =AM43/AF43 -> 0.30798845 | AO43: 256 | AP43: =AO43/AF43 -> 0.12319538 | AQ43: =SUM(U43,AF43) -> 4183 | AR43: =SUM(V43,AG43) -> 158 | AS43: =AR43/AQ43 -> 0.037771934 | AT43: =SUM(X43,AI43) -> 2421 | AU43: =AT43/AQ43 -> 0.57877122 | AV43: =SUM(Z43,AK43) -> 52 | AW43: =AV43/AQ43 -> 0.012431269 | AX43: =SUM(AB43,AM43) -> 956 | AY43: =AX43/AQ43 -> 0.22854411 | AZ43: =SUM(AD43,AO43) -> 596 | BA43: =AZ43/AQ43 -> 0.14248147 | BB43: 2079 | BC43: 830 | BD43: =BC43/BB43 -> 0.3992304 | BE43: 2061 | BF43: 499 | BG43: =BF43/BE43 -> 0.24211548 | BH43: =SUM(BB43,BE43) -> 4140 | BI43: =SUM(BC43,BF43) -> 1329 | BJ43: =BI43/BH43 -> 0.32101449 | BK43: 4183 | BL43: 1177 | BM43: =BL43/BK43 -> 0.281377 | BN43: 2105 | BO43: 522 | BP43: =BO43/BN43 -> 0.247981 | BQ43: 2078 | BR43: 655 | BS43: =BR43/BQ43 -> 0.31520693 | BT43: 15743 | BU43: 4425 | BV43: =BU43/BT43 -> 0.2810773 | BW43: =BU43/$BU43 -> 1 | BX43: 14581 | BY43: 4283 | BZ43: =BY43/BX43 -> 0.29373843 | CA43: =BY43/$BU43 -> 0.9679096 | CB43: 99 | CC43: 20 | CD43: =CC43/CB43 -> 0.2020202 | CE43: =CC43/$BU43 -> 0.004519774 | CF43: 123 | CG43: 36 | CH43: =CG43/CF43 -> 0.29268293 | CI43: =CG43/$BU43 -> 0.0081355932 | CJ43: 142 | CK43: 27 | CL43: =CK43/CJ43 -> 0.19014085 | CM43: =CK43/$BU43 -> 0.0061016949 | CN43: 4 | CO43: 0 | CP43: =CO43/CN43 -> 0 | CQ43: =CO43/$BU43 -> 0 | CR43: 152 | CS43: 0 | CT43: =CS43/CR43 -> 0 | CU43: =CS43/$BU43 -> 0 | CV43: 158 | CW43: 17 | CX43: =CW43/CV43 -> 0.10759494 | CY43: =CW43/$BU43 -> 0.0038418079 | CZ43: 636 | DA43: 42 | DB43: =DA43/CZ43 -> 0.066037736 | DC43: =DA43/BU43 -> 0.0094915254 | DD43: 2105 | DE43: 195 | DF43: 949 | DG43: 681 | DH43: 280 | DI43: =DE43/DD43 -> 0.09263658 | DJ43: =DF43/DD43 -> 0.45083135 | DK43: =SUM(DG43:DH43)/DD43 -> 0.45653207 | DL43: 2078 | DM43: 150 | DN43: 1047 | DO43: 576 | DP43: 305 | DQ43: =DM43/DL43 -> 0.072184793 | DR43: =DN43/DL43 -> 0.50384986 | DS43: =SUM(DO43:DP43)/DL43 -> 0.42396535 | DT43: =SUM(DL43,DD43) -> 4183 | DU43: =SUM(DM43,DE43) -> 345 | DV43: =SUM(DN43,DF43) -> 1996 | DW43: =SUM(DO43,DG43) -> 1257 | DX43: =SUM(DP43,DH43) -> 585 | DY43: =DU43/DT43 -> 0.082476691 | DZ43: =DV43/DT43 -> 0.4771695 | EA43: =SUM(DW43:DX43)/DT43 -> 0.44035381 | EB43: 2802 | EC43: 229 | ED43: =EC43/$EB43 -> 0.081727338 | EE43: 462 | EF43: =EE43/$EB43 -> 0.16488223 | EG43: 939 | EH43: =EG43/$EB43 -> 0.33511777 | EI43: 1309 | EJ43: =EI43/$EB43 -> 0.46716631 | EK43: 1994 | EL43: =EK43/$EB43 -> 0.71163455 | EM43: 2381 | EN43: =EM43/$EB43 -> 0.84975018 | EO43: 65681 | EP43: 65000 | EQ43: 84239 | ER43: 77881 | ES43: 53607 | ET43: 2079 | EU43: 185 | EV43: =EU43/ET43 -> 0.088985089 | EW43: 2061 | EX43: 217 | EY43: =EX43/EW43 -> 0.10528869 | EZ43: =SUM(ET43,EW43) -> 4140 | FA43: =SUM(EU43,EX43) -> 402 | FB43: =FA43/EZ43 -> 0.097101449 | FC43: 4140 | FD43: 402 | FE43: =FD43/$FC43 -> 0.097101449 | FF43: 680 | FG43: =FF43/$FC43 -> 0.16425121 | FH43: 1011 | FI43: =FH43/$FC43 -> 0.2442029 | FJ43: 1224 | FK43: =FJ43/$FC43 -> 0.29565217 | FL43: 1991 | FM43: =FL43/$FC43 -> 0.48091787 | FN43: 240 | FO43: 0.17582418 | FP43: 3 | FQ43: 0.0021978022 | FR43: 53 | FS43: 0.071621622 | FT43: 0 | FU43: 0 | FV43: 227 | FW43: 0.18145484 | FX43: 7 | FY43: 0.0055955236 | FZ43: 26 | GA43: 0.031438936 | GB43: 0 | GC43: 0 | GD43: 546 | GE43: 0.13052833 | GF43: 10 | GG43: 0.0023906287 | GH43: 2802 | GI43: 412 | GJ43: =GI43/GH43 -> 0.14703783 | GK43: 187 | GL43: =GK43/GI43 -> 0.4538835 | GM43: 168 | GN43: =GM43/GI43 -> 0.40776699 | GO43: 2390 | GP43: =GO43/GH43 -> 0.85296217 | GQ43: 1797 | GR43: =GQ43/GO43 -> 0.75188285 | GS43: 578 | GT43: =GS43/GO43 -> 0.241841
A44: Menominee | B44: 4252 | C44: 1007 | D44: 713 | E44: 232 | F44: 100 | G44: =C44/B44 -> 0.23682973 | H44: =D44/B44 -> 0.16768579 | I44: =E44/B44 -> 0.054562559 | J44: =F44/B44 -> 0.023518344 | K44: 352 | L44: =K44/D44 -> 0.49368864 | M44: 361 | N44: =M44/D44 -> 0.50631136 | O44: 34.3 | P44: 1405 | Q44: 675 | R44: =Q44/P44 -> 0.48042705 | S44: 518 | T44: =S44/P44 -> 0.36868327 | U44: 352 | V44: 16 | W44: =V44/U44 -> 0.045454545 | X44: 270 | Y44: =X44/U44 -> 0.76704545 | Z44: 3 | AA44: =Z44/U44 -> 0.0085227273 | AB44: 44 | AC44: =AB44/U44 -> 0.125 | AD44: 19 | AE44: =AD44/U44 -> 0.053977273 | AF44: 361 | AG44: 22 | AH44: =AG44/AF44 -> 0.060941828 | AI44: 141 | AJ44: =AI44/AF44 -> 0.39058172 | AK44: 4 | AL44: =AK44/AF44 -> 0.011080332 | AM44: 129 | AN44: =AM44/AF44 -> 0.35734072 | AO44: 65 | AP44: =AO44/AF44 -> 0.1800554 | AQ44: =SUM(U44,AF44) -> 713 | AR44: =SUM(V44,AG44) -> 38 | AS44: =AR44/AQ44 -> 0.053295933 | AT44: =SUM(X44,AI44) -> 411 | AU44: =AT44/AQ44 -> 0.57643759 | AV44: =SUM(Z44,AK44) -> 7 | AW44: =AV44/AQ44 -> 0.0098176718 | AX44: =SUM(AB44,AM44) -> 173 | AY44: =AX44/AQ44 -> 0.24263675 | AZ44: =SUM(AD44,AO44) -> 84 | BA44: =AZ44/AQ44 -> 0.11781206 | BB44: 352 | BC44: 138 | BD44: =BC44/BB44 -> 0.39204545 | BE44: 361 | BF44: 159 | BG44: =BF44/BE44 -> 0.44044321 | BH44: =SUM(BB44,BE44) -> 713 | BI44: =SUM(BC44,BF44) -> 297 | BJ44: =BI44/BH44 -> 0.41654979 | BK44: 713 | BL44: 118 | BM44: =BL44/BK44 -> 0.1654979 | BN44: 352 | BO44: 36 | BP44: =BO44/BN44 -> 0.10227273 | BQ44: 361 | BR44: 82 | BS44: =BR44/BQ44 -> 0.22714681 | BT44: 4286 | BU44: 735 | BV44: =BU44/BT44 -> 0.17148857 | BW44: =BU44/$BU44 -> 1 | BX44: 644 | BY44: 249 | BZ44: =BY44/BX44 -> 0.38664596 | CA44: =BY44/$BU44 -> 0.33877551 | CB44: 44 | CC44: 6 | CD44: =CC44/CB44 -> 0.13636364 | CE44: =CC44/$BU44 -> 0.0081632653 | CF44: 3180 | CG44: 447 | CH44: =CG44/CF44 -> 0.14056604 | CI44: =CG44/$BU44 -> 0.60816327 | CJ44: 71 | CK44: 11 | CL44: =CK44/CJ44 -> 0.15492958 | CM44: =CK44/$BU44 -> 0.014965986 | CN44: 1 | CO44: 1 | CP44: 0 | CQ44: =CO44/$BU44 -> 0.0013605442 | CR44: 7 | CS44: 0 | CT44: =CS44/CR44 -> 0 | CU44: =CS44/$BU44 -> 0 | CV44: 130 | CW44: 14 | CX44: =CW44/CV44 -> 0.10769231 | CY44: =CW44/$BU44 -> 0.019047619 | CZ44: 216 | DA44: 7 | DB44: =DA44/CZ44 -> 0.032407407 | DC44: =DA44/BU44 -> 0.0095238095 | DD44: 352 | DE44: 40 | DF44: 184 | DG44: 69 | DH44: 59 | DI44: =DE44/DD44 -> 0.11363636 | DJ44: =DF44/DD44 -> 0.52272727 | DK44: =SUM(DG44:DH44)/DD44 -> 0.36363636 | DL44: 361 | DM44: 24 | DN44: 171 | DO44: 94 | DP44: 72 | DQ44: =DM44/DL44 -> 0.066481994 | DR44: =DN44/DL44 -> 0.47368421 | DS44: =SUM(DO44:DP44)/DL44 -> 0.4598338 | DT44: =SUM(DL44,DD44) -> 713 | DU44: =SUM(DM44,DE44) -> 64 | DV44: =SUM(DN44,DF44) -> 355 | DW44: =SUM(DO44,DG44) -> 163 | DX44: =SUM(DP44,DH44) -> 131 | DY44: =DU44/DT44 -> 0.089761571 | DZ44: =DV44/DT44 -> 0.49789621 | EA44: =SUM(DW44:DX44)/DT44 -> 0.41234222 | EB44: 439 | EC44: 28 | ED44: =EC44/$EB44 -> 0.063781321 | EE44: 78 | EF44: =EE44/$EB44 -> 0.17767654 | EG44: 117 | EH44: =EG44/$EB44 -> 0.26651481 | EI44: 197 | EJ44: =EI44/$EB44 -> 0.44874715 | EK44: 277 | EL44: =EK44/$EB44 -> 0.6309795 | EM44: 352 | EN44: =EM44/$EB44 -> 0.80182232 | EO44: 62108 | EP44: - | EQ44: 60737 | ER44: 66743 | ES44: 61488 | ET44: 352 | EU44: 31 | EV44: =EU44/ET44 -> 0.088068182 | EW44: 361 | EX44: 41 | EY44: =EX44/EW44 -> 0.11357341 | EZ44: =SUM(ET44,EW44) -> 713 | FA44: =SUM(EU44,EX44) -> 72 | FB44: =FA44/EZ44 -> 0.10098177 | FC44: 713 | FD44: 72 | FE44: =FD44/$FC44 -> 0.10098177 | FF44: 126 | FG44: =FF44/$FC44 -> 0.17671809 | FH44: 199 | FI44: =FH44/$FC44 -> 0.27910238 | FJ44: 213 | FK44: =FJ44/$FC44 -> 0.29873773 | FL44: 355 | FM44: =FL44/$FC44 -> 0.49789621 | FN44: 30 | FO44: 0.12448133 | FP44: 3 | FQ44: 0.012448133 | FR44: 0 | FS44: 0 | FT44: 0 | FU44: 0 | FV44: 52 | FW44: 0.21666667 | FX44: 0 | FY44: 0 | FZ44: 7 | GA44: 0.05785124 | GB44: 0 | GC44: 0 | GD44: 89 | GE44: 0.12482468 | GF44: 3 | GG44: 0.0042075736 | GH44: 439 | GI44: 29 | GJ44: =GI44/GH44 -> 0.066059226 | GK44: 23 | GL44: =GK44/GI44 -> 0.79310345 | GM44: 3 | GN44: =GM44/GI44 -> 0.10344828 | GO44: 410 | GP44: =GO44/GH44 -> 0.93394077 | GQ44: 300 | GR44: =GQ44/GO44 -> 0.73170732 | GS44: 103 | GT44: =GS44/GO44 -> 0.25121951
A45: Milwaukee | B45: 926331 | C45: 188772 | D45: 136581 | E45: 52823 | F45: 16713 | G45: =C45/B45 -> 0.20378461 | H45: =D45/B45 -> 0.14744298 | I45: =E45/B45 -> 0.057023893 | J45: =F45/B45 -> 0.018042147 | K45: 59899 | L45: =K45/D45 -> 0.43856027 | M45: 76682 | N45: =M45/D45 -> 0.56143973 | O45: 35.5 | P45: 392399 | Q45: 137576 | R45: =Q45/P45 -> 0.35060232 | S45: 102663 | T45: =S45/P45 -> 0.26162911 | U45: 59899 | V45: 8811 | W45: =V45/U45 -> 0.14709761 | X45: 32763 | Y45: =X45/U45 -> 0.54697073 | Z45: 2528 | AA45: =Z45/U45 -> 0.042204377 | AB45: 5858 | AC45: =AB45/U45 -> 0.09779796 | AD45: 9939 | AE45: =AD45/U45 -> 0.16592931 | AF45: 76682 | AG45: 10817 | AH45: =AG45/AF45 -> 0.14106309 | AI45: 25857 | AJ45: =AI45/AF45 -> 0.33719778 | AK45: 2792 | AL45: =AK45/AF45 -> 0.036410109 | AM45: 21770 | AN45: =AM45/AF45 -> 0.28389974 | AO45: 15446 | AP45: =AO45/AF45 -> 0.20142928 | AQ45: =SUM(U45,AF45) -> 136581 | AR45: =SUM(V45,AG45) -> 19628 | AS45: =AR45/AQ45 -> 0.14370959 | AT45: =SUM(X45,AI45) -> 58620 | AU45: =AT45/AQ45 -> 0.42919586 | AV45: =SUM(Z45,AK45) -> 5320 | AW45: =AV45/AQ45 -> 0.038951245 | AX45: =SUM(AB45,AM45) -> 27628 | AY45: =AX45/AQ45 -> 0.20228289 | AZ45: =SUM(AD45,AO45) -> 25385 | BA45: =AZ45/AQ45 -> 0.18586041 | BB45: 58995 | BC45: 18258 | BD45: =BC45/BB45 -> 0.30948385 | BE45: 74256 | BF45: 25248 | BG45: =BF45/BE45 -> 0.34001293 | BH45: =SUM(BB45,BE45) -> 133251 | BI45: =SUM(BC45,BF45) -> 43506 | BJ45: =BI45/BH45 -> 0.32649661 | BK45: 136581 | BL45: 50520 | BM45: =BL45/BK45 -> 0.36989039 | BN45: 59899 | BO45: 17556 | BP45: =BO45/BN45 -> 0.29309337 | BQ45: 76682 | BR45: 32964 | BS45: =BR45/BQ45 -> 0.42987924 | BT45: 924740 | BU45: 142694 | BV45: =BU45/BT45 -> 0.15430716 | BW45: =BU45/$BU45 -> 1 | BX45: 442752 | BY45: 100834 | BZ45: =BY45/BX45 -> 0.22774375 | CA45: =BY45/$BU45 -> 0.70664499 | CB45: 237763 | CC45: 26869 | CD45: =CC45/CB45 -> 0.11300749 | CE45: =CC45/$BU45 -> 0.18829804 | CF45: 4861 | CG45: 602 | CH45: =CG45/CF45 -> 0.12384283 | CI45: =CG45/$BU45 -> 0.0042188179 | CJ45: 52010 | CK45: 3399 | CL45: =CK45/CJ45 -> 0.065352817 | CM45: =CK45/$BU45 -> 0.023820203 | CN45: 164 | CO45: 22 | CP45: =CO45/CN45 -> 0.13414634 | CQ45: =CO45/$BU45 -> 0.00015417607 | CR45: 39015 | CS45: 1170 | CT45: =CS45/CR45 -> 0.029988466 | CU45: =CS45/$BU45 -> 0.0081993637 | CV45: 24616 | CW45: 834 | CX45: =CW45/CV45 -> 0.033880403 | CY45: =CW45/$BU45 -> 0.0058446746 | CZ45: 162574 | DA45: 10134 | DB45: =DA45/CZ45 -> 0.062334691 | DC45: =DA45/BU45 -> 0.071019104 | DD45: 59899 | DE45: 6722 | DF45: 17615 | DG45: 16866 | DH45: 18696 | DI45: =DE45/DD45 -> 0.11222224 | DJ45: =DF45/DD45 -> 0.29407837 | DK45: =SUM(DG45:DH45)/DD45 -> 0.59369939 | DL45: 76682 | DM45: 9148 | DN45: 26471 | DO45: 19674 | DP45: 21389 | DQ45: =DM45/DL45 -> 0.11929788 | DR45: =DN45/DL45 -> 0.34520487 | DS45: =SUM(DO45:DP45)/DL45 -> 0.53549725 | DT45: =SUM(DL45,DD45) -> 136581 | DU45: =SUM(DM45,DE45) -> 15870 | DV45: =SUM(DN45,DF45) -> 44086 | DW45: =SUM(DO45,DG45) -> 36540 | DX45: =SUM(DP45,DH45) -> 40085 | DY45: =DU45/DT45 -> 0.11619479 | DZ45: =DV45/DT45 -> 0.32278282 | EA45: =SUM(DW45:DX45)/DT45 -> 0.5610224 | EB45: 91892 | EC45: 12703 | ED45: =EC45/$EB45 -> 0.13823837 | EE45: 23217 | EF45: =EE45/$EB45 -> 0.25265529 | EG45: 34721 | EH45: =EG45/$EB45 -> 0.37784573 | EI45: 46761 | EJ45: =EI45/$EB45 -> 0.50886911 | EK45: 63124 | EL45: =EK45/$EB45 -> 0.68693684 | EM45: 73909 | EN45: =EM45/$EB45 -> 0.80430288 | EO45: 64435 | EP45: 36115 | EQ45: 72589 | ER45: 74562 | ES45: 48974 | ET45: 58995 | EU45: 8080 | EV45: =EU45/ET45 -> 0.13696076 | EW45: 74256 | EX45: 11281 | EY45: =EX45/EW45 -> 0.15192038 | EZ45: =SUM(ET45,EW45) -> 133251 | FA45: =SUM(EU45,EX45) -> 19361 | FB45: =FA45/EZ45 -> 0.14529722 | FC45: 133251 | FD45: 19361 | FE45: =FD45/$FC45 -> 0.14529722 | FF45: 30519 | FG45: =FF45/$FC45 -> 0.22903393 | FH45: 38953 | FI45: =FH45/$FC45 -> 0.29232801 | FJ45: 44062 | FK45: =FJ45/$FC45 -> 0.33066919 | FL45: 65977 | FM45: =FL45/$FC45 -> 0.49513324 | FN45: 10213 | FO45: 0.26211375 | FP45: 349 | FQ45: 0.0089569859 | FR45: 1879 | FS45: 0.089754 | FT45: 18 | FU45: 0.00085980416 | FV45: 9376 | FW45: 0.20931375 | FX45: 257 | FY45: 0.0057373755 | FZ45: 1243 | GA45: 0.038980181 | GB45: 51 | GC45: 0.0015993477 | GD45: 22711 | GE45: 0.16628228 | GF45: 675 | GG45: 0.0049421223 | GH45: 91892 | GI45: 33839 | GJ45: =GI45/GH45 -> 0.36824751 | GK45: 11979 | GL45: =GK45/GI45 -> 0.35399982 | GM45: 19996 | GN45: =GM45/GI45 -> 0.59091581 | GO45: 58053 | GP45: =GO45/GH45 -> 0.63175249 | GQ45: 40367 | GR45: =GQ45/GO45 -> 0.69534736 | GS45: 16967 | GT45: =GS45/GO45 -> 0.29226741
